Workbook

Sheet Formular 4 step Y1
D1: 46113
D2: BKK | E2: CM | F2: CR | G2: PL | H2: NS | I2: KK | J2: SK | K2: UD | L2: UB | M2: NR | N2: RB | O2: PC | P2: BS | Q2: AY | R2: RY | S2: CB | T2: SR | U2: PK | V2: HY | W2: SB
A3: Y01010100109120240 | B3: STD 9 mm. | C3: Price List | D3: 238 | E3: 238 | F3: 238 | G3: 238 | H3: 238 | I3: 238 | J3: 238 | K3: 238 | L3: 238 | M3: 238 | N3: 238 | O3: 238 | P3: 238 | Q3: 238 | R3: 238 | S3: 238 | T3: 238 | U3: 238 | V3: 238 | W3: 238
A4: Y01010200109120240 | B4: Discount | D4: 0.03 | E4: 0.025 | F4: 0.025 | G4: 0.025 | H4: 0.025 | I4: 0.03 | J4: 0.03 | K4: 0.03 | L4: 0.03 | M4: 0.03 | N4: 0.04 | O4: 0.04 | P4: 0.04 | Q4: 0.04 | R4: 0.04 | S4: 0.04 | T4: 0.04 | U4: 0.04 | V4: 0.04 | W4: 0.04
D5: =D3*(1-D4) -> 230.86 | E5: =E3*(1-E4) -> 232.05 | F5: =F3*(1-F4) -> 232.05 | G5: =G3*(1-G4) -> 232.05 | H5: =H3*(1-H4) -> 232.05 | I5: =I3*(1-I4) -> 230.86 | J5: =J3*(1-J4) -> 230.86 | K5: =K3*(1-K4) -> 230.86 | ... W5: =W3*(1-W4) -> 228.48
B6: Discount | C6: 0 | D6: =D5*$C6 -> 0 | E6: =E5*$C6 -> 0 | F6: =F5*$C6 -> 0 | G6: =G5*$C6 -> 0 | H6: =H5*$C6 -> 0 | I6: =I5*$C6 -> 0 | J6: =J5*$C6 -> 0 | K6: =K5*$C6 -> 0 | ... W6: =W5*$C6 -> 0
B7: RE (ex VAT) | D7: =D5-D6 -> 230.86 | E7: =E5-E6 -> 232.05 | F7: =F5-F6 -> 232.05 | G7: =G5-G6 -> 232.05 | H7: =H5-H6 -> 232.05 | I7: =I5-I6 -> 230.86 | J7: =J5-J6 -> 230.86 | K7: =K5-K6 -> 230.86 | ... W7: =W5-W6 -> 228.48
B8: VAT | C8: 0.07 | D8: =D7*$C8 -> 16.1602 | E8: =E7*$C8 -> 16.2435 | F8: =F7*$C8 -> 16.2435 | G8: =G7*$C8 -> 16.2435 | H8: =H7*$C8 -> 16.2435 | I8: =I7*$C8 -> 16.1602 | J8: =J7*$C8 -> 16.1602 | K8: =K7*$C8 -> 16.1602 | ... W8: =W7*$C8 -> 15.9936
B9: Net Price (inc VAT) | D9: =D7+D8 -> 247.0202 | E9: =E7+E8 -> 248.2935 | F9: =F7+F8 -> 248.2935 | G9: =G7+G8 -> 248.2935 | H9: =H7+H8 -> 248.2935 | I9: =I7+I8 -> 247.0202 | J9: =J7+J8 -> 247.0202 | K9: =K7+K8 -> 247.0202 | ... W9: =W7+W8 -> 244.4736
B10: Transportation
B11: COGS | D11: =SUM(D9:D10) -> 247.0202 | E11: =SUM(E9:E10) -> 248.2935 | F11: =SUM(F9:F10) -> 248.2935 | G11: =SUM(G9:G10) -> 248.2935 | H11: =SUM(H9:H10) -> 248.2935 | I11: =SUM(I9:I10) -> 247.0202 | J11: =SUM(J9:J10) -> 247.0202 | K11: =SUM(K9:K10) -> 247.0202 | ... W11: =SUM(W9:W10) -> 244.4736
B12: Promotion Rebate
B13: Net Cost | D13: =D11 -> 247.0202 | E13: =E11 -> 248.2935 | F13: =F11 -> 248.2935 | G13: =G11 -> 248.2935 | H13: =H11 -> 248.2935 | I13: =I11 -> 247.0202 | J13: =J11 -> 247.0202 | K13: =K11 -> 247.0202 | ... W13: =W11 -> 244.4736
B14: Price : W1 | D14: 124 | E14: 136 | F14: 139 | G14: 134 | H14: 129 | I14: 134 | J14: 138 | K14: 136 | L14: 137 | M14: 132 | N14: 124 | O14: 124 | P14: 124 | Q14: 124 | R14: 124 | S14: 124 | T14: 126 | U14: 129 | V14: 120 | W14: 124
B15: Price : W2 | D15: 125 | E15: 137 | F15: 140 | G15: 135 | H15: 130 | I15: 135 | J15: 139 | K15: 137 | L15: 138 | M15: 133 | N15: 125 | O15: 125 | P15: 125 | Q15: 125 | R15: 125 | S15: 125 | T15: 127 | U15: 130 | V15: 121 | W15: 125
B16: Price : R1 | D16: 126 | E16: 138 | F16: 141 | G16: 136 | H16: 131 | I16: 136 | J16: 140 | K16: 138 | L16: 139 | M16: 134 | N16: 126 | O16: 126 | P16: 126 | Q16: 126 | R16: 126 | S16: 126 | T16: 128 | U16: 131 | V16: 122 | W16: 126
B17: Price : R2 | D17: 127 | E17: 139 | F17: 142 | G17: 137 | H17: 132 | I17: 137 | J17: 141 | K17: 139 | L17: 140 | M17: 135 | N17: 127 | O17: 127 | P17: 127 | Q17: 127 | R17: 127 | S17: 127 | T17: 129 | U17: 132 | V17: 123 | W17: 127
B18: MG/Bht : W1 | D18: =+D14-D13 -> -123.0202 | E18: =+E14-E13 -> -112.2935 | F18: =+F14-F13 -> -109.2935 | G18: =+G14-G13 -> -114.2935 | H18: =+H14-H13 -> -119.2935 | I18: =+I14-I13 -> -113.0202 | J18: =+J14-J13 -> -109.0202 | K18: =+K14-K13 -> -111.0202 | ... W18: =+W14-W13 -> -120.4736
B19: MG/Bht : W2 | D19: =+D15-D$13 -> -122.0202 | E19: =+E15-E$13 -> -111.2935 | F19: =+F15-F$13 -> -108.2935 | G19: =+G15-G$13 -> -113.2935 | H19: =+H15-H$13 -> -118.2935 | I19: =+I15-I$13 -> -112.0202 | J19: =+J15-J$13 -> -108.0202 | K19: =+K15-K$13 -> -110.0202 | ... W19: =+W15-W$13 -> -119.4736
B20: MG/Bht : R1 | D20: =+D16-D$13 -> -121.0202 | E20: =+E16-E$13 -> -110.2935 | F20: =+F16-F$13 -> -107.2935 | G20: =+G16-G$13 -> -112.2935 | H20: =+H16-H$13 -> -117.2935 | I20: =+I16-I$13 -> -111.0202 | J20: =+J16-J$13 -> -107.0202 | K20: =+K16-K$13 -> -109.0202 | ... W20: =+W16-W$13 -> -118.4736
B21: MG/Bht : R2 | D21: =+D17-D$13 -> -120.0202 | E21: =+E17-E$13 -> -109.2935 | F21: =+F17-F$13 -> -106.2935 | G21: =+G17-G$13 -> -111.2935 | H21: =+H17-H$13 -> -116.2935 | I21: =+I17-I$13 -> -110.0202 | J21: =+J17-J$13 -> -106.0202 | K21: =+K17-K$13 -> -108.0202 | ... W21: =+W17-W$13 -> -117.4736
B22: MG/% : W1 | D22: =+D18/D14 -> -0.99209839 | E22: =+E18/E14 -> -0.8256875 | F22: =+F18/F14 -> -0.78628417 | G22: =+G18/G14 -> -0.85293657 | H22: =+H18/H14 -> -0.92475581 | I22: =+I18/I14 -> -0.84343433 | J22: =+J18/J14 -> -0.79000145 | K22: =+K18/K14 -> -0.816325 | ... W22: =+W18/W14 -> -0.97156129
B23: MG/% : W2 | D23: =+D19/D15 -> -0.9761616 | E23: =+E19/E15 -> -0.81236131 | F23: =+F19/F15 -> -0.773525 | G23: =+G19/G15 -> -0.83921111 | H23: =+H19/H15 -> -0.90995 | I23: =+I19/I15 -> -0.82977926 | J23: =+J19/J15 -> -0.77712374 | K23: =+K19/K15 -> -0.80306715 | ... W23: =+W19/W15 -> -0.9557888
B24: MG/% : R1 | D24: =+D20/D16 -> -0.96047778 | E24: =+E20/E16 -> -0.79922826 | F24: =+F20/F16 -> -0.76094681 | G24: =+G20/G16 -> -0.8256875 | H24: =+H20/H16 -> -0.89537023 | I24: =+I20/I16 -> -0.816325 | J24: =+J20/J16 -> -0.76443 | K24: =+K20/K16 -> -0.79000145 | ... W24: =+W20/W16 -> -0.94026667
B25: MG/% : R2 | D25: =+D21/D17 -> -0.94504094 | E25: =+E21/E17 -> -0.78628417 | F25: =+F21/F17 -> -0.74854577 | G25: =+G21/G17 -> -0.81236131 | H25: =+H21/H17 -> -0.88101136 | I25: =+I21/I17 -> -0.80306715 | J25: =+J21/J17 -> -0.75191631 | K25: =+K21/K17 -> -0.77712374 | ... W25: =+W21/W17 -> -0.92498898
A27: Y01010700109120240 | B27: SYNIA 9 mm. | D27: BKK | E27: CM | F27: CR | G27: PL | H27: NS | I27: KK | J27: SK | K27: UD | L27: UB | M27: NR | N27: RB | O27: PC | P27: BS | Q27: AY | R27: RY | S27: CB | T27: SR | U27: PK | V27: HY | W27: SB
B28: Price List | D28: 274 | E28: =D28 -> 274 | F28: =D28 -> 274 | G28: =D28 -> 274 | H28: =E28 -> 274 | I28: =D28 -> 274 | J28: =D28 -> 274 | K28: =D28 -> 274 | L28: =D28 -> 274 | M28: =D28 -> 274 | N28: =D28 -> 274 | O28: =D28 -> 274 | P28: =D28 -> 274 | Q28: =D28 -> 274 | R28: =D28 -> 274 | S28: =D28 -> 274 | T28: =D28 -> 274 | U28: =D28 -> 274 | V28: =D28 -> 274 | W28: =H28 -> 274
B29: Discount | D29: 0.04 | E29: 0.04 | F29: 0.04 | G29: 0.04 | H29: 0.04 | I29: 0.04 | J29: 0.04 | K29: 0.04 | L29: 0.04 | M29: 0.04 | N29: 0.04 | O29: 0.04 | P29: 0.04 | Q29: 0.04 | R29: 0.04 | S29: 0.04 | T29: 0.04 | U29: 0.04 | V29: 0.04 | W29: 0.04
D30: =D28*(1-D29) -> 263.04 | E30: =E28*(1-E29) -> 263.04 | F30: =F28*(1-F29) -> 263.04 | G30: =G28*(1-G29) -> 263.04 | H30: =H28*(1-H29) -> 263.04 | I30: =I28*(1-I29) -> 263.04 | J30: =J28*(1-J29) -> 263.04 | K30: =K28*(1-K29) -> 263.04 | ... W30: =W28*(1-W29) -> 263.04
B31: Discount | C31: 0 | D31: =D30*$C31 -> 0 | E31: =E30*$C31 -> 0 | F31: =F30*$C31 -> 0 | G31: =G30*$C31 -> 0 | H31: =H30*$C31 -> 0 | I31: =I30*$C31 -> 0 | J31: =J30*$C31 -> 0 | K31: =K30*$C31 -> 0 | ... W31: =W30*$C31 -> 0
B32: RE (ex VAT) | D32: =D30-D31 -> 263.04 | E32: =E30-E31 -> 263.04 | F32: =F30-F31 -> 263.04 | G32: =G30-G31 -> 263.04 | H32: =H30-H31 -> 263.04 | I32: =I30-I31 -> 263.04 | J32: =J30-J31 -> 263.04 | K32: =K30-K31 -> 263.04 | ... W32: =W30-W31 -> 263.04
B33: VAT | C33: 0.07 | D33: =D32*$C33 -> 18.4128 | E33: =E32*$C33 -> 18.4128 | F33: =F32*$C33 -> 18.4128 | G33: =G32*$C33 -> 18.4128 | H33: =H32*$C33 -> 18.4128 | I33: =I32*$C33 -> 18.4128 | J33: =J32*$C33 -> 18.4128 | K33: =K32*$C33 -> 18.4128 | ... W33: =W32*$C33 -> 18.4128
B34: Net Price (inc VAT) | D34: =D32+D33 -> 281.4528 | E34: =E32+E33 -> 281.4528 | F34: =F32+F33 -> 281.4528 | G34: =G32+G33 -> 281.4528 | H34: =H32+H33 -> 281.4528 | I34: =I32+I33 -> 281.4528 | J34: =J32+J33 -> 281.4528 | K34: =K32+K33 -> 281.4528 | ... W34: =W32+W33 -> 281.4528
B35: Transportation
B36: COGS | D36: =SUM(D34:D35) -> 281.4528 | E36: =SUM(E34:E35) -> 281.4528 | F36: =SUM(F34:F35) -> 281.4528 | G36: =SUM(G34:G35) -> 281.4528 | H36: =SUM(H34:H35) -> 281.4528 | I36: =SUM(I34:I35) -> 281.4528 | J36: =SUM(J34:J35) -> 281.4528 | K36: =SUM(K34:K35) -> 281.4528 | ... W36: =SUM(W34:W35) -> 281.4528
B37: Promotion Rebate
B38: Net Cost | D38: =D36 -> 281.4528 | E38: =E36 -> 281.4528 | F38: =F36 -> 281.4528 | G38: =G36 -> 281.4528 | H38: =H36 -> 281.4528 | I38: =I36 -> 281.4528 | J38: =J36 -> 281.4528 | K38: =K36 -> 281.4528 | ... W38: =W36 -> 281.4528
B39: Price : W1 | D39: 124 | E39: 139 | F39: 141 | G39: 136 | H39: 132 | I39: 133 | J39: 137 | K39: 135 | L39: 137 | M39: 131 | N39: 124 | O39: 124 | P39: 124 | Q39: 124 | R39: 124 | S39: 124 | T39: 128 | U39: 131 | V39: 123 | W39: 124
B40: Price : W2 | D40: 125 | E40: 140 | F40: 142 | G40: 137 | H40: 133 | I40: 134 | J40: 138 | K40: 136 | L40: 138 | M40: 132 | N40: 125 | O40: 125 | P40: 125 | Q40: 125 | R40: 125 | S40: 125 | T40: 129 | U40: 132 | V40: 124 | W40: 125
B41: Price : R1 | D41: 126 | E41: 141 | F41: 143 | G41: 138 | H41: 134 | I41: 135 | J41: 139 | K41: 137 | L41: 139 | M41: 133 | N41: 126 | O41: 126 | P41: 126 | Q41: 126 | R41: 126 | S41: 126 | T41: 130 | U41: 133 | V41: 125 | W41: 126
B42: Price : R2 | D42: 127 | E42: 142 | F42: 144 | G42: 139 | H42: 135 | I42: 136 | J42: 140 | K42: 138 | L42: 140 | M42: 134 | N42: 127 | O42: 127 | P42: 127 | Q42: 127 | R42: 127 | S42: 127 | T42: 131 | U42: 134 | V42: 126 | W42: 127
B43: MG/Bht : W1 | D43: =+D39-D$38 -> -157.4528 | E43: =+E39-E$38 -> -142.4528 | F43: =+F39-F$38 -> -140.4528 | G43: =+G39-G$38 -> -145.4528 | H43: =+H39-H$38 -> -149.4528 | I43: =+I39-I$38 -> -148.4528 | J43: =+J39-J$38 -> -144.4528 | K43: =+K39-K$38 -> -146.4528 | ... W43: =+W39-W$38 -> -157.4528
B44: MG/Bht : W2 | D44: =+D40-D$38 -> -156.4528 | E44: =+E40-E$38 -> -141.4528 | F44: =+F40-F$38 -> -139.4528 | G44: =+G40-G$38 -> -144.4528 | H44: =+H40-H$38 -> -148.4528 | I44: =+I40-I$38 -> -147.4528 | J44: =+J40-J$38 -> -143.4528 | K44: =+K40-K$38 -> -145.4528 | ... W44: =+W40-W$38 -> -156.4528
B45: MG/Bht : R1 | D45: =+D41-D$38 -> -155.4528 | E45: =+E41-E$38 -> -140.4528 | F45: =+F41-F$38 -> -138.4528 | G45: =+G41-G$38 -> -143.4528 | H45: =+H41-H$38 -> -147.4528 | I45: =+I41-I$38 -> -146.4528 | J45: =+J41-J$38 -> -142.4528 | K45: =+K41-K$38 -> -144.4528 | ... W45: =+W41-W$38 -> -155.4528
B46: MG/Bht : R2 | D46: =+D42-D$38 -> -154.4528 | E46: =+E42-E$38 -> -139.4528 | F46: =+F42-F$38 -> -137.4528 | G46: =+G42-G$38 -> -142.4528 | H46: =+H42-H$38 -> -146.4528 | I46: =+I42-I$38 -> -145.4528 | J46: =+J42-J$38 -> -141.4528 | K46: =+K42-K$38 -> -143.4528 | ... W46: =+W42-W$38 -> -154.4528
B47: MG/% : W1 | D47: =+D43/D39 -> -1.2697806 | E47: =+E43/E39 -> -1.0248403 | F47: =+F43/F39 -> -0.99611915 | G47: =+G43/G39 -> -1.0695059 | H47: =+H43/H39 -> -1.1322182 | I47: =+I43/I39 -> -1.1161865 | J47: =+J43/J39 -> -1.0544 | K47: =+K43/K39 -> -1.0848356 | ... W47: =+W43/W39 -> -1.2697806
B48: MG/% : W2 | D48: =+D44/D40 -> -1.2516224 | E48: =+E44/E40 -> -1.0103771 | F48: =+F44/F40 -> -0.98206197 | G48: =+G44/G40 -> -1.0544 | H48: =+H44/H40 -> -1.1161865 | I48: =+I44/I40 -> -1.100394 | J48: =+J44/J40 -> -1.039513 | K48: =+K44/K40 -> -1.0695059 | ... W48: =+W44/W40 -> -1.2516224
B49: MG/% : R1 | D49: =+D45/D41 -> -1.2337524 | E49: =+E45/E41 -> -0.99611915 | F49: =+F45/F41 -> -0.9682014 | G49: =+G45/G41 -> -1.039513 | H49: =+H45/H41 -> -1.100394 | I49: =+I45/I41 -> -1.0848356 | J49: =+J45/J41 -> -1.0248403 | K49: =+K45/K41 -> -1.0544 | ... W49: =+W45/W41 -> -1.2337524
B50: MG/% : R2 | D50: =+D46/D42 -> -1.2161638 | E50: =+E46/E42 -> -0.98206197 | F50: =+F46/F42 -> -0.95453333 | G50: =+G46/G42 -> -1.0248403 | H50: =+H46/H42 -> -1.0848356 | I50: =+I46/I42 -> -1.0695059 | J50: =+J46/J42 -> -1.0103771 | K50: =+K46/K42 -> -1.039513 | ... W50: =+W46/W42 -> -1.2161638
D51: 5
A52: Y01020000109120240 | B52: TEC 9 mm. | D52: BKK | E52: CM | F52: CR | G52: PL | H52: NS | I52: KK | J52: SK | K52: UD | L52: UB | M52: NR | N52: RB | O52: PC | P52: BS | Q52: AY | R52: RY | S52: CB | T52: SR | U52: PK | V52: HY | W52: SB
A53: Y01020300109120240 | B53: Price List | D53: 352 | E53: 352 | F53: 352 | G53: 352 | H53: 352 | I53: 352 | J53: 352 | K53: 352 | L53: 352 | M53: 352 | N53: 352 | O53: 352 | P53: 352 | Q53: 352 | R53: 352 | S53: 352 | T53: 352 | U53: 352 | V53: 352 | W53: 352
A54: Y01020400109120240 | B54: Discount
A55: Y01020500109120240 | D55: =D53*(1-D54) -> 352 | E55: =E53*(1-E54) -> 352 | F55: =F53*(1-F54) -> 352 | G55: =G53*(1-G54) -> 352 | H55: =H53*(1-H54) -> 352 | I55: =I53*(1-I54) -> 352 | J55: =J53*(1-J54) -> 352 | K55: =K53*(1-K54) -> 352 | ... W55: =W53*(1-W54) -> 352
A56: Y01020600109120240 | B56: Discount | C56: 0 | D56: =D55*$C56 -> 0 | E56: =E55*$C56 -> 0 | F56: =F55*$C56 -> 0 | G56: =G55*$C56 -> 0 | H56: =H55*$C56 -> 0 | I56: =I55*$C56 -> 0 | J56: =J55*$C56 -> 0 | K56: =K55*$C56 -> 0 | ... W56: =W55*$C56 -> 0
B57: RE (ex VAT) | D57: =D55-D56 -> 352 | E57: =E55-E56 -> 352 | F57: =F55-F56 -> 352 | G57: =G55-G56 -> 352 | H57: =H55-H56 -> 352 | I57: =I55-I56 -> 352 | J57: =J55-J56 -> 352 | K57: =K55-K56 -> 352 | ... W57: =W55-W56 -> 352
B58: VAT | C58: 0.07 | D58: =D57*$C58 -> 24.64 | E58: =E57*$C58 -> 24.64 | F58: =F57*$C58 -> 24.64 | G58: =G57*$C58 -> 24.64 | H58: =H57*$C58 -> 24.64 | I58: =I57*$C58 -> 24.64 | J58: =J57*$C58 -> 24.64 | K58: =K57*$C58 -> 24.64 | ... W58: =W57*$C58 -> 24.64
B59: Net Price (inc VAT) | D59: =D57+D58 -> 376.64 | E59: =E57+E58 -> 376.64 | F59: =F57+F58 -> 376.64 | G59: =G57+G58 -> 376.64 | H59: =H57+H58 -> 376.64 | I59: =I57+I58 -> 376.64 | J59: =J57+J58 -> 376.64 | K59: =K57+K58 -> 376.64 | ... W59: =W57+W58 -> 376.64
B60: Transportation
B61: COGS | D61: =SUM(D59:D60) -> 376.64 | E61: =SUM(E59:E60) -> 376.64 | F61: =SUM(F59:F60) -> 376.64 | G61: =SUM(G59:G60) -> 376.64 | H61: =SUM(H59:H60) -> 376.64 | I61: =SUM(I59:I60) -> 376.64 | J61: =SUM(J59:J60) -> 376.64 | K61: =SUM(K59:K60) -> 376.64 | ... W61: =SUM(W59:W60) -> 376.64
B62: Promotion Rebate
B63: Net Cost | D63: =D61 -> 376.64 | E63: =E61 -> 376.64 | F63: =F61 -> 376.64 | G63: =G61 -> 376.64 | H63: =H61 -> 376.64 | I63: =I61 -> 376.64 | J63: =J61 -> 376.64 | K63: =K61 -> 376.64 | ... W63: =W61 -> 376.64
B64: Price : W1 | D64: 185 | E64: 202 | F64: 204 | G64: 199 | H64: 195 | I64: 197 | J64: 201 | K64: 199 | L64: 200 | M64: 195 | N64: 185 | O64: 185 | P64: 185 | Q64: 185 | R64: 187 | S64: 187 | T64: 189 | U64: 192 | V64: 184 | W64: 187
B65: Price : W2 | D65: 186 | E65: 203 | F65: 205 | G65: 200 | H65: 196 | I65: 198 | J65: 202 | K65: 200 | L65: 201 | M65: 196 | N65: 186 | O65: 186 | P65: 186 | Q65: 186 | R65: 188 | S65: 188 | T65: 190 | U65: 193 | V65: 185 | W65: 188
B66: Price : R1 | D66: 187 | E66: 204 | F66: 206 | G66: 201 | H66: 197 | I66: 199 | J66: 203 | K66: 201 | L66: 202 | M66: 197 | N66: 187 | O66: 187 | P66: 187 | Q66: 187 | R66: 189 | S66: 189 | T66: 191 | U66: 194 | V66: 186 | W66: 189
B67: Price : R2 | D67: 188 | E67: 205 | F67: 207 | G67: 202 | H67: 198 | I67: 200 | J67: 204 | K67: 202 | L67: 203 | M67: 198 | N67: 188 | O67: 188 | P67: 188 | Q67: 188 | R67: 190 | S67: 190 | T67: 192 | U67: 195 | V67: 187 | W67: 190
B68: MG/Bht : W1 | D68: =+D64-D$63 -> -191.64 | E68: =+E64-E$63 -> -174.64 | F68: =+F64-F$63 -> -172.64 | G68: =+G64-G$63 -> -177.64 | H68: =+H64-H$63 -> -181.64 | I68: =+I64-I$63 -> -179.64 | J68: =+J64-J$63 -> -175.64 | K68: =+K64-K$63 -> -177.64 | ... W68: =+W64-W$63 -> -189.64
B69: MG/Bht : W2 | D69: =+D65-D$63 -> -190.64 | E69: =+E65-E$63 -> -173.64 | F69: =+F65-F$63 -> -171.64 | G69: =+G65-G$63 -> -176.64 | H69: =+H65-H$63 -> -180.64 | I69: =+I65-I$63 -> -178.64 | J69: =+J65-J$63 -> -174.64 | K69: =+K65-K$63 -> -176.64 | ... W69: =+W65-W$63 -> -188.64
B70: MG/Bht : R1 | D70: =+D66-D$63 -> -189.64 | E70: =+E66-E$63 -> -172.64 | F70: =+F66-F$63 -> -170.64 | G70: =+G66-G$63 -> -175.64 | H70: =+H66-H$63 -> -179.64 | I70: =+I66-I$63 -> -177.64 | J70: =+J66-J$63 -> -173.64 | K70: =+K66-K$63 -> -175.64 | ... W70: =+W66-W$63 -> -187.64
B71: MG/Bht : R2 | D71: =+D67-D$63 -> -188.64 | E71: =+E67-E$63 -> -171.64 | F71: =+F67-F$63 -> -169.64 | G71: =+G67-G$63 -> -174.64 | H71: =+H67-H$63 -> -178.64 | I71: =+I67-I$63 -> -176.64 | J71: =+J67-J$63 -> -172.64 | K71: =+K67-K$63 -> -174.64 | ... W71: =+W67-W$63 -> -186.64
B72: MG/% : W1 | D72: =+D68/D64 -> -1.0358919 | E72: =+E68/E64 -> -0.86455446 | F72: =+F68/F64 -> -0.84627451 | G72: =+G68/G64 -> -0.89266332 | H72: =+H68/H64 -> -0.93148718 | I72: =+I68/I64 -> -0.91187817 | J72: =+J68/J64 -> -0.87383085 | K72: =+K68/K64 -> -0.89266332 | ... W72: =+W68/W64 -> -1.0141176
B73: MG/% : W2 | D73: =+D69/D65 -> -1.0249462 | E73: =+E69/E65 -> -0.85536946 | F73: =+F69/F65 -> -0.83726829 | G73: =+G69/G65 -> -0.8832 | H73: =+H69/H65 -> -0.92163265 | I73: =+I69/I65 -> -0.90222222 | J73: =+J69/J65 -> -0.86455446 | K73: =+K69/K65 -> -0.8832 | ... W73: =+W69/W65 -> -1.0034043
B74: MG/% : R1 | D74: =+D70/D66 -> -1.0141176 | E74: =+E70/E66 -> -0.84627451 | F74: =+F70/F66 -> -0.82834951 | G74: =+G70/G66 -> -0.87383085 | H74: =+H70/H66 -> -0.91187817 | I74: =+I70/I66 -> -0.89266332 | J74: =+J70/J66 -> -0.85536946 | K74: =+K70/K66 -> -0.87383085 | ... W74: =+W70/W66 -> -0.99280423
B75: MG/% : R2 | D75: =+D71/D67 -> -1.0034043 | E75: =+E71/E67 -> -0.83726829 | F75: =+F71/F67 -> -0.81951691 | G75: =+G71/G67 -> -0.86455446 | H75: =+H71/H67 -> -0.90222222 | I75: =+I71/I67 -> -0.8832 | J75: =+J71/J67 -> -0.84627451 | K75: =+K71/K67 -> -0.86455446 | ... W75: =+W71/W67 -> -0.98231579
A77: Y01020800109120240 | B77: SYNIA TEC 9 mm. | D77: BKK | E77: CM | F77: CR | G77: PL | H77: NS | I77: KK | J77: SK | K77: UD | L77: UB | M77: NR | N77: RB | O77: PC | P77: BS | Q77: AY | R77: RY | S77: CB | T77: SR | U77: PK | V77: HY | W77: SB
A78: Y01020900109120240 | B78: Price List | D78: 405 | E78: =D78 -> 405 | F78: =D78 -> 405 | G78: =D78 -> 405 | H78: =E78 -> 405 | I78: =D78 -> 405 | J78: =D78 -> 405 | K78: =D78 -> 405 | L78: =D78 -> 405 | M78: =D78 -> 405 | N78: =D78 -> 405 | O78: =D78 -> 405 | P78: =D78 -> 405 | Q78: =D78 -> 405 | R78: =D78 -> 405 | S78: =D78 -> 405 | T78: =D78 -> 405 | U78: =D78 -> 405 | V78: =D78 -> 405 | W78: =H78 -> 405
B79: Discount
D80: =D78*(1-D79) -> 405 | E80: =E78*(1-E79) -> 405 | F80: =F78*(1-F79) -> 405 | G80: =G78*(1-G79) -> 405 | H80: =H78*(1-H79) -> 405 | I80: =I78*(1-I79) -> 405 | J80: =J78*(1-J79) -> 405 | K80: =K78*(1-K79) -> 405 | ... W80: =W78*(1-W79) -> 405
B81: Discount | C81: 0 | D81: =D80*$C81 -> 0 | E81: =E80*$C81 -> 0 | F81: =F80*$C81 -> 0 | G81: =G80*$C81 -> 0 | H81: =H80*$C81 -> 0 | I81: =I80*$C81 -> 0 | J81: =J80*$C81 -> 0 | K81: =K80*$C81 -> 0 | ... W81: =W80*$C81 -> 0
B82: RE (ex VAT) | D82: =D80-D81 -> 405 | E82: =E80-E81 -> 405 | F82: =F80-F81 -> 405 | G82: =G80-G81 -> 405 | H82: =H80-H81 -> 405 | I82: =I80-I81 -> 405 | J82: =J80-J81 -> 405 | K82: =K80-K81 -> 405 | ... W82: =W80-W81 -> 405
B83: VAT | C83: 0.07 | D83: =D82*$C83 -> 28.35 | E83: =E82*$C83 -> 28.35 | F83: =F82*$C83 -> 28.35 | G83: =G82*$C83 -> 28.35 | H83: =H82*$C83 -> 28.35 | I83: =I82*$C83 -> 28.35 | J83: =J82*$C83 -> 28.35 | K83: =K82*$C83 -> 28.35 | ... W83: =W82*$C83 -> 28.35
B84: Net Price (inc VAT) | D84: =((D78*(1-D79))-((D78*(1-D79)*2%)))*1.07 -> 424.683 | E84: =((E78*(1-E79))-((E78*(1-E79)*2%)))*1.07 -> 424.683 | F84: =((F78*(1-F79))-((F78*(1-F79)*2%)))*1.07 -> 424.683 | G84: =((G78*(1-G79))-((G78*(1-G79)*2%)))*1.07 -> 424.683 | H84: =((H78*(1-H79))-((H78*(1-H79)*2%)))*1.07 -> 424.683 | I84: =((I78*(1-I79))-((I78*(1-I79)*2%)))*1.07 -> 424.683 | J84: =((J78*(1-J79))-((J78*(1-J79)*2%)))*1.07 -> 424.683 | K84: =((K78*(1-K79))-((K78*(1-K79)*2%)))*1.07 -> 424.683 | ... W84: =((W78*(1-W79))-((W78*(1-W79)*2%)))*1.07 -> 424.683
B85: Transportation
B86: COGS | D86: =SUM(D84:D85) -> 424.683 | E86: =SUM(E84:E85) -> 424.683 | F86: =SUM(F84:F85) -> 424.683 | G86: =SUM(G84:G85) -> 424.683 | H86: =SUM(H84:H85) -> 424.683 | I86: =SUM(I84:I85) -> 424.683 | J86: =SUM(J84:J85) -> 424.683 | K86: =SUM(K84:K85) -> 424.683 | ... W86: =SUM(W84:W85) -> 424.683
B87: Promotion Rebate
B88: Net Cost | D88: =D86 -> 424.683 | E88: =E86 -> 424.683 | F88: =F86 -> 424.683 | G88: =G86 -> 424.683 | H88: =H86 -> 424.683 | I88: =I86 -> 424.683 | J88: =J86 -> 424.683 | K88: =K86 -> 424.683 | ... W88: =W86 -> 424.683
B89: Price : W1 | D89: 184 | E89: 201 | F89: 203 | G89: 198 | H89: 194 | I89: 195 | J89: 199 | K89: 197 | L89: 199 | M89: 193 | N89: 184 | O89: 184 | P89: 184 | Q89: 184 | R89: 185 | S89: 185 | T89: 190 | U89: 193 | V89: 184 | W89: 185
B90: Price : W2 | D90: 185 | E90: 202 | F90: 204 | G90: 199 | H90: 195 | I90: 196 | J90: 200 | K90: 198 | L90: 200 | M90: 194 | N90: 185 | O90: 185 | P90: 185 | Q90: 185 | R90: 186 | S90: 186 | T90: 191 | U90: 194 | V90: 185 | W90: 186
B91: Price : R1 | D91: 186 | E91: 203 | F91: 205 | G91: 200 | H91: 196 | I91: 197 | J91: 201 | K91: 199 | L91: 201 | M91: 195 | N91: 186 | O91: 186 | P91: 186 | Q91: 186 | R91: 187 | S91: 187 | T91: 192 | U91: 195 | V91: 186 | W91: 187
B92: Price : R2 | D92: 187 | E92: 204 | F92: 206 | G92: 201 | H92: 197 | I92: 198 | J92: 202 | K92: 200 | L92: 202 | M92: 196 | N92: 187 | O92: 187 | P92: 187 | Q92: 187 | R92: 188 | S92: 188 | T92: 193 | U92: 196 | V92: 187 | W92: 188
B93: MG/Bht : W1 | D93: =+D89-D$88 -> -240.683 | E93: =+E89-E$88 -> -223.683 | F93: =+F89-F$88 -> -221.683 | G93: =+G89-G$88 -> -226.683 | H93: =+H89-H$88 -> -230.683 | I93: =+I89-I$88 -> -229.683 | J93: =+J89-J$88 -> -225.683 | K93: =+K89-K$88 -> -227.683 | ... W93: =+W89-W$88 -> -239.683
B94: MG/Bht : W2 | D94: =+D90-D$88 -> -239.683 | E94: =+E90-E$88 -> -222.683 | F94: =+F90-F$88 -> -220.683 | G94: =+G90-G$88 -> -225.683 | H94: =+H90-H$88 -> -229.683 | I94: =+I90-I$88 -> -228.683 | J94: =+J90-J$88 -> -224.683 | K94: =+K90-K$88 -> -226.683 | ... W94: =+W90-W$88 -> -238.683
B95: MG/Bht : R1 | D95: =+D91-D$88 -> -238.683 | E95: =+E91-E$88 -> -221.683 | F95: =+F91-F$88 -> -219.683 | G95: =+G91-G$88 -> -224.683 | H95: =+H91-H$88 -> -228.683 | I95: =+I91-I$88 -> -227.683 | J95: =+J91-J$88 -> -223.683 | K95: =+K91-K$88 -> -225.683 | ... W95: =+W91-W$88 -> -237.683
B96: MG/Bht : R2 | D96: =+D92-D$88 -> -237.683 | E96: =+E92-E$88 -> -220.683 | F96: =+F92-F$88 -> -218.683 | G96: =+G92-G$88 -> -223.683 | H96: =+H92-H$88 -> -227.683 | I96: =+I92-I$88 -> -226.683 | J96: =+J92-J$88 -> -222.683 | K96: =+K92-K$88 -> -224.683 | ... W96: =+W92-W$88 -> -236.683
B97: MG/% : W1 | D97: =+D93/D89 -> -1.3080598 | E97: =+E93/E89 -> -1.1128507 | F97: =+F93/F89 -> -1.0920345 | G97: =+G93/G89 -> -1.1448636 | H97: =+H93/H89 -> -1.1890876 | I97: =+I93/I89 -> -1.1778615 | J97: =+J93/J89 -> -1.1340854 | K97: =+K93/K89 -> -1.1557513 | ... W97: =+W93/W89 -> -1.2955838
B98: MG/% : W2 | D98: =+D94/D90 -> -1.2955838 | E98: =+E94/E90 -> -1.1023911 | F98: =+F94/F90 -> -1.0817794 | G98: =+G94/G90 -> -1.1340854 | H98: =+H94/H90 -> -1.1778615 | I98: =+I94/I90 -> -1.16675 | J98: =+J94/J90 -> -1.123415 | K98: =+K94/K90 -> -1.1448636 | ... W98: =+W94/W90 -> -1.2832419
B99: MG/% : R1 | D99: =+D95/D91 -> -1.2832419 | E99: =+E95/E91 -> -1.0920345 | F99: =+F95/F91 -> -1.0716244 | G99: =+G95/G91 -> -1.123415 | H99: =+H95/H91 -> -1.16675 | I99: =+I95/I91 -> -1.1557513 | J99: =+J95/J91 -> -1.1128507 | K99: =+K95/K91 -> -1.1340854 | ... W99: =+W95/W91 -> -1.2710321
B100: MG/% : R2 | D100: =+D96/D92 -> -1.2710321 | E100: =+E96/E92 -> -1.0817794 | F100: =+F96/F92 -> -1.061568 | G100: =+G96/G92 -> -1.1128507 | H100: =+H96/H92 -> -1.1557513 | I100: =+I96/I92 -> -1.1448636 | J100: =+J96/J92 -> -1.1023911 | K100: =+K96/K92 -> -1.123415 | ... W100: =+W96/W92 -> -1.2589521
A102: Y01010100112120240 | B102: STD 12 mm. | D102: BKK | E102: CM | F102: CR | G102: PL | H102: NS | I102: KK | J102: SK | K102: UD | L102: UB | M102: NR | N102: RB | O102: PC | P102: BS | Q102: AY | R102: RY | S102: CB | T102: SR | U102: PK | V102: HY | W102: SB
A103: Y01010200012120240 | B103: Price List | D103: 268 | E103: 268 | F103: 268 | G103: 268 | H103: 268 | I103: 268 | J103: 268 | K103: 268 | L103: 268 | M103: 268 | N103: 268 | O103: 268 | P103: 268 | Q103: 268 | R103: 268 | S103: 268 | T103: 268 | U103: 268 | V103: 268 | W103: 268
...

Sheet Sheet1
A1: STD 9 mm. | B1: SYNIA 9 mm. | C1: TEC 9 mm. | D1: SYNIA TEC 9 mm. | E1: STD 12 mm. | F1: TEC 12 mm. | G1: ทนไฟ 12 มม. | H1: ทนไฟ 15 มม. | I1: ยิปซัมลดเสียงสะท้อน เอคโค่บล็อค | J1: Paper touch ลวดลาย | K1: Paper touch หยาดเพชร | L1: Paper touch หยาดเพชร ติดฟอยลด์ | M1: Color touch 60x60 9 mm. | N1: Color touch 60x120 9 mm. | O1: Color touch 60x60 9 mm.ทนชื้น | P1: Color touch 60x120 ทนชื้น 9 มม. | Q1: เซิฟบอร์ด ขนาด 30 ซม. | R1: เซิฟบอร์ด ขนาด 45 ซม. | S1: เซิฟบอร์ด ขนาด 60 ซม. | T1: เซิฟบอร์ด ขนาด 60*120 ซม. | U1: เซิฟบอร์ด ขนาด 30 ซม. ทนชื้น | V1: เซิฟบอร์ด ขนาด 45 ซม. ทนชื้น | W1: เซิฟบอร์ด ขนาด 60 ซม. ทนชื้น | X1: เซิฟบอร์ด ขนาด 60*120 ซม. ทนชื้น | Y1: อะคูสติก กาแลคซี่ | Z1: อะคูสติก-อิมเพรสชันME903 | AA1: อะคูสติก-อิมเพรสชันME904 | AB1: อะคูสติก-อิมเพรสชันME905 | AC1: อะคูสติก-อิมเพรสชันME908 | AD1: คนอฟ | AE1: คนอฟ ทนชื้น/ฟอล์ย | AF1: เวเทอร์บล็อค W0 | AG1: เวเทอร์บล็อค W1 | AH1: STD 15 mm. | AI1: ยิปซัมเฟล็กบอร์ด(ดัดโค้ง) 6 มม. 120*240 มม. | AJ1: Color touch สีมุก/สีเพชร 60x120*12 mm. | AK1: Color touch สีมุก/สีเพชร 60x120*12 mm. ทนชื้น | AL1: SB 120x240 4 mm | AM1: SB 120x120 4 mm | AN1: SB 60x240 4 mm | AO1: SB 120x240 6 mm | AP1: SB 120x240 8 mm | AQ1: SB 120x240 10 mm | AR1: SB 120x240 12 mm | AS1: SB 120x280 8 mm | AT1: ลายไม้/เซาะร่อง | AU1: ระบายอากาศ | AV1: ลายไม้ระบายอากาศ | AW1: ลายไม้ระบายอากาศ โพรเทคชั่น | AX1: SB 60*120 4 mm | AY1: ไม้มอบ | AZ1: ไม้ระแนงลบมุม 7.5 | BA1: Sun 120x240 4 mm | BB1: Sun 120x120 4 mm | BC1: Sun 60x240 4 mm | BD1: Sun 120x240 6 mm | BE1: Sun ไม้มอบ | BF1: Sun ไม้ระแนงลบมุม 7.5 | BG1: Sun 120x240 8 mm | BH1: ระบายอากาศ โพรเทคชั่น 60*120 ซม. 4 มม. | BI1: SB 120x240 15 mm (65.3 Kg.) | BJ1: SB 120x240 16 mm | BK1: SB 120x240 18 mm | BL1: SB 120x240 20 mm (87 Kg.) | BM1: ไม้ฝา ซูเปอร์ซัน 15*300*0.8 สีซิเมนต์ | BN1: SB เซาะร่อง 4" 120*280 8 มม. | BO1: ซีเมนต์บอร์ด 120*240 8 มม. | BP1: ซีเมนต์บอร์ด 120*240 10 มม. | BQ1: ซีเมนต์บอร์ด 120*240 12 มม. | BR1: ซีเมนต์บอร์ด 120*240 16 มม. | BS1: ซีเมนต์บอร์ด 120*240 20 มม. | BT1: ซีเมนต์บอร์ด 120*240 24 มม. | BU1: ไม้ฝา ซูเปอร์ซัน 15*400*0.8 สีซิเมนต์ | BV1: ไม้ฝา ซูเปอร์ซัน 20*300*0.8 สีซิเมนต์ | BW1: ไม้ฝา ซูเปอร์ซัน 20*400*0.8 สีซิเมนต์ | BX1: ไม้พื้น ซูเปอร์ซัน ลายไม้ 10*300*2.5 รองพื้น | BY1: ไม้พื้น ซูเปอร์ซัน ลายไม้ 15*300*2.5 รองพื้น | BZ1: ไม้พื้น ซูเปอร์ซัน ลายไม้ 20*300*2.5 รองพื้น | CA1: ไม้ระแนงลบมุม 10 | CB1: เซาะร่อง ลายเสี้ยน 120*240*6 มม. | CC1: Sun 120x240 15 mm | CD1: Sun 120x240 20 mm | CE1: Rockchill | CF1: Safe 'n' Silent Pro 330 หนา 50 มม. 60*120 | CG1: Safe 'n' Silent Pro 330 หนา 75 มม. 60*120 | CH1: Safe 'n' Silent Pro 350 หนา 50 มม. 60*120 | CI1: Safe 'n' Silent Pro 330 หนา 50 มม. 40*120 | CJ1: Safe 'n' Silent Pro 330 หนา 50 มม. 40*120
A2: Y01010100109120240 | B2: Y01010700109120240 | C2: Y01020000109120240 | D2: Y01020800109120240 | E2: Y01010100112120240 | F2: Y01020300112120240 | G2: Y01021500112120240 | H2: Y01021500115120240 | I2: Y01041400212120240 | J2: Y01062001908060060 | K2: Y01062001708060060 | L2: Y01062001808060060 | M2: Y01062201409060060 | N2: Y01062201409060120 | O2: Y01062301409060060 | P2: Y01062301409060120 | Q2: Y01083300109030030 | R2: Y01083300109045045 | S2: Y01083300109060060 | T2: Y01083300109060120 | U2: Y01083400109030030 | V2: Y01083400109045045 | W2: Y01083400109060060 | X2: Y01083400109060120 | Y2: Y01070104114060120 | Z2: Y01070103516060060 | AA2: Y01070103616060120 | AB2: Y01073203716060060 | AC2: Y01073203816060120 | AD2: Y02010200109120240 | AE2: Y02020400109120240 | AF2: Y01030500909120240 | AG2: Y01031001009120240 | AH2: Y01010200115120240 | AI2: Y01021700106120240 | AJ2: Y01062201412060120 | AK2: Y01062301412060120 | AL2: Y03094001604120240 | AM2: Y03094001604120120 | AN2: Y03094001604060240 | AO2: Y03094001606120240 | AP2: Y03094001608120240 | AQ2: Y03094001610120240 | AR2: Y03094001612120240 | AS2: Y03094101608120280 | AT2: Y03094204804060120 | AU2: Y03094304504060120 | AV2: Y03094304904060120 | AW2: Y03094305004060120 | AX2: Y03094001604060120 | AY2: Y03104501608050300 | AZ2: Y03104601608075301 | BA2: Y04094001604120240 | BB2: Y04094001604120120 | BC2: Y04094001604060240 | BD2: Y04094001606120240 | BE2: Y04104501608050300 | BF2: Y04104601608075300 | BG2: Y04094001608120240 | BH2: Y03094304604060120 | BI2: Y03094001615120240 | BJ2: Y03094001616120240 | BK2: Y03094001618120240 | BL2: Y03094001620120240 | BM2: Y04104701608015300 | BO2: Y03110101608120240 | BP2: Y03110101610120240 | BQ2: Y03110101612120240 | BR2: Y03110101616120240 | BS2: Y03110101620120240 | BT2: Y03110101624120240 | BU2: Y04104701608015400 | BV2: Y04104701608020300 | CA2: Y03104601610100300 | CB2: Y03094007906120240 | CC2: Y04094001615120240 | CD2: Y04094001620120240 | CE2: Y06135105682060400 | CF2: Y06135005881060120 | CG2: Y06135005882060120 | CH2: Y06135005981060120 | CI2: Y06135005981060120 | CJ2: Y06135005881040120
A3: Y01010200109120240 | C3: Y01020300109120240 | D3: Y01020900109120240 | E3: Y01010200012120240 | F3: Y01020400012120240 | I3: Y01041400312120240 | J3: Y01062002008060060 | K3: Y01062101708060060 | L3: Y01062101808060060 | AE3: Y02020600109120240 | AT3: Y03094205104060120
C4: Y01020400109120240 | F4: Y01020400112120240 | I4: Y01041400412120240 | J4: Y01062002108060060
C5: Y01020500109120240 | F5: Y01020600012120240 | I5: Y01041400512120240 | J5: Y01062002208060060
C6: Y01020600109120240 | F6: Y01020600112120240 | J6: Y01062002308060060
J7: Y01062002408060060
J8: Y01062002508060060
J9: Y01062007508060060
J10: Y01062007608060060
J11: Y01062007708060060
J12: Y01062101908060060
J13: Y01062102008060060
J14: Y01062102108060060
J15: Y01062102208060060
J16: Y01062102308060060
J17: Y01062102408060060
J18: Y01062102508060060

Sheet สูตร 4 step SB
A1: Y03094001604120240 | B1: SB 120x240 4 mm | D1: BKK | E1: CM | F1: CR | G1: PL | H1: NS | I1: KK | J1: SK | K1: UD | L1: UB | M1: NR | N1: RB | O1: PC | P1: BS | Q1: AY | R1: RY | S1: CB | T1: SR | U1: PK | V1: HY | W1: SB | Y1: BKK | Z1: CM | AA1: CR | AB1: PL | AC1: NS | AD1: KK | AE1: SK | AF1: UD | AG1: UB | AH1: NR | AI1: RB | AJ1: PC | AK1: BS | AL1: AY | AM1: RY | AN1: CB | AO1: SR | AP1: PK | AQ1: HY | AR1: SB
B2: Price List | D2: 175 | E2: =D2 -> 175 | F2: =D2 -> 175 | G2: =D2 -> 175 | H2: =E2 -> 175 | I2: =D2 -> 175 | J2: =D2 -> 175 | K2: =D2 -> 175 | L2: =D2 -> 175 | M2: =D2 -> 175 | N2: =D2 -> 175 | O2: =D2 -> 175 | P2: =D2 -> 175 | Q2: =D2 -> 175 | R2: =D2 -> 175 | S2: =D2 -> 175 | W2: =J2 -> 175
B3: Discount | D3: 0.26 | E3: =D3 -> 0.26 | F3: =D3 -> 0.26 | G3: =D3 -> 0.26 | H3: =D3 -> 0.26 | I3: =D3 -> 0.26 | J3: =D3 -> 0.26 | K3: =D3 -> 0.26 | L3: =D3 -> 0.26 | M3: =D3 -> 0.26 | N3: =D3 -> 0.26 | O3: =D3 -> 0.26 | P3: =D3 -> 0.26 | Q3: =D3 -> 0.26 | R3: =D3 -> 0.26 | S3: =D3 -> 0.26 | W3: =J3 -> 0.26
B4: ค่าคลัง ตันละ 150 | D4: 0 | E4: 0 | F4: 0 | G4: 0 | H4: 0 | I4: 0 | J4: 0 | K4: 0 | L4: 0 | M4: 0 | N4: 0 | O4: 0 | P4: 0 | Q4: 0 | R4: 0 | S4: 0 | W4: 0
B5: RE (ex VAT) | D5: =D2-(D2*D3) -> 129.5 | E5: =E2-(E2*E3) -> 129.5 | F5: =F2-(F2*F3) -> 129.5 | G5: =G2-(G2*G3) -> 129.5 | H5: =H2-(H2*H3) -> 129.5 | I5: =I2-(I2*I3) -> 129.5 | J5: =J2-(J2*J3) -> 129.5 | K5: =K2-(K2*K3) -> 129.5 | ... S5: =S2-(S2*S3) -> 129.5 | T5: 141.71 | U5: 141.71 | V5: 141.71 | W5: =W2-(W2*W3) -> 129.5
B6: VAT | C6: 0.07 | D6: =D5*$C6 -> 9.065 | E6: =E5*$C6 -> 9.065 | F6: =F5*$C6 -> 9.065 | G6: =G5*$C6 -> 9.065 | H6: =H5*$C6 -> 9.065 | I6: =I5*$C6 -> 9.065 | J6: =J5*$C6 -> 9.065 | K6: =K5*$C6 -> 9.065 | ... W6: =W5*$C6 -> 9.065
B7: Net Price (inc VAT) | D7: =D5+D6 -> 138.565 | E7: =E5+E6 -> 138.565 | F7: =F5+F6 -> 138.565 | G7: =G5+G6 -> 138.565 | H7: =H5+H6 -> 138.565 | I7: =I5+I6 -> 138.565 | J7: =J5+J6 -> 138.565 | K7: =K5+K6 -> 138.565 | ... W7: =W5+W6 -> 138.565
B8: Transportation | D8: =Y10 -> 6.9611111 | E8: =Z10 -> 15.812222 | F8: =AA10 -> 18.975 | G8: =AB10 -> 12.65 | H8: =AC10 -> 6.7766667 | I8: =AD10 -> 9.0355556 | J8: =AE10 -> 14.005556 | K8: =AF10 -> 11.475556 | ... W8: =AR10 -> 6.5055556 | Y8: 12530 | Z8: 28462 | AA8: 34155 | AB8: 22770 | AC8: 12198 | AD8: 16264 | AE8: 25210 | AF8: 20656 | AG8: 24396 | AH8: 11710 | AI8: 13012 | AJ8: 30581 | AK8: 11710 | AL8: 11710 | AM8: 15451 | AN8: 14638 | AP8: 30581 | AR8: 11710
B9: COGS | D9: =SUM(D7:D8) -> 145.52611 | E9: =SUM(E7:E8) -> 154.37722 | F9: =SUM(F7:F8) -> 157.54 | G9: =SUM(G7:G8) -> 151.215 | H9: =SUM(H7:H8) -> 145.34167 | I9: =SUM(I7:I8) -> 147.60056 | J9: =SUM(J7:J8) -> 152.57056 | K9: =SUM(K7:K8) -> 150.04056 | ... W9: =SUM(W7:W8) -> 145.07056 | Y9: 1800 | Z9: 1800 | AA9: 1800 | AB9: 1800 | AC9: 1800 | AD9: 1800 | AE9: 1800 | AF9: 1800 | AG9: 1800 | AH9: 1800 | AI9: 1800 | AJ9: 1800 | AK9: 1800 | AL9: 1800 | AM9: 1800 | AN9: 1800 | AP9: 1800 | AR9: 1800
B10: Promotion Rebate | Y10: =Y8/Y9 -> 6.9611111 | Z10: =Z8/Z9 -> 15.812222 | AA10: =AA8/AA9 -> 18.975 | AB10: =AB8/AB9 -> 12.65 | AC10: =AC8/AC9 -> 6.7766667 | AD10: =AD8/AD9 -> 9.0355556 | AE10: =AE8/AE9 -> 14.005556 | AF10: =AF8/AF9 -> 11.475556 | ... AN10: =AN8/AN9 -> 8.1322222 | AP10: =AP8/AP9 -> 16.989444 | AR10: =AR8/AR9 -> 6.5055556
B11: Net Cost | D11: =D9+D10 -> 145.52611 | E11: =E9+E10 -> 154.37722 | F11: =F9+F10 -> 157.54 | G11: =G9+G10 -> 151.215 | H11: =H9+H10 -> 145.34167 | I11: =I9+I10 -> 147.60056 | J11: =J9+J10 -> 152.57056 | K11: =K9+K10 -> 150.04056 | ... W11: =W9+W10 -> 145.07056
B12: Price : SDM | D12: 0 | E12: 0 | F12: 0 | G12: 0 | H12: 0 | I12: 0 | J12: 0 | K12: 0 | L12: 0 | M12: 0 | N12: 0 | O12: 0 | P12: 0 | Q12: 0 | R12: 0 | S12: 0 | T12: 0 | U12: 0 | V12: 0 | W12: 0
B13: Price : W1 | D13: 156 | E13: 165 | F13: 168 | G13: 162 | H13: 156 | I13: 158 | J13: 163 | K13: 161 | L13: 163 | M13: 156 | N13: 156 | O13: 166 | P13: 156 | Q13: 156 | R13: 158 | S13: 157 | T13: 162 | U13: 179 | V13: 162 | W13: 156
B14: Price : W2 | D14: 159 | E14: 168 | F14: 171 | G14: 165 | H14: 159 | I14: 161 | J14: 166 | K14: 164 | L14: 166 | M14: 159 | N14: 159 | O14: 169 | P14: 159 | Q14: 159 | R14: 161 | S14: 160 | T14: 165 | U14: 182 | V14: 165 | W14: 159
B15: Price : R1 | D15: 161 | E15: 170 | F15: 173 | G15: 167 | H15: 161 | I15: 163 | J15: 168 | K15: 166 | L15: 168 | M15: 161 | N15: 161 | O15: 171 | P15: 161 | Q15: 161 | R15: 163 | S15: 162 | T15: 167 | U15: 184 | V15: 167 | W15: 161
B16: Price : R2 | D16: 163 | E16: 172 | F16: 175 | G16: 169 | H16: 163 | I16: 165 | J16: 170 | K16: 168 | L16: 170 | M16: 163 | N16: 163 | O16: 173 | P16: 163 | Q16: 163 | R16: 165 | S16: 164 | T16: 169 | U16: 186 | V16: 169 | W16: 163
B17: MG/Bht : SDM | D17: 0 | E17: 0 | F17: 0 | G17: 0 | H17: 0 | I17: 0 | J17: 0 | K17: 0 | L17: 0 | M17: 0 | N17: 0 | O17: 0 | P17: 0 | Q17: 0 | R17: 0 | S17: 0 | T17: 0 | U17: 0 | V17: 0 | W17: 0
B18: MG/Bht : W1 | D18: =+D13-D$11 -> 10.473889 | E18: =+E13-E$11 -> 10.622778 | F18: =+F13-F$11 -> 10.46 | G18: =+G13-G$11 -> 10.785 | H18: =+H13-H$11 -> 10.658333 | I18: =+I13-I$11 -> 10.399444 | J18: =+J13-J$11 -> 10.429444 | K18: =+K13-K$11 -> 10.959444 | ... W18: =+W13-W$11 -> 10.929444
B19: MG/Bht : W2 | D19: =+D14-D$11 -> 13.473889 | E19: =+E14-E$11 -> 13.622778 | F19: =+F14-F$11 -> 13.46 | G19: =+G14-G$11 -> 13.785 | H19: =+H14-H$11 -> 13.658333 | I19: =+I14-I$11 -> 13.399444 | J19: =+J14-J$11 -> 13.429444 | K19: =+K14-K$11 -> 13.959444 | ... W19: =+W14-W$11 -> 13.929444
B20: MG/Bht : R1 | D20: =+D15-D$11 -> 15.473889 | E20: =+E15-E$11 -> 15.622778 | F20: =+F15-F$11 -> 15.46 | G20: =+G15-G$11 -> 15.785 | H20: =+H15-H$11 -> 15.658333 | I20: =+I15-I$11 -> 15.399444 | J20: =+J15-J$11 -> 15.429444 | K20: =+K15-K$11 -> 15.959444 | ... W20: =+W15-W$11 -> 15.929444
B21: MG/Bht : R2 | D21: =+D16-D$11 -> 17.473889 | E21: =+E16-E$11 -> 17.622778 | F21: =+F16-F$11 -> 17.46 | G21: =+G16-G$11 -> 17.785 | H21: =+H16-H$11 -> 17.658333 | I21: =+I16-I$11 -> 17.399444 | J21: =+J16-J$11 -> 17.429444 | K21: =+K16-K$11 -> 17.959444 | ... W21: =+W16-W$11 -> 17.929444
B22: MG/% : SDM | D22: 0 | E22: 0 | F22: 0 | G22: 0 | H22: 0 | I22: 0 | J22: 0 | K22: 0 | L22: 0 | M22: 0 | N22: 0 | O22: 0 | P22: 0 | Q22: 0 | R22: 0 | S22: 0 | T22: 0 | U22: 0 | V22: 0 | W22: 0
B23: MG/% : W1 | D23: =+D18/D$13 -> 0.067140313 | E23: =+E18/E$13 -> 0.064380471 | F23: =+F18/F$13 -> 0.062261905 | G23: =+G18/G$13 -> 0.066574074 | H23: =+H18/H$13 -> 0.06832265 | I23: =+I18/I$13 -> 0.065819269 | J23: =+J18/J$13 -> 0.063984322 | K23: =+K18/K$13 -> 0.068071084 | ... W23: =+W18/W$13 -> 0.070060541
B24: MG/% : W2 | D24: =+D19/D$14 -> 0.08474144 | E24: =+E19/E$14 -> 0.081087963 | F24: =+F19/F$14 -> 0.07871345 | G24: =+G19/G$14 -> 0.083545455 | H24: =+H19/H$14 -> 0.085901468 | I24: =+I19/I$14 -> 0.083226363 | J24: =+J19/J$14 -> 0.080900268 | K24: =+K19/K$14 -> 0.085118564 | ... W24: =+W19/W$14 -> 0.087606569
B25: MG/% : R1 | D25: =+D20/D$15 -> 0.096111111 | E25: =+E20/E$15 -> 0.091898693 | F25: =+F20/F$15 -> 0.089364162 | G25: =+G20/G$15 -> 0.094520958 | H25: =+H20/H$15 -> 0.097256729 | I25: =+I20/I$15 -> 0.094475119 | J25: =+J20/J$15 -> 0.091841931 | K25: =+K20/K$15 -> 0.096141232 | ... W25: =+W20/W$15 -> 0.098940649
B26: MG/% : R2 | D26: =+D21/D$16 -> 0.10720177 | E26: =+E21/E$16 -> 0.10245801 | F26: =+F21/F$16 -> 0.099771429 | G26: =+G21/G$16 -> 0.10523669 | H26: =+H21/H$16 -> 0.10833333 | I26: =+I21/I$16 -> 0.10545118 | J26: =+J21/J$16 -> 0.10252614 | K26: =+K21/K$16 -> 0.10690146 | ... W26: =+W21/W$16 -> 0.10999659
A29: Y03094001604120120 | B29: SB 120x120 4 mm | D29: BKK | E29: CM | F29: CR | G29: PL | H29: NS | I29: KK | J29: SK | K29: UD | L29: UB | M29: NR | N29: RB | O29: PC | P29: BS | Q29: AY | R29: RY | S29: CB | T29: SR | U29: PK | V29: HY | W29: SB
B30: Price List | D30: 89 | E30: 89 | F30: 89 | G30: 89 | H30: 89 | I30: 89 | J30: 89 | K30: 89 | L30: 89 | M30: 89 | N30: 89 | O30: 89 | P30: 89 | Q30: 89 | R30: 89 | S30: 89 | W30: 89
B31: Discount | D31: 0.26 | E31: =D31 -> 0.26 | F31: =D31 -> 0.26 | G31: =D31 -> 0.26 | H31: =D31 -> 0.26 | I31: =D31 -> 0.26 | J31: =D31 -> 0.26 | K31: =D31 -> 0.26 | L31: =D31 -> 0.26 | M31: =D31 -> 0.26 | N31: =D31 -> 0.26 | O31: =D31 -> 0.26 | P31: =D31 -> 0.26 | Q31: =D31 -> 0.26 | R31: =D31 -> 0.26 | S31: =D31 -> 0.26 | W31: =J31 -> 0.26
B32: ค่าคลัง ตันละ 150 | D32: 0 | E32: 0 | F32: 0 | G32: 0 | H32: 0 | I32: 0 | J32: 0 | K32: 0 | L32: 0 | M32: 0 | N32: 0 | O32: 0 | P32: 0 | Q32: 0 | R32: 0 | S32: 0 | W32: 0
B33: RE (ex VAT) | D33: =D30-(D30*D31) -> 65.86 | E33: =E30-(E30*E31) -> 65.86 | F33: =F30-(F30*F31) -> 65.86 | G33: =G30-(G30*G31) -> 65.86 | H33: =H30-(H30*H31) -> 65.86 | I33: =I30-(I30*I31) -> 65.86 | J33: =J30-(J30*J31) -> 65.86 | K33: =K30-(K30*K31) -> 65.86 | ... S33: =S30-(S30*S31) -> 65.86 | T33: 72.05 | U33: 72.05 | V33: 72.05 | W33: =W30-(W30*W31) -> 65.86
B34: VAT | C34: 0.07 | D34: =D33*$C34 -> 4.6102 | E34: =E33*$C34 -> 4.6102 | F34: =F33*$C34 -> 4.6102 | G34: =G33*$C34 -> 4.6102 | H34: =H33*$C34 -> 4.6102 | I34: =I33*$C34 -> 4.6102 | J34: =J33*$C34 -> 4.6102 | K34: =K33*$C34 -> 4.6102 | ... W34: =W33*$C34 -> 4.6102
B35: Net Price (inc VAT) | D35: =D33+D34 -> 70.4702 | E35: =E33+E34 -> 70.4702 | F35: =F33+F34 -> 70.4702 | G35: =G33+G34 -> 70.4702 | H35: =H33+H34 -> 70.4702 | I35: =I33+I34 -> 70.4702 | J35: =J33+J34 -> 70.4702 | K35: =K33+K34 -> 70.4702 | ... W35: =W33+W34 -> 70.4702
B36: Transportation | D36: =Y38 -> 3.4805556 | E36: =Z38 -> 7.9061111 | F36: =AA38 -> 9.4875 | G36: =AB38 -> 6.325 | H36: =AC38 -> 3.3883333 | I36: =AD38 -> 4.5177778 | J36: =AE38 -> 7.0027778 | K36: =AF38 -> 5.7377778 | ... W36: =AR38 -> 3.2527778 | Y36: 12530 | Z36: 28462 | AA36: 34155 | AB36: 22770 | AC36: 12198 | AD36: 16264 | AE36: 25210 | AF36: 20656 | AG36: 24396 | AH36: 11710 | AI36: 13012 | AJ36: 30581 | AK36: 11710 | AL36: 11710 | AM36: 15451 | AN36: 14638 | AP36: 30581 | AR36: 11710
B37: COGS | D37: =SUM(D35:D36) -> 73.950756 | E37: =SUM(E35:E36) -> 78.376311 | F37: =SUM(F35:F36) -> 79.9577 | G37: =SUM(G35:G36) -> 76.7952 | H37: =SUM(H35:H36) -> 73.858533 | I37: =SUM(I35:I36) -> 74.987978 | J37: =SUM(J35:J36) -> 77.472978 | K37: =SUM(K35:K36) -> 76.207978 | ... W37: =SUM(W35:W36) -> 73.722978 | Y37: 3600 | Z37: 3600 | AA37: 3600 | AB37: 3600 | AC37: 3600 | AD37: 3600 | AE37: 3600 | AF37: 3600 | AG37: 3600 | AH37: 3600 | AI37: 3600 | AJ37: 3600 | AK37: 3600 | AL37: 3600 | AM37: 3600 | AN37: 3600 | AP37: 3600 | AR37: 3600
B38: Promotion Rebate | Y38: =Y36/Y37 -> 3.4805556 | Z38: =Z36/Z37 -> 7.9061111 | AA38: =AA36/AA37 -> 9.4875 | AB38: =AB36/AB37 -> 6.325 | AC38: =AC36/AC37 -> 3.3883333 | AD38: =AD36/AD37 -> 4.5177778 | AE38: =AE36/AE37 -> 7.0027778 | AF38: =AF36/AF37 -> 5.7377778 | ... AN38: =AN36/AN37 -> 4.0661111 | AP38: =AP36/AP37 -> 8.4947222 | AR38: =AR36/AR37 -> 3.2527778
B39: Net Cost | D39: =D37+D38 -> 73.950756 | E39: =E37+E38 -> 78.376311 | F39: =F37+F38 -> 79.9577 | G39: =G37+G38 -> 76.7952 | H39: =H37+H38 -> 73.858533 | I39: =I37+I38 -> 74.987978 | J39: =J37+J38 -> 77.472978 | K39: =K37+K38 -> 76.207978 | ... W39: =W37+W38 -> 73.722978
B40: Price : SDM | D40: 0 | E40: 0 | F40: 0 | G40: 0 | H40: 0 | I40: 0 | J40: 0 | K40: 0 | L40: 0 | M40: 0 | N40: 0 | O40: 0 | P40: 0 | Q40: 0 | R40: 0 | S40: 0 | T40: 0 | U40: 0 | V40: 0 | W40: 0
B41: Price : W1 | D41: 79 | E41: 84 | F41: 85 | G41: 82 | H41: 79 | I41: 80 | J41: 83 | K41: 82 | L41: 83 | M41: 79 | N41: 80 | O41: 84 | P41: 79 | Q41: 79 | R41: 80 | S41: 80 | T41: 83 | U41: 91 | V41: 83 | W41: 79
B42: Price : W2 | D42: 81 | E42: 86 | F42: 87 | G42: 84 | H42: 81 | I42: 82 | J42: 85 | K42: 84 | L42: 85 | M42: 81 | N42: 82 | O42: 86 | P42: 81 | Q42: 81 | R42: 82 | S42: 82 | T42: 85 | U42: 93 | V42: 85 | W42: 81
B43: Price : R1 | D43: 82 | E43: 87 | F43: 88 | G43: 85 | H43: 82 | I43: 83 | J43: 86 | K43: 85 | L43: 86 | M43: 82 | N43: 83 | O43: 87 | P43: 82 | Q43: 82 | R43: 83 | S43: 83 | T43: 86 | U43: 94 | V43: 86 | W43: 82
B44: Price : R2 | D44: 83 | E44: 88 | F44: 89 | G44: 86 | H44: 83 | I44: 84 | J44: 87 | K44: 86 | L44: 87 | M44: 83 | N44: 84 | O44: 88 | P44: 83 | Q44: 83 | R44: 84 | S44: 84 | T44: 87 | U44: 95 | V44: 87 | W44: 83
B45: MG/Bht : SDM | D45: 0 | E45: 0 | F45: 0 | G45: 0 | H45: 0 | I45: 0 | J45: 0 | K45: 0 | L45: 0 | M45: 0 | N45: 0 | O45: 0 | P45: 0 | Q45: 0 | R45: 0 | S45: 0 | T45: 0 | U45: 0 | V45: 0 | W45: 0
B46: MG/Bht : W1 | D46: =+D41-D$39 -> 5.0492444 | E46: =+E41-E$39 -> 5.6236889 | F46: =+F41-F$39 -> 5.0423 | G46: =+G41-G$39 -> 5.2048 | H46: =+H41-H$39 -> 5.1414667 | I46: =+I41-I$39 -> 5.0120222 | J46: =+J41-J$39 -> 5.5270222 | K46: =+K41-K$39 -> 5.7920222 | ... W46: =+W41-W$39 -> 5.2770222
B47: MG/Bht : W2 | D47: =+D42-D$39 -> 7.0492444 | E47: =+E42-E$39 -> 7.6236889 | F47: =+F42-F$39 -> 7.0423 | G47: =+G42-G$39 -> 7.2048 | H47: =+H42-H$39 -> 7.1414667 | I47: =+I42-I$39 -> 7.0120222 | J47: =+J42-J$39 -> 7.5270222 | K47: =+K42-K$39 -> 7.7920222 | ... W47: =+W42-W$39 -> 7.2770222
B48: MG/Bht : R1 | D48: =+D43-D$39 -> 8.0492444 | E48: =+E43-E$39 -> 8.6236889 | F48: =+F43-F$39 -> 8.0423 | G48: =+G43-G$39 -> 8.2048 | H48: =+H43-H$39 -> 8.1414667 | I48: =+I43-I$39 -> 8.0120222 | J48: =+J43-J$39 -> 8.5270222 | K48: =+K43-K$39 -> 8.7920222 | ... W48: =+W43-W$39 -> 8.2770222
B49: MG/Bht : R2 | D49: =+D44-D$39 -> 9.0492444 | E49: =+E44-E$39 -> 9.6236889 | F49: =+F44-F$39 -> 9.0423 | G49: =+G44-G$39 -> 9.2048 | H49: =+H44-H$39 -> 9.1414667 | I49: =+I44-I$39 -> 9.0120222 | J49: =+J44-J$39 -> 9.5270222 | K49: =+K44-K$39 -> 9.7920222 | ... W49: =+W44-W$39 -> 9.2770222
B50: MG/% : SDM | D50: 0 | E50: 0 | F50: 0 | G50: 0 | H50: 0 | I50: 0 | J50: 0 | K50: 0 | L50: 0 | M50: 0 | N50: 0 | O50: 0 | P50: 0 | Q50: 0 | R50: 0 | S50: 0 | T50: 0 | U50: 0 | V50: 0 | W50: 0
B51: MG/% : W1 | D51: =+D46/D$41 -> 0.063914487 | E51: =+E46/E$41 -> 0.066948677 | F51: =+F46/F$41 -> 0.059321176 | G51: =+G46/G$41 -> 0.063473171 | H51: =+H46/H$41 -> 0.065081857 | I51: =+I46/I$41 -> 0.062650278 | J51: =+J46/J$41 -> 0.066590629 | K51: =+K46/K$41 -> 0.070634417 | ... W51: =+W46/W$41 -> 0.06679775
B52: MG/% : W2 | D52: =+D47/D$42 -> 0.087027709 | E52: =+E47/E$42 -> 0.088647545 | F52: =+F47/F$42 -> 0.080945977 | G52: =+G47/G$42 -> 0.085771429 | H52: =+H47/H$42 -> 0.088166255 | I52: =+I47/I$42 -> 0.085512466 | J52: =+J47/J$42 -> 0.088553203 | K52: =+K47/K$42 -> 0.092762169 | ... W52: =+W47/W$42 -> 0.089839781
B53: MG/% : R1 | D53: =+D48/D$43 -> 0.098161518 | E53: =+E48/E$43 -> 0.099122861 | F53: =+F48/F$43 -> 0.091389773 | G53: =+G48/G$43 -> 0.096527059 | H53: =+H48/H$43 -> 0.099286179 | I53: =+I48/I$43 -> 0.096530388 | J53: =+J48/J$43 -> 0.099151421 | K53: =+K48/K$43 -> 0.10343556 | ... W53: =+W48/W$43 -> 0.1009393
B54: MG/% : R2 | D54: =+D49/D$44 -> 0.10902704 | E54: =+E49/E$44 -> 0.1093601 | F54: =+F49/F$44 -> 0.10159888 | G54: =+G49/G$44 -> 0.10703256 | H54: =+H49/H$44 -> 0.11013815 | I54: =+I49/I$44 -> 0.10728598 | J54: =+J49/J$44 -> 0.109506 | K54: =+K49/K$44 -> 0.11386072 | ... W54: =+W49/W$44 -> 0.11177135
A56: Y03094001604060240 | B56: SB 60x240 4 mm | D56: BKK | E56: CM | F56: CR | G56: PL | H56: NS | I56: KK | J56: SK | K56: UD | L56: UB | M56: NR | N56: RB | O56: PC | P56: BS | Q56: AY | R56: RY | S56: CB | T56: SR | U56: PK | V56: HY | W56: SB
B57: Price List | D57: 89 | E57: 89 | F57: 89 | G57: 89 | H57: 89 | I57: 89 | J57: 89 | K57: 89 | L57: 89 | M57: 89 | N57: 89 | O57: 89 | P57: 89 | Q57: 89 | R57: 89 | S57: 89 | W57: 89
B58: Discount | D58: 0.26 | E58: =D58 -> 0.26 | F58: =D58 -> 0.26 | G58: =D58 -> 0.26 | H58: =D58 -> 0.26 | I58: =D58 -> 0.26 | J58: =D58 -> 0.26 | K58: =D58 -> 0.26 | L58: =D58 -> 0.26 | M58: =D58 -> 0.26 | N58: =D58 -> 0.26 | O58: =D58 -> 0.26 | P58: =D58 -> 0.26 | Q58: =D58 -> 0.26 | R58: =D58 -> 0.26 | S58: =D58 -> 0.26 | W58: =J58 -> 0.26
B59: ค่าคลัง ตันละ 150 | D59: 0 | E59: 0 | F59: 0 | G59: 0 | H59: 0 | I59: 0 | J59: 0 | K59: 0 | L59: 0 | M59: 0 | N59: 0 | O59: 0 | P59: 0 | Q59: 0 | R59: 0 | S59: 0 | W59: 0
B60: RE (ex VAT) | D60: =D57-(D57*D58) -> 65.86 | E60: =E57-(E57*E58) -> 65.86 | F60: =F57-(F57*F58) -> 65.86 | G60: =G57-(G57*G58) -> 65.86 | H60: =H57-(H57*H58) -> 65.86 | I60: =I57-(I57*I58) -> 65.86 | J60: =J57-(J57*J58) -> 65.86 | K60: =K57-(K57*K58) -> 65.86 | ... S60: =S57-(S57*S58) -> 65.86 | T60: 72.05 | U60: 72.05 | V60: 72.05 | W60: =W57-(W57*W58) -> 65.86
B61: VAT | C61: 0.07 | D61: =D60*$C61 -> 4.6102 | E61: =E60*$C61 -> 4.6102 | F61: =F60*$C61 -> 4.6102 | G61: =G60*$C61 -> 4.6102 | H61: =H60*$C61 -> 4.6102 | I61: =I60*$C61 -> 4.6102 | J61: =J60*$C61 -> 4.6102 | K61: =K60*$C61 -> 4.6102 | ... W61: =W60*$C61 -> 4.6102
B62: Net Price (inc VAT) | D62: =D60+D61 -> 70.4702 | E62: =E60+E61 -> 70.4702 | F62: =F60+F61 -> 70.4702 | G62: =G60+G61 -> 70.4702 | H62: =H60+H61 -> 70.4702 | I62: =I60+I61 -> 70.4702 | J62: =J60+J61 -> 70.4702 | K62: =K60+K61 -> 70.4702 | ... W62: =W60+W61 -> 70.4702
B63: Transportation | D63: =Y65 -> 3.4805556 | E63: =Z65 -> 7.9061111 | F63: =AA65 -> 9.4875 | G63: =AB65 -> 6.325 | H63: =AC65 -> 3.3883333 | I63: =AD65 -> 4.5177778 | J63: =AE65 -> 7.0027778 | K63: =AF65 -> 5.7377778 | ... W63: =AR65 -> 3.2527778 | Y63: 12530 | Z63: 28462 | AA63: 34155 | AB63: 22770 | AC63: 12198 | AD63: 16264 | AE63: 25210 | AF63: 20656 | AG63: 24396 | AH63: 11710 | AI63: 13012 | AJ63: 30581 | AK63: 11710 | AL63: 11710 | AM63: 15451 | AN63: 14638 | AP63: 30581 | AR63: 11710
B64: COGS | D64: =SUM(D62:D63) -> 73.950756 | E64: =SUM(E62:E63) -> 78.376311 | F64: =SUM(F62:F63) -> 79.9577 | G64: =SUM(G62:G63) -> 76.7952 | H64: =SUM(H62:H63) -> 73.858533 | I64: =SUM(I62:I63) -> 74.987978 | J64: =SUM(J62:J63) -> 77.472978 | K64: =SUM(K62:K63) -> 76.207978 | ... W64: =SUM(W62:W63) -> 73.722978 | Y64: 3600 | Z64: 3600 | AA64: 3600 | AB64: 3600 | AC64: 3600 | AD64: 3600 | AE64: 3600 | AF64: 3600 | AG64: 3600 | AH64: 3600 | AI64: 3600 | AJ64: 3600 | AK64: 3600 | AL64: 3600 | AM64: 3600 | AN64: 3600 | AP64: 3600 | AR64: 3600
B65: Promotion Rebate | Y65: =Y63/Y64 -> 3.4805556 | Z65: =Z63/Z64 -> 7.9061111 | AA65: =AA63/AA64 -> 9.4875 | AB65: =AB63/AB64 -> 6.325 | AC65: =AC63/AC64 -> 3.3883333 | AD65: =AD63/AD64 -> 4.5177778 | AE65: =AE63/AE64 -> 7.0027778 | AF65: =AF63/AF64 -> 5.7377778 | ... AN65: =AN63/AN64 -> 4.0661111 | AP65: =AP63/AP64 -> 8.4947222 | AR65: =AR63/AR64 -> 3.2527778
B66: Net Cost | D66: =SUM(D64:D65) -> 73.950756 | E66: =SUM(E64:E65) -> 78.376311 | F66: =SUM(F64:F65) -> 79.9577 | G66: =SUM(G64:G65) -> 76.7952 | H66: =SUM(H64:H65) -> 73.858533 | I66: =SUM(I64:I65) -> 74.987978 | J66: =SUM(J64:J65) -> 77.472978 | K66: =SUM(K64:K65) -> 76.207978 | ... W66: =SUM(W64:W65) -> 73.722978
B67: Price : SDM | D67: 0 | E67: 0 | F67: 0 | G67: 0 | H67: 0 | I67: 0 | J67: 0 | K67: 0 | L67: 0 | M67: 0 | N67: 0 | O67: 0 | P67: 0 | Q67: 0 | R67: 0 | S67: 0 | T67: 0 | U67: 0 | V67: 0 | W67: 0
B68: Price : W1 | D68: 78 | E68: 83 | F68: 84 | G68: 81 | H68: 78 | I68: 79 | J68: 82 | K68: 81 | L68: 82 | M68: 78 | N68: 79 | O68: 83 | P68: 78 | Q68: 78 | R68: 79 | S68: 79 | T68: 82 | U68: 90 | V68: 82 | W68: 78
B69: Price : W2 | D69: 80 | E69: 85 | F69: 86 | G69: 83 | H69: 80 | I69: 81 | J69: 84 | K69: 83 | L69: 84 | M69: 80 | N69: 81 | O69: 85 | P69: 80 | Q69: 80 | R69: 81 | S69: 81 | T69: 84 | U69: 92 | V69: 84 | W69: 80
B70: Price : R1 | D70: 81 | E70: 86 | F70: 87 | G70: 84 | H70: 81 | I70: 82 | J70: 85 | K70: 84 | L70: 85 | M70: 81 | N70: 82 | O70: 86 | P70: 81 | Q70: 81 | R70: 82 | S70: 82 | T70: 85 | U70: 93 | V70: 85 | W70: 81
B71: Price : R2 | D71: 83 | E71: 88 | F71: 89 | G71: 86 | H71: 83 | I71: 84 | J71: 87 | K71: 86 | L71: 87 | M71: 83 | N71: 84 | O71: 88 | P71: 83 | Q71: 83 | R71: 84 | S71: 84 | T71: 87 | U71: 95 | V71: 87 | W71: 83
B72: MG/Bht : SDM | D72: 0 | E72: 0 | F72: 0 | G72: 0 | H72: 0 | I72: 0 | J72: 0 | K72: 0 | L72: 0 | M72: 0 | N72: 0 | O72: 0 | P72: 0 | Q72: 0 | R72: 0 | S72: 0 | T72: 0 | U72: 0 | V72: 0 | W72: 0
B73: MG/Bht : W1 | D73: =+D68-D$66 -> 4.0492444 | E73: =+E68-E$66 -> 4.6236889 | F73: =+F68-F$66 -> 4.0423 | G73: =+G68-G$66 -> 4.2048 | H73: =+H68-H$66 -> 4.1414667 | I73: =+I68-I$66 -> 4.0120222 | J73: =+J68-J$66 -> 4.5270222 | K73: =+K68-K$66 -> 4.7920222 | ... W73: =+W68-W$66 -> 4.2770222
B74: MG/Bht : W2 | D74: =+D69-D$66 -> 6.0492444 | E74: =+E69-E$66 -> 6.6236889 | F74: =+F69-F$66 -> 6.0423 | G74: =+G69-G$66 -> 6.2048 | H74: =+H69-H$66 -> 6.1414667 | I74: =+I69-I$66 -> 6.0120222 | J74: =+J69-J$66 -> 6.5270222 | K74: =+K69-K$66 -> 6.7920222 | ... W74: =+W69-W$66 -> 6.2770222
B75: MG/Bht : R1 | D75: =+D70-D$66 -> 7.0492444 | E75: =+E70-E$66 -> 7.6236889 | F75: =+F70-F$66 -> 7.0423 | G75: =+G70-G$66 -> 7.2048 | H75: =+H70-H$66 -> 7.1414667 | I75: =+I70-I$66 -> 7.0120222 | J75: =+J70-J$66 -> 7.5270222 | K75: =+K70-K$66 -> 7.7920222 | ... W75: =+W70-W$66 -> 7.2770222
B76: MG/Bht : R2 | D76: =+D71-D$66 -> 9.0492444 | E76: =+E71-E$66 -> 9.6236889 | F76: =+F71-F$66 -> 9.0423 | G76: =+G71-G$66 -> 9.2048 | H76: =+H71-H$66 -> 9.1414667 | I76: =+I71-I$66 -> 9.0120222 | J76: =+J71-J$66 -> 9.5270222 | K76: =+K71-K$66 -> 9.7920222 | ... W76: =+W71-W$66 -> 9.2770222
B77: MG/% : SDM | D77: 0 | E77: 0 | F77: 0 | G77: 0 | H77: 0 | I77: 0 | J77: 0 | K77: 0 | L77: 0 | M77: 0 | N77: 0 | O77: 0 | P77: 0 | Q77: 0 | R77: 0 | S77: 0 | T77: 0 | U77: 0 | V77: 0 | W77: 0
B78: MG/% : W1 | D78: =+D73/D$68 -> 0.05191339 | E78: =+E73/E$68 -> 0.055707095 | F78: =+F73/F$68 -> 0.048122619 | G78: =+G73/G$68 -> 0.051911111 | H78: =+H73/H$68 -> 0.053095726 | I78: =+I73/I$68 -> 0.050785091 | J78: =+J73/J$68 -> 0.055207588 | K78: =+K73/K$68 -> 0.059160768 | ... W78: =+W73/W$68 -> 0.054833618
B79: MG/% : W2 | D79: =+D74/D$69 -> 0.075615556 | E79: =+E74/E$69 -> 0.077925752 | F79: =+F74/F$69 -> 0.070259302 | G79: =+G74/G$69 -> 0.074756627 | H79: =+H74/H$69 -> 0.076768333 | I79: =+I74/I$69 -> 0.074222497 | J79: =+J74/J$69 -> 0.077702646 | K79: =+K74/K$69 -> 0.081831593 | ... W79: =+W74/W$69 -> 0.078462778
B80: MG/% : R1 | D80: =+D75/D$70 -> 0.087027709 | E80: =+E75/E$70 -> 0.088647545 | F80: =+F75/F$70 -> 0.080945977 | G80: =+G75/G$70 -> 0.085771429 | H80: =+H75/H$70 -> 0.088166255 | I80: =+I75/I$70 -> 0.085512466 | J80: =+J75/J$70 -> 0.088553203 | K80: =+K75/K$70 -> 0.092762169 | ... W80: =+W75/W$70 -> 0.089839781
B81: MG/% : R2 | D81: =+D76/D$71 -> 0.10902704 | E81: =+E76/E$71 -> 0.1093601 | F81: =+F76/F$71 -> 0.10159888 | G81: =+G76/G$71 -> 0.10703256 | H81: =+H76/H$71 -> 0.11013815 | I81: =+I76/I$71 -> 0.10728598 | J81: =+J76/J$71 -> 0.109506 | K81: =+K76/K$71 -> 0.11386072 | ... W81: =+W76/W$71 -> 0.11177135
A84: Y03094001606120240 | B84: SB 120x240 6 mm | D84: BKK | E84: CM | F84: CR | G84: PL | H84: NS | I84: KK | J84: SK | K84: UD | L84: UB | M84: NR | N84: RB | O84: PC | P84: BS | Q84: AY | R84: RY | S84: CB | T84: SR | U84: PK | V84: HY | W84: SB
B85: Price List | D85: 265 | E85: 265 | F85: 265 | G85: 265 | H85: 265 | I85: 265 | J85: 265 | K85: 265 | L85: 265 | M85: 265 | N85: 265 | O85: 265 | P85: 265 | Q85: 265 | R85: 265 | S85: 265 | W85: 265
B86: Discount | D86: 0.26 | E86: =D86 -> 0.26 | F86: =D86 -> 0.26 | G86: =D86 -> 0.26 | H86: =D86 -> 0.26 | I86: =D86 -> 0.26 | J86: =D86 -> 0.26 | K86: =D86 -> 0.26 | L86: =D86 -> 0.26 | M86: =D86 -> 0.26 | N86: =D86 -> 0.26 | O86: =D86 -> 0.26 | P86: =D86 -> 0.26 | Q86: =D86 -> 0.26 | R86: =D86 -> 0.26 | S86: =D86 -> 0.26 | W86: =J86 -> 0.26
B87: ค่าคลัง ตันละ 150 | D87: 0 | E87: 0 | F87: 0 | G87: 0 | H87: 0 | I87: 0 | J87: 0 | K87: 0 | L87: 0 | M87: 0 | N87: 0 | O87: 0 | P87: 0 | Q87: 0 | R87: 0 | S87: 0 | T87: 0 | U87: 0 | V87: 0 | W87: 0
B88: RE (ex VAT) | D88: =D85-(D85*D86) -> 196.1 | E88: =E85-(E85*E86) -> 196.1 | F88: =F85-(F85*F86) -> 196.1 | G88: =G85-(G85*G86) -> 196.1 | H88: =H85-(H85*H86) -> 196.1 | I88: =I85-(I85*I86) -> 196.1 | J88: =J85-(J85*J86) -> 196.1 | K88: =K85-(K85*K86) -> 196.1 | ... S88: =S85-(S85*S86) -> 196.1 | T88: 214.46 | U88: 214.46 | V88: 214.46 | W88: =W85-(W85*W86) -> 196.1
B89: VAT | C89: 0.07 | D89: =D88*$C89 -> 13.727 | E89: =E88*$C89 -> 13.727 | F89: =F88*$C89 -> 13.727 | G89: =G88*$C89 -> 13.727 | H89: =H88*$C89 -> 13.727 | I89: =I88*$C89 -> 13.727 | J89: =J88*$C89 -> 13.727 | K89: =K88*$C89 -> 13.727 | ... W89: =W88*$C89 -> 13.727
B90: Net Price (inc VAT) | D90: =D88+D89 -> 209.827 | E90: =E88+E89 -> 209.827 | F90: =F88+F89 -> 209.827 | G90: =G88+G89 -> 209.827 | H90: =H88+H89 -> 209.827 | I90: =I88+I89 -> 209.827 | J90: =J88+J89 -> 209.827 | K90: =K88+K89 -> 209.827 | ... W90: =W88+W89 -> 209.827
B91: Transportation | D91: =Y93 -> 10.441667 | E91: =Z93 -> 23.718333 | F91: =AA93 -> 28.4625 | G91: =AB93 -> 18.975 | H91: =AC93 -> 10.165 | I91: =AD93 -> 13.553333 | J91: =AE93 -> 21.008333 | K91: =AF93 -> 17.213333 | ... W91: =AR93 -> 9.7583333 | Y91: 12530 | Z91: 28462 | AA91: 34155 | AB91: 22770 | AC91: 12198 | AD91: 16264 | AE91: 25210 | AF91: 20656 | AG91: 24396 | AH91: 11710 | AI91: 13012 | AJ91: 30581 | AK91: 11710 | AL91: 11710 | AM91: 15451 | AN91: 14638 | AP91: 30581 | AR91: 11710
B92: COGS | D92: =SUM(D90:D91) -> 220.26867 | E92: =SUM(E90:E91) -> 233.54533 | F92: =SUM(F90:F91) -> 238.2895 | G92: =SUM(G90:G91) -> 228.802 | H92: =SUM(H90:H91) -> 219.992 | I92: =SUM(I90:I91) -> 223.38033 | J92: =SUM(J90:J91) -> 230.83533 | K92: =SUM(K90:K91) -> 227.04033 | ... W92: =SUM(W90:W91) -> 219.58533 | Y92: 1200 | Z92: 1200 | AA92: 1200 | AB92: 1200 | AC92: 1200 | AD92: 1200 | AE92: 1200 | AF92: 1200 | AG92: 1200 | AH92: 1200 | AI92: 1200 | AJ92: 1200 | AK92: 1200 | AL92: 1200 | AM92: 1200 | AN92: 1200 | AP92: 1200 | AR92: 1200
B93: Promotion Rebate | Y93: =Y91/Y92 -> 10.441667 | Z93: =Z91/Z92 -> 23.718333 | AA93: =AA91/AA92 -> 28.4625 | AB93: =AB91/AB92 -> 18.975 | AC93: =AC91/AC92 -> 10.165 | AD93: =AD91/AD92 -> 13.553333 | AE93: =AE91/AE92 -> 21.008333 | AF93: =AF91/AF92 -> 17.213333 | ... AN93: =AN91/AN92 -> 12.198333 | AP93: =AP91/AP92 -> 25.484167 | AR93: =AR91/AR92 -> 9.7583333
B94: Net Cost | D94: =SUM(D92:D93) -> 220.26867 | E94: =SUM(E92:E93) -> 233.54533 | F94: =SUM(F92:F93) -> 238.2895 | G94: =SUM(G92:G93) -> 228.802 | H94: =SUM(H92:H93) -> 219.992 | I94: =SUM(I92:I93) -> 223.38033 | J94: =SUM(J92:J93) -> 230.83533 | K94: =SUM(K92:K93) -> 227.04033 | ... W94: =SUM(W92:W93) -> 219.58533
B95: Price : SDM | D95: 0 | E95: 0 | F95: 0 | G95: 0 | H95: 0 | I95: 0 | J95: 0 | K95: 0 | L95: 0 | M95: 0 | N95: 0 | O95: 0 | P95: 0 | Q95: 0 | R95: 0 | S95: 0 | T95: 0 | U95: 0 | V95: 0 | W95: 0
B96: Price : W1 | D96: 237 | E96: 250 | F96: 255 | G96: 245 | H96: 236 | I96: 240 | J96: 247 | K96: 244 | L96: 247 | M96: 236 | N96: 237 | O96: 252 | P96: 236 | Q96: 236 | R96: 239 | S96: 239 | T96: 246 | U96: 271 | V96: 246 | W96: 236
B97: Price : W2 | D97: 241 | E97: 254 | F97: 259 | G97: 249 | H97: 240 | I97: 244 | J97: 251 | K97: 248 | L97: 251 | M97: 240 | N97: 241 | O97: 256 | P97: 240 | Q97: 240 | R97: 243 | S97: 243 | T97: 250 | U97: 275 | V97: 250 | W97: 240
B98: Price : R1 | D98: 243 | E98: 256 | F98: 261 | G98: 251 | H98: 242 | I98: 246 | J98: 253 | K98: 250 | L98: 253 | M98: 242 | N98: 243 | O98: 258 | P98: 242 | Q98: 242 | R98: 245 | S98: 245 | T98: 252 | U98: 277 | V98: 252 | W98: 242
B99: Price : R2 | D99: 245 | E99: 258 | F99: 263 | G99: 253 | H99: 244 | I99: 248 | J99: 255 | K99: 252 | L99: 255 | M99: 244 | N99: 245 | O99: 260 | P99: 244 | Q99: 244 | R99: 247 | S99: 247 | T99: 254 | U99: 279 | V99: 254 | W99: 244
B100: MG/Bht : SDM | D100: 0 | E100: 0 | F100: 0 | G100: 0 | H100: 0 | I100: 0 | J100: 0 | K100: 0 | L100: 0 | M100: 0 | N100: 0 | O100: 0 | P100: 0 | Q100: 0 | R100: 0 | S100: 0 | T100: 0 | U100: 0 | V100: 0 | W100: 0
B101: MG/Bht : W1 | D101: =+D96-D$94 -> 16.731333 | E101: =+E96-E$94 -> 16.454667 | F101: =+F96-F$94 -> 16.7105 | G101: =+G96-G$94 -> 16.198 | H101: =+H96-H$94 -> 16.008 | I101: =+I96-I$94 -> 16.619667 | J101: =+J96-J$94 -> 16.164667 | K101: =+K96-K$94 -> 16.959667 | ... W101: =+W96-W$94 -> 16.414667
B102: MG/Bht : W2 | D102: =+D97-D$94 -> 20.731333 | E102: =+E97-E$94 -> 20.454667 | F102: =+F97-F$94 -> 20.7105 | G102: =+G97-G$94 -> 20.198 | H102: =+H97-H$94 -> 20.008 | I102: =+I97-I$94 -> 20.619667 | J102: =+J97-J$94 -> 20.164667 | K102: =+K97-K$94 -> 20.959667 | ... W102: =+W97-W$94 -> 20.414667
B103: MG/Bht : R1 | D103: =+D98-D$94 -> 22.731333 | E103: =+E98-E$94 -> 22.454667 | F103: =+F98-F$94 -> 22.7105 | G103: =+G98-G$94 -> 22.198 | H103: =+H98-H$94 -> 22.008 | I103: =+I98-I$94 -> 22.619667 | J103: =+J98-J$94 -> 22.164667 | K103: =+K98-K$94 -> 22.959667 | ... W103: =+W98-W$94 -> 22.414667
B104: MG/Bht : R2 | D104: =+D99-D$94 -> 24.731333 | E104: =+E99-E$94 -> 24.454667 | F104: =+F99-F$94 -> 24.7105 | G104: =+G99-G$94 -> 24.198 | H104: =+H99-H$94 -> 24.008 | I104: =+I99-I$94 -> 24.619667 | J104: =+J99-J$94 -> 24.164667 | K104: =+K99-K$94 -> 24.959667 | ... W104: =+W99-W$94 -> 24.414667
B105: MG/% : SDM | D105: 0 | E105: 0 | F105: 0 | G105: 0 | H105: 0 | I105: 0 | J105: 0 | K105: 0 | L105: 0 | M105: 0 | N105: 0 | O105: 0 | P105: 0 | Q105: 0 | R105: 0 | S105: 0 | T105: 0 | U105: 0 | V105: 0 | W105: 0
...

Sheet Rockwool
A1: Y06135105682060400 | B1: Rockchill | D1: BKK | E1: CM | F1: CR | G1: PL | H1: NS | I1: KK | J1: SK | K1: UD | L1: UB | M1: NR | N1: RB | O1: PC | P1: BS | Q1: AY | R1: RY | S1: CB | T1: SR | U1: PK | V1: HY | W1: SB
B2: Price List
B3: Discount
D4: =D2*(1-D3) -> 0 | E4: =E2*(1-E3) -> 0 | F4: =F2*(1-F3) -> 0 | G4: =G2*(1-G3) -> 0 | H4: =H2*(1-H3) -> 0 | I4: =I2*(1-I3) -> 0 | J4: =J2*(1-J3) -> 0 | K4: =K2*(1-K3) -> 0 | ... W4: =W2*(1-W3) -> 0
B5: Discount | C5: 0.02
B6: RE (ex VAT) | D6: =D4-D5 -> 0 | E6: =E4-E5 -> 0 | F6: =F4-F5 -> 0 | G6: =G4-G5 -> 0 | H6: =H4-H5 -> 0 | I6: =I4-I5 -> 0 | J6: =J4-J5 -> 0 | K6: =K4-K5 -> 0 | ... W6: =W4-W5 -> 0
B7: VAT | C7: 0.07 | D7: =D6*$C7 -> 0 | E7: =E6*$C7 -> 0 | F7: =F6*$C7 -> 0 | G7: =G6*$C7 -> 0 | H7: =H6*$C7 -> 0 | I7: =I6*$C7 -> 0 | J7: =J6*$C7 -> 0 | K7: =K6*$C7 -> 0 | ... W7: =W6*$C7 -> 0
B8: Net Price (inc VAT) | D8: =D6+D7 -> 0 | E8: =E6+E7 -> 0 | F8: =F6+F7 -> 0 | G8: =G6+G7 -> 0 | H8: =H6+H7 -> 0 | I8: =I6+I7 -> 0 | J8: =J6+J7 -> 0 | K8: =K6+K7 -> 0 | ... W8: =W6+W7 -> 0
B9: Transportation
B10: COGS | D10: =SUM(D8:D9) -> 0 | E10: =SUM(E8:E9) -> 0 | F10: =SUM(F8:F9) -> 0 | G10: =SUM(G8:G9) -> 0 | H10: =SUM(H8:H9) -> 0 | I10: =SUM(I8:I9) -> 0 | J10: =SUM(J8:J9) -> 0 | K10: =SUM(K8:K9) -> 0 | ... W10: =SUM(W8:W9) -> 0
B11: Promotion Rebate
B12: Net Cost | D12: =SUM(D10:D11) -> 0 | E12: =SUM(E10:E11) -> 0 | F12: =SUM(F10:F11) -> 0 | G12: =SUM(G10:G11) -> 0 | H12: =SUM(H10:H11) -> 0 | I12: =SUM(I10:I11) -> 0 | J12: =SUM(J10:J11) -> 0 | K12: =SUM(K10:K11) -> 0 | ... W12: =SUM(W10:W11) -> 0
B13: Price : SDM | D13: 0 | E13: 0 | F13: 0 | G13: 0 | H13: 0 | I13: 0 | J13: 0 | K13: 0 | L13: 0 | M13: 0 | N13: 0 | O13: 0 | P13: 0 | Q13: 0 | R13: 0 | S13: 0 | T13: 0 | U13: 0 | V13: 0 | W13: 0
B14: Price : W1 | D14: 308.9625 | E14: 338.3625 | F14: 0 | G14: 335.3595 | H14: 324.6705 | I14: 330.9495 | J14: 338.3625 | K14: 0 | L14: 0 | M14: 0 | N14: 319.515 | O14: 331.044 | P14: 308.9625 | Q14: 317.3625 | R14: 308.9625 | S14: 308.9625 | T14: 0 | U14: 359.4465 | V14: 0 | W14: 317.3625
B15: Price : W2 | D15: 323.675 | E15: 354.475 | F15: 0 | G15: 351.329 | H15: 340.131 | I15: 346.709 | J15: 354.475 | K15: 0 | L15: 0 | M15: 0 | N15: 334.73 | O15: 346.808 | P15: 323.675 | Q15: 332.475 | R15: 323.675 | S15: 323.675 | T15: 0 | U15: 376.563 | V15: 0 | W15: 332.475
B16: Price : R1 | D16: 338.3875 | E16: 370.5875 | F16: 0 | G16: 367.2985 | H16: 349.4073 | I16: 356.1647 | J16: 370.5875 | K16: 0 | L16: 0 | M16: 0 | N16: 349.945 | O16: 362.572 | P16: 338.3875 | Q16: 347.5875 | R16: 338.3875 | S16: 338.3875 | T16: 0 | U16: 393.6795 | V16: 0 | W16: 347.5875
B17: Price : R2 | D17: 353.1 | E17: 386.7 | F17: 0 | G17: 383.268 | H17: 355.5915 | I17: 362.4685 | J17: 386.7 | K17: 0 | L17: 0 | M17: 0 | N17: 365.16 | O17: 378.336 | P17: 353.1 | Q17: 362.7 | R17: 353.1 | S17: 353.1 | T17: 0 | U17: 410.796 | V17: 0 | W17: 362.7
B18: MG/Bht : SDM | D18: 0 | E18: 0 | F18: 0 | G18: 0 | H18: 0 | I18: 0 | J18: 0 | K18: 0 | L18: 0 | M18: 0 | N18: 0 | O18: 0 | P18: 0 | Q18: 0 | R18: 0 | S18: 0 | T18: 0 | U18: 0 | V18: 0 | W18: 0
B19: MG/Bht : W1 | D19: =D14-D12 -> 308.9625 | E19: =E14-E12 -> 338.3625 | F19: =F14-F12 -> 0 | G19: =G14-G12 -> 335.3595 | H19: =H14-H12 -> 324.6705 | I19: =I14-I12 -> 330.9495 | J19: =J14-J12 -> 338.3625 | K19: =K14-K12 -> 0 | ... W19: =W14-W12 -> 317.3625
B20: MG/Bht : W2 | D20: =+D15-D$12 -> 323.675 | E20: =+E15-E12 -> 354.475 | F20: =+F15-F12 -> 0 | G20: =+G15-G12 -> 351.329 | H20: =+H15-H12 -> 340.131 | I20: =+I15-I12 -> 346.709 | J20: =+J15-J12 -> 354.475 | K20: =+K15-K12 -> 0 | L20: =+L15-L12 -> 0 | ... P20: =+P15-P12 -> 323.675 | Q20: =+Q15-Q$12 -> 332.475 | R20: =+R15-R12 -> 323.675 | S20: =+S15-S12 -> 323.675 | T20: =+T15-T12 -> 0 | U20: =+U15-U12 -> 376.563 | V20: =+V15-V12 -> 0 | W20: =+W15-W12 -> 332.475
B21: MG/Bht : R1 | D21: =+D16-D$12 -> 338.3875 | E21: =+E16-E12 -> 370.5875 | F21: =+F16-F12 -> 0 | G21: =+G16-G12 -> 367.2985 | H21: =+H16-H12 -> 349.4073 | I21: =+I16-I12 -> 356.1647 | J21: =+J16-J12 -> 370.5875 | K21: =+K16-K12 -> 0 | L21: =+L16-L12 -> 0 | ... P21: =+P16-P12 -> 338.3875 | Q21: =+Q16-Q$12 -> 347.5875 | R21: =+R16-R12 -> 338.3875 | S21: =+S16-S12 -> 338.3875 | T21: =+T16-T12 -> 0 | U21: =+U16-U12 -> 393.6795 | V21: =+V16-V12 -> 0 | W21: =+W16-W12 -> 347.5875
B22: MG/Bht : R2 | D22: =+D17-D$12 -> 353.1 | E22: =+E17-E12 -> 386.7 | F22: =+F17-F12 -> 0 | G22: =+G17-G12 -> 383.268 | H22: =+H17-H12 -> 355.5915 | I22: =+I17-I12 -> 362.4685 | J22: =+J17-J12 -> 386.7 | K22: =+K17-K12 -> 0 | L22: =+L17-L12 -> 0 | ... P22: =+P17-P12 -> 353.1 | Q22: =+Q17-Q$12 -> 362.7 | R22: =+R17-R12 -> 353.1 | S22: =+S17-S12 -> 353.1 | T22: =+T17-T12 -> 0 | U22: =+U17-U12 -> 410.796 | V22: =+V17-V12 -> 0 | W22: =+W17-W12 -> 362.7
B23: MG/% : SDM | D23: 0 | E23: 0 | F23: 0 | G23: 0 | H23: 0 | I23: 0 | J23: 0 | K23: 0 | L23: 0 | M23: 0 | N23: 0 | O23: 0 | P23: 0 | Q23: 0 | R23: 0 | S23: 0 | T23: 0 | U23: 0 | V23: 0 | W23: 0
B24: MG/% : W1 | D24: =+D19/D12 -> #DIV/0! | E24: =+E19/E12 -> #DIV/0! | F24: =+F19/F12 -> #DIV/0! | G24: =+G19/G12 -> #DIV/0! | H24: =+H19/H12 -> #DIV/0! | I24: =+I19/I12 -> #DIV/0! | J24: =+J19/J12 -> #DIV/0! | K24: =+K19/K12 -> #DIV/0! | ... W24: =+W19/W12 -> #DIV/0!
B25: MG/% : W2 | D25: =+D20/D12 -> #DIV/0! | E25: =+E20/E12 -> #DIV/0! | F25: =+F20/F12 -> #DIV/0! | G25: =+G20/G12 -> #DIV/0! | H25: =+H20/H12 -> #DIV/0! | I25: =+I20/I12 -> #DIV/0! | J25: =+J20/J12 -> #DIV/0! | K25: =+K20/K12 -> #DIV/0! | ... W25: =+W20/W12 -> #DIV/0!
B26: MG/% : R1 | D26: =+D21/D12 -> #DIV/0! | E26: =+E21/E12 -> #DIV/0! | F26: =+F21/F12 -> #DIV/0! | G26: =+G21/G12 -> #DIV/0! | H26: =+H21/H12 -> #DIV/0! | I26: =+I21/I12 -> #DIV/0! | J26: =+J21/J12 -> #DIV/0! | K26: =+K21/K12 -> #DIV/0! | ... W26: =+W21/W12 -> #DIV/0!
B27: MG/% : R2 | D27: =+D22/D12 -> #DIV/0! | E27: =+E22/E12 -> #DIV/0! | F27: =+F22/F12 -> #DIV/0! | G27: =+G22/G12 -> #DIV/0! | H27: =+H22/H12 -> #DIV/0! | I27: =+I22/I12 -> #DIV/0! | J27: =+J22/J12 -> #DIV/0! | K27: =+K22/K12 -> #DIV/0! | ... W27: =+W22/W12 -> #DIV/0!
A29: Y06135005881060120 | B29: Safe 'n' Silent Pro 330 หนา 50 มม. 60*120 | D29: BKK | E29: CM | F29: CR | G29: PL | H29: NS | I29: KK | J29: SK | K29: UD | L29: UB | M29: NR | N29: RB | O29: PC | P29: BS | Q29: AY | R29: RY | S29: CB | T29: SR | U29: PK | V29: HY | W29: SB
B30: Price List
B31: Discount
D32: =D30*(1-D31) -> 0 | E32: =E30*(1-E31) -> 0 | F32: =F30*(1-F31) -> 0 | G32: =G30*(1-G31) -> 0 | H32: =H30*(1-H31) -> 0 | I32: =I30*(1-I31) -> 0 | J32: =J30*(1-J31) -> 0 | K32: =K30*(1-K31) -> 0 | ... W32: =W30*(1-W31) -> 0
B33: Discount | C33: 0.02
B34: RE (ex VAT) | D34: =D32-D33 -> 0 | E34: =E32-E33 -> 0 | F34: =F32-F33 -> 0 | G34: =G32-G33 -> 0 | H34: =H32-H33 -> 0 | I34: =I32-I33 -> 0 | J34: =J32-J33 -> 0 | K34: =K32-K33 -> 0 | ... W34: =W32-W33 -> 0
B35: VAT | C35: 0.07 | D35: =D34*$C35 -> 0 | E35: =E34*$C35 -> 0 | F35: =F34*$C35 -> 0 | G35: =G34*$C35 -> 0 | H35: =H34*$C35 -> 0 | I35: =I34*$C35 -> 0 | J35: =J34*$C35 -> 0 | K35: =K34*$C35 -> 0 | ... W35: =W34*$C35 -> 0
B36: Net Price (inc VAT) | D36: =D34+D35 -> 0 | E36: =E34+E35 -> 0 | F36: =F34+F35 -> 0 | G36: =G34+G35 -> 0 | H36: =H34+H35 -> 0 | I36: =I34+I35 -> 0 | J36: =J34+J35 -> 0 | K36: =K34+K35 -> 0 | ... W36: =W34+W35 -> 0
B37: Transportation | E37: 4.5 | G37: 11.67 | H37: 6.94 | I37: 9.72 | N37: 4.67 | O37: 9.76 | P37: 0 | Q37: 2.87 | U37: 22.32 | W37: 3.71
B38: COGS | D38: =SUM(D36:D37) -> 0 | E38: =SUM(E36:E37) -> 4.5 | F38: =SUM(F36:F37) -> 0 | G38: =SUM(G36:G37) -> 11.67 | H38: =SUM(H36:H37) -> 6.94 | I38: =SUM(I36:I37) -> 9.72 | J38: =SUM(J36:J37) -> 0 | K38: =SUM(K36:K37) -> 0 | ... W38: =SUM(W36:W37) -> 3.71
B39: Promotion Rebate
B40: Net Cost | D40: =SUM(D38:D39) -> 0 | E40: =SUM(E38:E39) -> 4.5 | F40: =SUM(F38:F39) -> 0 | G40: =SUM(G38:G39) -> 11.67 | H40: =SUM(H38:H39) -> 6.94 | I40: =SUM(I38:I39) -> 9.72 | J40: =SUM(J38:J39) -> 0 | K40: =SUM(K38:K39) -> 0 | ... W40: =SUM(W38:W39) -> 3.71
B41: Price : SDM | D41: 0 | E41: 0 | F41: 0 | G41: 0 | H41: 0 | I41: 0 | J41: 0 | K41: 0 | L41: 0 | M41: 0 | N41: 0 | O41: 0 | P41: 0 | Q41: 0 | R41: 0 | S41: 0 | T41: 0 | U41: 0 | V41: 0 | W41: 0
B42: Price : W1 | D42: 84.9366 | E42: 81.16794 | F42: 0 | G42: 88.69644 | H42: 83.72994 | I42: 86.64894 | J42: 0 | K42: 0 | L42: 0 | M42: 0 | N42: 81.34644 | O42: 86.69094 | P42: 76.44294 | Q42: 87.9501 | R42: 84.9366 | S42: 84.9366 | T42: 0 | U42: 99.87894 | V42: 0 | W42: 80.33844
B43: Price : W2 | D43: 86.55444 | E43: 82.713996 | F43: 0 | G43: 90.385896 | H43: 85.324796 | I43: 88.299396 | J43: 0 | K43: 0 | L43: 0 | M43: 0 | N43: 82.895896 | O43: 88.342196 | P43: 77.898996 | Q43: 89.62534 | R43: 86.55444 | S43: 86.55444 | T43: 0 | U43: 101.7814 | V43: 0 | W43: 81.868696
B44: Price : R1 | D44: 88.9812 | E44: 85.03308 | F44: 0 | G44: 92.92008 | H44: 87.71708 | I44: 90.77508 | J44: 0 | K44: 0 | L44: 0 | M44: 0 | N44: 85.22008 | O44: 90.81908 | P44: 80.08308 | Q44: 92.1382 | R44: 88.9812 | S44: 88.9812 | T44: 0 | U44: 104.63508 | V44: 0 | W44: 84.16408
B45: Price : R2 | D45: 93.0258 | E45: 88.89822 | F45: 0 | G45: 97.14372 | H45: 91.70422 | I45: 94.90122 | J45: 0 | K45: 0 | L45: 0 | M45: 0 | N45: 89.09372 | O45: 94.94722 | P45: 83.72322 | Q45: 96.3263 | R45: 93.0258 | S45: 93.0258 | T45: 0 | U45: 109.39122 | V45: 0 | W45: 87.98972
B46: MG/Bht : SDM | D46: 0 | E46: 0 | F46: 0 | G46: 0 | H46: 0 | I46: 0 | J46: 0 | K46: 0 | L46: 0 | M46: 0 | N46: 0 | O46: 0 | P46: 0 | Q46: 0 | R46: 0 | S46: 0 | T46: 0 | U46: 0 | V46: 0 | W46: 0
B47: MG/Bht : W1 | D47: =D42-D40 -> 84.9366 | E47: =E42-E40 -> 76.66794 | F47: =F42-F40 -> 0 | G47: =G42-G40 -> 77.02644 | H47: =H42-H40 -> 76.78994 | I47: =I42-I40 -> 76.92894 | J47: =J42-J40 -> 0 | K47: =K42-K40 -> 0 | ... W47: =W42-W40 -> 76.62844
B48: MG/Bht : W2 | D48: =+D43-D40 -> 86.55444 | E48: =+E43-E$14 -> -255.6485 | F48: =+F43-F$14 -> 0 | G48: =+G43-G$14 -> -244.9736 | H48: =+H43-H$14 -> -239.3457 | I48: =+I43-I$14 -> -242.6501 | J48: =+J43-J$14 -> -338.3625 | K48: =+K43-K$14 -> 0 | L48: =+L43-L$14 -> 0 | M48: =+M43-M$40 -> 0 | N48: =+N43-N$14 -> -236.6191 | O48: =+O43-O$14 -> -242.7018 | P48: =+P43-P$14 -> -231.0635 | Q48: =+Q43-Q40 -> 86.75534 | R48: =+R43-R$14 -> -222.40806 | S48: =+S43-S$14 -> -222.40806 | T48: =+T43-T$14 -> 0 | U48: =+U43-U$14 -> -257.6651 | V48: =+V43-V$14 -> 0 | W48: =+W43-W$14 -> -235.4938
B49: MG/Bht : R1 | D49: =+D44-D40 -> 88.9812 | E49: =+E44-E$14 -> -253.32942 | F49: =+F44-F$14 -> 0 | G49: =+G44-G$14 -> -242.43942 | H49: =+H44-H$14 -> -236.95342 | I49: =+I44-I$14 -> -240.17442 | J49: =+J44-J$14 -> -338.3625 | K49: =+K44-K$14 -> 0 | L49: =+L44-L$14 -> 0 | M49: =+M44-M$40 -> 0 | N49: =+N44-N$14 -> -234.29492 | O49: =+O44-O$14 -> -240.22492 | P49: =+P44-P$14 -> -228.87942 | Q49: =+Q44-Q40 -> 89.2682 | R49: =+R44-R$14 -> -219.9813 | S49: =+S44-S$14 -> -219.9813 | T49: =+T44-T$14 -> 0 | U49: =+U44-U$14 -> -254.81142 | V49: =+V44-V$14 -> 0 | W49: =+W44-W$14 -> -233.19842
B50: MG/Bht : R2 | D50: =+D45-D40 -> 93.0258 | E50: =+E45-E$14 -> -249.46428 | F50: =+F45-F$14 -> 0 | G50: =+G45-G$14 -> -238.21578 | H50: =+H45-H$14 -> -232.96628 | I50: =+I45-I$14 -> -236.04828 | J50: =+J45-J$14 -> -338.3625 | K50: =+K45-K$14 -> 0 | L50: =+L45-L$14 -> 0 | M50: =+M45-M$40 -> 0 | N50: =+N45-N$14 -> -230.42128 | O50: =+O45-O$14 -> -236.09678 | P50: =+P45-P$14 -> -225.23928 | Q50: =+Q45-Q40 -> 93.4563 | R50: =+R45-R$14 -> -215.9367 | S50: =+S45-S$14 -> -215.9367 | T50: =+T45-T$14 -> 0 | U50: =+U45-U$14 -> -250.05528 | V50: =+V45-V$14 -> 0 | W50: =+W45-W$14 -> -229.37278
B51: MG/% : SDM | D51: 0 | E51: 0 | F51: 0 | G51: 0 | H51: 0 | I51: 0 | J51: 0 | K51: 0 | L51: 0 | M51: 0 | N51: 0 | O51: 0 | P51: 0 | Q51: 0 | R51: 0 | S51: 0 | T51: 0 | U51: 0 | V51: 0 | W51: 0
B52: MG/% : W1 | D52: =+D47/D40 -> #DIV/0! | E52: =+E47/E40 -> 17.03732 | F52: =+F47/F40 -> #DIV/0! | G52: =+G47/G40 -> 6.6003805 | H52: =+H47/H40 -> 11.064833 | I52: =+I47/I40 -> 7.9145 | J52: =+J47/J40 -> #DIV/0! | K52: =+K47/K40 -> #DIV/0! | ... W52: =+W47/W40 -> 20.654566
B53: MG/% : W2 | D53: =+D48/D40 -> #DIV/0! | E53: =+E48/E40 -> -56.810779 | F53: =+F48/F40 -> #DIV/0! | G53: =+G48/G40 -> -20.99174 | H53: =+H48/H40 -> -34.487854 | I53: =+I48/I40 -> -24.964002 | J53: =+J48/J40 -> #DIV/0! | K53: =+K48/K40 -> #DIV/0! | ... W53: =+W48/W40 -> -63.475419
B54: MG/% : R1 | D54: =+D49/D40 -> #DIV/0! | E54: =+E49/E40 -> -56.295427 | F54: =+F49/F40 -> #DIV/0! | G54: =+G49/G40 -> -20.774586 | H54: =+H49/H40 -> -34.143144 | I54: =+I49/I40 -> -24.709302 | J54: =+J49/J40 -> #DIV/0! | K54: =+K49/K40 -> #DIV/0! | ... W54: =+W49/W40 -> -62.856717
B55: MG/% : R2 | D55: =+D50/D40 -> #DIV/0! | E55: =+E50/E40 -> -55.436507 | F55: =+F50/F40 -> #DIV/0! | G55: =+G50/G40 -> -20.412663 | H55: =+H50/H40 -> -33.568628 | I55: =+I50/I40 -> -24.284802 | J55: =+J50/J40 -> #DIV/0! | K55: =+K50/K40 -> #DIV/0! | ... W55: =+W50/W40 -> -61.825547
B56: MG/% : หน้าร้าน | D56: =+D51/D40 -> #DIV/0! | E56: =+E51/E40 -> 0 | F56: =+F51/F40 -> #DIV/0! | G56: =+G51/G40 -> 0 | H56: =+H51/H40 -> 0 | I56: =+I51/I40 -> 0 | J56: =+J51/J40 -> #DIV/0! | K56: =+K51/K40 -> #DIV/0! | ... W56: =+W51/W40 -> 0
A58: Y06135005882060120 | B58: Safe 'n' Silent Pro 330 หนา 75 มม. 60*120 | D58: BKK | E58: CM | F58: CR | G58: PL | H58: NS | I58: KK | J58: SK | K58: UD | L58: UB | M58: NR | N58: RB | O58: PC | P58: BS | Q58: AY | R58: RY | S58: CB | T58: SR | U58: PK | V58: HY | W58: SB
B59: Price List
B60: Discount
D61: =D59*(1-D60) -> 0 | E61: =E59*(1-E60) -> 0 | F61: =F59*(1-F60) -> 0 | G61: =G59*(1-G60) -> 0 | H61: =H59*(1-H60) -> 0 | I61: =I59*(1-I60) -> 0 | J61: =J59*(1-J60) -> 0 | K61: =K59*(1-K60) -> 0 | ... W61: =W59*(1-W60) -> 0
B62: Discount | C62: 0.02
B63: RE (ex VAT) | D63: =D61-D62 -> 0 | E63: =E61-E62 -> 0 | F63: =F61-F62 -> 0 | G63: =G61-G62 -> 0 | H63: =H61-H62 -> 0 | I63: =I61-I62 -> 0 | J63: =J61-J62 -> 0 | K63: =K61-K62 -> 0 | ... W63: =W61-W62 -> 0
B64: VAT | C64: 0.07 | D64: =D63*$C64 -> 0 | E64: =E63*$C64 -> 0 | F64: =F63*$C64 -> 0 | G64: =G63*$C64 -> 0 | H64: =H63*$C64 -> 0 | I64: =I63*$C64 -> 0 | J64: =J63*$C64 -> 0 | K64: =K63*$C64 -> 0 | ... W64: =W63*$C64 -> 0
B65: Net Price (inc VAT) | D65: =D63+D64 -> 0 | E65: =E63+E64 -> 0 | F65: =F63+F64 -> 0 | G65: =G63+G64 -> 0 | H65: =H63+H64 -> 0 | I65: =I63+I64 -> 0 | J65: =J63+J64 -> 0 | K65: =K63+K64 -> 0 | ... W65: =W63+W64 -> 0
B66: Transportation | E66: 23 | I66: 10.5 | Q66: 4.3 | U66: 25
B67: COGS | D67: =SUM(D65:D66) -> 0 | E67: =SUM(E65:E66) -> 23 | F67: =SUM(F65:F66) -> 0 | G67: =SUM(G65:G66) -> 0 | H67: =SUM(H65:H66) -> 0 | I67: =SUM(I65:I66) -> 10.5 | J67: =SUM(J65:J66) -> 0 | K67: =SUM(K65:K66) -> 0 | ... W67: =SUM(W65:W66) -> 0
B68: Promotion Rebate | X68: 131
B69: Net Cost | D69: =SUM(D67:D68) -> 0 | E69: =SUM(E67:E68) -> 23 | F69: =SUM(F67:F68) -> 0 | G69: =SUM(G67:G68) -> 0 | H69: =SUM(H67:H68) -> 0 | I69: =SUM(I67:I68) -> 10.5 | J69: =SUM(J67:J68) -> 0 | K69: =SUM(K67:K68) -> 0 | ... W69: =SUM(W67:W68) -> 0 | X69: 16
B70: Price : SDM | D70: 0 | E70: 0 | F70: 0 | G70: 0 | H70: 0 | I70: 0 | J70: 0 | K70: 0 | L70: 0 | M70: 0 | N70: 0 | O70: 0 | P70: 0 | Q70: 0 | R70: 0 | S70: 0 | T70: 0 | U70: 0 | V70: 0 | W70: 0
B71: Price : W1 | D71: 125.3826 | E71: 136.99434 | F71: 0 | G71: 0 | H71: 0 | I71: 123.86934 | J71: 0 | K71: 0 | L71: 0 | M71: 0 | N71: 0 | O71: 0 | P71: 0 | Q71: 129.8976 | R71: 0 | S71: 125.3826 | T71: 0 | U71: 151.6326 | V71: 0 | W71: 0 | X71: =X68*X69 -> 2096
B72: Price : W2 | D72: 127.77084 | E72: 139.60376 | F72: 0 | G72: 0 | H72: 0 | I72: 126.22876 | J72: 0 | K72: 0 | L72: 0 | M72: 0 | N72: 0 | O72: 0 | P72: 0 | Q72: 132.37184 | R72: 0 | S72: 127.77084 | T72: 0 | U72: 154.52084 | V72: 0 | W72: 0
B73: Price : R1 | D73: 131.3532 | E73: 143.51788 | F73: 0 | G73: 0 | H73: 0 | I73: 129.76788 | J73: 0 | K73: 0 | L73: 0 | M73: 0 | N73: 0 | O73: 0 | P73: 0 | Q73: 136.0832 | R73: 0 | S73: 131.3532 | T73: 0 | U73: 158.8532 | V73: 0 | W73: 0
B74: Price : R2 | D74: 137.3238 | E74: 150.04142 | F74: 0 | G74: 0 | H74: 0 | I74: 135.66642 | J74: 0 | K74: 0 | L74: 0 | M74: 0 | N74: 0 | O74: 0 | P74: 0 | Q74: 142.2688 | R74: 0 | S74: 137.3238 | T74: 0 | U74: 166.0738 | V74: 0 | W74: 0
B75: MG/Bht : SDM | D75: 0 | E75: 0 | F75: 0 | G75: 0 | H75: 0 | I75: 0 | J75: 0 | K75: 0 | L75: 0 | M75: 0 | N75: 0 | O75: 0 | P75: 0 | Q75: 0 | R75: 0 | S75: 0 | T75: 0 | U75: 0 | V75: 0 | W75: 0
B76: MG/Bht : W1 | D76: =D71-D69 -> 125.3826 | E76: =E71-E69 -> 113.99434 | F76: =F71-F69 -> 0 | G76: =G71-G69 -> 0 | H76: =H71-H69 -> 0 | I76: =I71-I69 -> 113.36934 | J76: =J71-J69 -> 0 | K76: =K71-K69 -> 0 | ... W76: =W71-W69 -> 0
B77: MG/Bht : W2 | D77: =+D72-D69 -> 127.77084 | E77: =+E72-E$14 -> -198.75874 | F77: =+F72-F$14 -> 0 | G77: =+G72-G$14 -> -335.3595 | H77: =+H72-H$14 -> -324.6705 | I77: =+I72-I$14 -> -204.72074 | J77: =+J72-J$14 -> -338.3625 | K77: =+K72-K$14 -> 0 | L77: =+L72-L$14 -> 0 | ... P77: =+P72-P$14 -> -308.9625 | Q77: =+Q72-Q69 -> 128.07184 | R77: =+R72-R$14 -> -308.9625 | S77: =+S72-S$14 -> -181.19166 | T77: =+T72-T$14 -> 0 | U77: =+U72-U69 -> 129.52084 | V77: =+V72-V$14 -> 0 | W77: =+W72-W$14 -> -317.3625
B78: MG/Bht : R1 | D78: =+D73-D69 -> 131.3532 | E78: =+E73-E$14 -> -194.84462 | F78: =+F73-F$14 -> 0 | G78: =+G73-G$14 -> -335.3595 | H78: =+H73-H$14 -> -324.6705 | I78: =+I73-I$14 -> -201.18162 | J78: =+J73-J$14 -> -338.3625 | K78: =+K73-K$14 -> 0 | L78: =+L73-L$14 -> 0 | ... P78: =+P73-P$14 -> -308.9625 | Q78: =+Q73-Q69 -> 131.7832 | R78: =+R73-R$14 -> -308.9625 | S78: =+S73-S$14 -> -177.6093 | T78: =+T73-T$14 -> 0 | U78: =+U73-U69 -> 133.8532 | V78: =+V73-V$14 -> 0 | W78: =+W73-W$14 -> -317.3625
B79: MG/Bht : R2 | D79: =+D74-D69 -> 137.3238 | E79: =+E74-E$14 -> -188.32108 | F79: =+F74-F$14 -> 0 | G79: =+G74-G$14 -> -335.3595 | H79: =+H74-H$14 -> -324.6705 | I79: =+I74-I$14 -> -195.28308 | J79: =+J74-J$14 -> -338.3625 | K79: =+K74-K$14 -> 0 | L79: =+L74-L$14 -> 0 | ... P79: =+P74-P$14 -> -308.9625 | Q79: =+Q74-Q69 -> 137.9688 | R79: =+R74-R$14 -> -308.9625 | S79: =+S74-S$14 -> -171.6387 | T79: =+T74-T$14 -> 0 | U79: =+U74-U69 -> 141.0738 | V79: =+V74-V$14 -> 0 | W79: =+W74-W$14 -> -317.3625
B80: MG/% : SDM | D80: 0 | E80: 0 | F80: 0 | G80: 0 | H80: 0 | I80: 0 | J80: 0 | K80: 0 | L80: 0 | M80: 0 | N80: 0 | O80: 0 | P80: 0 | Q80: 0 | R80: 0 | S80: 0 | T80: 0 | U80: 0 | V80: 0 | W80: 0
B81: MG/% : W1 | D81: =+D76/D69 -> #DIV/0! | E81: =+E76/E69 -> 4.9562757 | F81: =+F76/F69 -> #DIV/0! | G81: =+G76/G69 -> #DIV/0! | H81: =+H76/H69 -> #DIV/0! | I81: =+I76/I69 -> 10.79708 | J81: =+J76/J69 -> #DIV/0! | K81: =+K76/K69 -> #DIV/0! | ... W81: =+W76/W69 -> #DIV/0!
B82: MG/% : W2 | D82: =+D77/D69 -> #DIV/0! | E82: =+E77/E72 -> -1.4237349 | F82: =+F77/F72 -> #DIV/0! | G82: =+G77/G72 -> #DIV/0! | H82: =+H77/H72 -> #DIV/0! | I82: =+I77/I72 -> -1.6218234 | J82: =+J77/J72 -> #DIV/0! | K82: =+K77/K72 -> #DIV/0! | L82: =+L77/L72 -> #DIV/0! | ... P82: =+P77/P72 -> #DIV/0! | Q82: =+Q77/Q69 -> 29.784149 | R82: =+R77/R72 -> #DIV/0! | S82: =+S77/S72 -> -1.4180987 | T82: =+T77/T72 -> #DIV/0! | U82: =+U77/U69 -> 5.1808336 | V82: =+V77/V72 -> #DIV/0! | W82: =+W77/W72 -> #DIV/0!
B83: MG/% : R1 | D83: =+D78/D69 -> #DIV/0! | E83: =+E78/E73 -> -1.3576331 | F83: =+F78/F73 -> #DIV/0! | G83: =+G78/G73 -> #DIV/0! | H83: =+H78/H73 -> #DIV/0! | I83: =+I78/I73 -> -1.5503191 | J83: =+J78/J73 -> #DIV/0! | K83: =+K78/K73 -> #DIV/0! | L83: =+L78/L73 -> #DIV/0! | ... P83: =+P78/P73 -> #DIV/0! | Q83: =+Q78/Q69 -> 30.647256 | R83: =+R78/R73 -> #DIV/0! | S83: =+S78/S73 -> -1.3521505 | T83: =+T78/T73 -> #DIV/0! | U83: =+U78/U69 -> 5.354128 | V83: =+V78/V73 -> #DIV/0! | W83: =+W78/W73 -> #DIV/0!
B84: MG/% : R2 | D84: =+D79/D69 -> #DIV/0! | E84: =+E79/E74 -> -1.2551273 | F84: =+F79/F74 -> #DIV/0! | G84: =+G79/G74 -> #DIV/0! | H84: =+H79/H74 -> #DIV/0! | I84: =+I79/I74 -> -1.4394356 | J84: =+J79/J74 -> #DIV/0! | K84: =+K79/K74 -> #DIV/0! | L84: =+L79/L74 -> #DIV/0! | ... P84: =+P79/P74 -> #DIV/0! | Q84: =+Q79/Q69 -> 32.085767 | R84: =+R79/R74 -> #DIV/0! | S84: =+S79/S74 -> -1.2498831 | T84: =+T79/T74 -> #DIV/0! | U84: =+U79/U69 -> 5.642952 | V84: =+V79/V74 -> #DIV/0! | W84: =+W79/W74 -> #DIV/0!
B85: MG/% : หน้าร้าน | D85: =+D80/D69 -> #DIV/0! | E85: =+E80/E75 -> #DIV/0! | F85: =+F80/F75 -> #DIV/0! | G85: =+G80/G75 -> #DIV/0! | H85: =+H80/H75 -> #DIV/0! | I85: =+I80/I75 -> #DIV/0! | J85: =+J80/J75 -> #DIV/0! | K85: =+K80/K75 -> #DIV/0! | L85: =+L80/L75 -> #DIV/0! | ... P85: =+P80/P75 -> #DIV/0! | Q85: =+Q80/Q69 -> 0 | R85: =+R80/R75 -> #DIV/0! | S85: =+S80/S75 -> #DIV/0! | T85: =+T80/T75 -> #DIV/0! | U85: =+U80/U75 -> #DIV/0! | V85: =+V80/V75 -> #DIV/0! | W85: =+W80/W75 -> #DIV/0!
A87: Y06135005981060120 | B87: Safe 'n' Silent Pro 350 หนา 50 มม. 60*120 | D87: BKK | E87: CM | F87: CR | G87: PL | H87: NS | I87: KK | J87: SK | K87: UD | L87: UB | M87: NR | N87: RB | O87: PC | P87: BS | Q87: AY | R87: RY | S87: CB | T87: SR | U87: PK | V87: HY | W87: SB
B88: Price List
B89: Discount
D90: =D88*(1-D89) -> 0 | E90: =E88*(1-E89) -> 0 | F90: =F88*(1-F89) -> 0 | G90: =G88*(1-G89) -> 0 | H90: =H88*(1-H89) -> 0 | I90: =I88*(1-I89) -> 0 | J90: =J88*(1-J89) -> 0 | K90: =K88*(1-K89) -> 0 | ... W90: =W88*(1-W89) -> 0
B91: Discount | C91: 0.02 | E91: =E90*$C91 -> 0 | F91: =F90*$C91 -> 0 | G91: =G90*$C91 -> 0 | H91: =H90*$C91 -> 0 | I91: =I90*$C91 -> 0 | J91: =J90*$C91 -> 0 | K91: =K90*$C91 -> 0 | L91: =L90*$C91 -> 0 | ... W91: =W90*$C91 -> 0
B92: RE (ex VAT) | D92: =D90-D91 -> 0 | E92: =E90-E91 -> 0 | F92: =F90-F91 -> 0 | G92: =G90-G91 -> 0 | H92: =H90-H91 -> 0 | I92: =I90-I91 -> 0 | J92: =J90-J91 -> 0 | K92: =K90-K91 -> 0 | ... W92: =W90-W91 -> 0
B93: VAT | C93: 0.07 | D93: =D92*$C93 -> 0 | E93: =E92*$C93 -> 0 | F93: =F92*$C93 -> 0 | G93: =G92*$C93 -> 0 | H93: =H92*$C93 -> 0 | I93: =I92*$C93 -> 0 | J93: =J92*$C93 -> 0 | K93: =K92*$C93 -> 0 | ... W93: =W92*$C93 -> 0
B94: Net Price (inc VAT) | D94: =D92+D93 -> 0 | E94: =E92+E93 -> 0 | F94: =F92+F93 -> 0 | G94: =G92+G93 -> 0 | H94: =H92+H93 -> 0 | I94: =I92+I93 -> 0 | J94: =J92+J93 -> 0 | K94: =K92+K93 -> 0 | ... W94: =W92+W93 -> 0
B95: Transportation
B96: COGS | D96: =SUM(D94:D95) -> 0 | E96: =SUM(E94:E95) -> 0 | F96: =SUM(F94:F95) -> 0 | G96: =SUM(G94:G95) -> 0 | H96: =SUM(H94:H95) -> 0 | I96: =SUM(I94:I95) -> 0 | J96: =SUM(J94:J95) -> 0 | K96: =SUM(K94:K95) -> 0 | ... W96: =SUM(W94:W95) -> 0
B97: Promotion Rebate
B98: Net Cost | D98: =SUM(D96:D97) -> 0 | E98: =SUM(E96:E97) -> 0 | F98: =SUM(F96:F97) -> 0 | G98: =SUM(G96:G97) -> 0 | H98: =SUM(H96:H97) -> 0 | I98: =SUM(I96:I97) -> 0 | J98: =SUM(J96:J97) -> 0 | K98: =SUM(K96:K97) -> 0 | ... W98: =SUM(W96:W97) -> 0
B99: Price : SDM | D99: 0 | E99: 0 | F99: 0 | G99: 0 | H99: 0 | I99: 0 | J99: 0 | K99: 0 | L99: 0 | M99: 0 | N99: 0 | O99: 0 | P99: 0 | Q99: 0 | R99: 0 | S99: 0 | T99: 0 | U99: 0 | V99: 0 | W99: 0
B100: Price : W1 | D100: 128.8048 | E100: 0 | F100: 0 | G100: 0 | H100: 0 | I100: 0 | J100: 0 | K100: 0 | L100: 0 | M100: 0 | N100: 0 | O100: 0 | P100: 0 | Q100: 0 | R100: 0 | S100: 0 | T100: 0 | U100: 0 | V100: 0 | W100: 0
B101: Price : W2 | D101: 129.8048 | E101: 0 | F101: 0 | G101: 0 | H101: 0 | I101: 0 | J101: 0 | K101: 0 | L101: 0 | M101: 0 | N101: 0 | O101: 0 | P101: 0 | Q101: 0 | R101: 0 | S101: 0 | T101: 0 | U101: 0 | V101: 0 | W101: 0
B102: Price : R1 | D102: 131.8048 | E102: 0 | F102: 0 | G102: 0 | H102: 0 | I102: 0 | J102: 0 | K102: 0 | L102: 0 | M102: 0 | N102: 0 | O102: 0 | P102: 0 | Q102: 0 | R102: 0 | S102: 0 | T102: 0 | U102: 0 | V102: 0 | W102: 0
B103: Price : R2 | D103: 134.8048 | E103: 0 | F103: 0 | G103: 0 | H103: 0 | I103: 0 | J103: 0 | K103: 0 | L103: 0 | M103: 0 | N103: 0 | O103: 0 | P103: 0 | Q103: 0 | R103: 0 | S103: 0 | T103: 0 | U103: 0 | V103: 0 | W103: 0
...

Sheet BKK DCM
A1: Internal Memo | E1: No.
A2: To : | B2: ผู้จัดการภาค / ผู้จัดการเขต | E2: Date :
A3: RE :
A4: หมายเหตุ : | B4: 1 | C4: ราคาขายข้างต้นรวม VAT
B5: 2 | C5: หากราคาข้างต้นสูง ไม่สามารถขายได้ โปรดสอบถาม ผจก.PM
B6: 3 | C6: ราคาขายข้างต้นให้ถือเป็นราคาขายต่ำสุด สามารถขายที่ราคาสูงกว่านี้ได้ ขึ้นอยู่กับแต่ละพื้นที่
B7: 4 | C7: ปริมาณการขายส่งแผ่น 120x240 ขั้นต่ำ 400 แผ่น : เดือน
B8: 5 | C8: ราคา RE (EX VAT) และไม่รวมค่าขนส่ง ยังไม่หักรีเบทประจำเดือน
A10: BKK Price | D10: BKK
A11: Y 1: Gypsum | C11: WIP | D11: WIPR | E11: WIPRSO
B12: W1 | C12: W2 | D12: R1 | E12: R2
A13: ยิปซัม ธรรมดา 9 มม. ขอบเรียบ/ลาด | B13: ='Formular 4 step Y1'!D14 -> 124 | C13: ='Formular 4 step Y1'!D15 -> 125 | D13: ='Formular 4 step Y1'!D16 -> 126 | E13: ='Formular 4 step Y1'!D17 -> 127
A14: ยิปซัม ธรรมดา 9 มม. ขอบลาด 4 ด้าน | B14: ='Formular 4 step Y1'!D39 -> 124 | C14: ='Formular 4 step Y1'!D40 -> 125 | D14: ='Formular 4 step Y1'!D41 -> 126 | E14: ='Formular 4 step Y1'!D42 -> 127
A15: ยิปซัม ทนชื้น/ฟลอยด์ 9 มม. ขอบเรียบ/ลาด | B15: ='Formular 4 step Y1'!D64 -> 185 | C15: ='Formular 4 step Y1'!D65 -> 186 | D15: ='Formular 4 step Y1'!D66 -> 187 | E15: ='Formular 4 step Y1'!D67 -> 188
A16: ยิปซัม ทนชื้น/ฟลอยด์ 9 มม. ขอบลาด 4 ด้าน | B16: ='Formular 4 step Y1'!D89 -> 184 | C16: ='Formular 4 step Y1'!D90 -> 185 | D16: ='Formular 4 step Y1'!D91 -> 186 | E16: ='Formular 4 step Y1'!D92 -> 187
A17: ยิปซัม ธรรมดา 12 มม. ขอบเรียบ/ลาด | B17: ='Formular 4 step Y1'!D114 -> 143 | C17: ='Formular 4 step Y1'!D115 -> 144 | D17: ='Formular 4 step Y1'!D116 -> 145 | E17: ='Formular 4 step Y1'!D117 -> 146
A18: ยิปซัม ทนชื้น/ฟลอยด์ 12 มม. ขอบเรียบ/ลาด | B18: ='Formular 4 step Y1'!D139 -> 206 | C18: ='Formular 4 step Y1'!D140 -> 207 | D18: ='Formular 4 step Y1'!D141 -> 208 | E18: ='Formular 4 step Y1'!D142 -> 209
A19: ยิปซัม ธรรมดา 15 มม. ขอบลาด | B19: ='Formular 4 step Y1'!D838 -> 205 | C19: ='Formular 4 step Y1'!D839 -> 206 | D19: ='Formular 4 step Y1'!D840 -> 207 | E19: ='Formular 4 step Y1'!D841 -> 208
A20: ทนไฟ 12 มม. | B20: ='Formular 4 step Y1'!D164 -> 241 | C20: ='Formular 4 step Y1'!D165 -> 244 | D20: ='Formular 4 step Y1'!D166 -> 249 | E20: ='Formular 4 step Y1'!D167 -> 254
A21: ทนไฟ 15 มม. | B21: ='Formular 4 step Y1'!D189 -> 269 | C21: ='Formular 4 step Y1'!D190 -> 272 | D21: ='Formular 4 step Y1'!D191 -> 277 | E21: ='Formular 4 step Y1'!D192 -> 282
A22: ยิปซัมเฟล็กบอร์ด(ดัดโค้ง) 6 มม. 120*240 มม. | B22: ='Formular 4 step Y1'!D863 -> 178.69762 | C22: ='Formular 4 step Y1'!D864 -> 180.35223 | D22: ='Formular 4 step Y1'!D865 -> 185.31605 | E22: ='Formular 4 step Y1'!D866 -> 190.27987
A23: อี่ซี่บอร์ท / คนอฟ | B23: ='Formular 4 step Y1'!D738 -> 101 | C23: ='Formular 4 step Y1'!D739 -> 102 | D23: ='Formular 4 step Y1'!D740 -> 103 | E23: ='Formular 4 step Y1'!D741 -> 104
A24: อี่ซี่บอร์ท/คนอฟ ทนชื้น / ฟอล์ย | B24: ='Formular 4 step Y1'!D763 -> 156 | C24: ='Formular 4 step Y1'!D764 -> 157 | D24: ='Formular 4 step Y1'!D765 -> 158 | E24: ='Formular 4 step Y1'!D766 -> 159
A25: เวเทอร์บล็อค W0 | B25: ='Formular 4 step Y1'!D788 -> 268 | C25: ='Formular 4 step Y1'!D789 -> 269 | D25: ='Formular 4 step Y1'!D790 -> 270 | E25: ='Formular 4 step Y1'!D791 -> 271
A26: เวเทอร์บล็อค W1 | B26: ='Formular 4 step Y1'!D813 -> 425 | C26: ='Formular 4 step Y1'!D814 -> 426 | D26: ='Formular 4 step Y1'!D815 -> 427 | E26: ='Formular 4 step Y1'!D816 -> 428
A27: ยิปซัมลดเสียงสะท้อน เอคโค่บล็อค (R1,R2,R8,S8) | B27: ='Formular 4 step Y1'!D214 -> 904 | C27: ='Formular 4 step Y1'!D215 -> 907 | D27: ='Formular 4 step Y1'!D216 -> 917 | E27: ='Formular 4 step Y1'!D217 -> 927
A28: Paper touch ลวดลาย 60*60*8 mm. | B28: ='Formular 4 step Y1'!D239 -> 20.902296 | C28: ='Formular 4 step Y1'!D240 -> 22 | D28: ='Formular 4 step Y1'!D241 -> 23 | E28: ='Formular 4 step Y1'!D242 -> 24
A29: Paper touch หยาดเพชร 60*60*8 mm. | B29: ='Formular 4 step Y1'!D264 -> 20.189248 | C29: ='Formular 4 step Y1'!D265 -> 21 | D29: ='Formular 4 step Y1'!D266 -> 22 | E29: ='Formular 4 step Y1'!D267 -> 23
A30: Paper touch หยาดเพชร 60*60*8 mm. กันร้อน | B30: ='Formular 4 step Y1'!D289 -> 23.754488 | C30: ='Formular 4 step Y1'!D290 -> 25 | D30: ='Formular 4 step Y1'!D291 -> 26 | E30: ='Formular 4 step Y1'!D292 -> 27
A31: Color touch สีมุก/สีเพชร 60x60*9 mm. | B31: ='Formular 4 step Y1'!D313 -> 23 | C31: ='Formular 4 step Y1'!D314 -> 24 | D31: ='Formular 4 step Y1'!D315 -> 25 | E31: ='Formular 4 step Y1'!D316 -> 26
A32: Color touch สีมุก/สีเพชร 60x120*9 mm. | B32: ='Formular 4 step Y1'!D338 -> 46 | C32: ='Formular 4 step Y1'!D339 -> 47 | D32: ='Formular 4 step Y1'!D340 -> 48 | E32: ='Formular 4 step Y1'!D341 -> 50
A33: Color touch สีมุก/สีเพชร 60x120*12 mm. | B33: ='Formular 4 step Y1'!D888 -> 46.911609 | C33: ='Formular 4 step Y1'!D889 -> 47.5 | D33: ='Formular 4 step Y1'!D890 -> 48.202754 | E33: ='Formular 4 step Y1'!D891 -> 49.493899
A34: Color touch สีมุก/สีเพชร 60x60*9 mm. ทนชื้น | B34: ='Formular 4 step Y1'!D363 -> 28 | C34: ='Formular 4 step Y1'!D364 -> 29 | D34: ='Formular 4 step Y1'!D365 -> 31 | E34: ='Formular 4 step Y1'!D366 -> 32
A35: Color touch สีมุก/สีเพชร 60x120*9 mm. ทนชื้น | B35: ='Formular 4 step Y1'!D388 -> 57 | C35: ='Formular 4 step Y1'!D389 -> 58 | D35: ='Formular 4 step Y1'!D390 -> 59 | E35: ='Formular 4 step Y1'!D391 -> 61
A36: Color touch สีมุก/สีเพชร 60x120*12 mm. ทนชื้น | B36: ='Formular 4 step Y1'!D913 -> 63.551024 | C36: ='Formular 4 step Y1'!D914 -> 64.5 | D36: ='Formular 4 step Y1'!D915 -> 65.300135 | E36: ='Formular 4 step Y1'!D916 -> 67.049246
A37: เซิฟบอร์ด ขนาด 30 ซม. | B37: ='Formular 4 step Y1'!D413 -> 189 | C37: ='Formular 4 step Y1'!D414 -> 190 | D37: ='Formular 4 step Y1'!D415 -> 195 | E37: ='Formular 4 step Y1'!D416 -> 200
A38: เซิฟบอร์ด ขนาด 45 ซม. | B38: ='Formular 4 step Y1'!D438 -> 260 | C38: ='Formular 4 step Y1'!D439 -> 262 | D38: ='Formular 4 step Y1'!D440 -> 264 | E38: ='Formular 4 step Y1'!D441 -> 266
A39: เซิฟบอร์ด ขนาด 60 ซม. | B39: ='Formular 4 step Y1'!D463 -> 319 | C39: ='Formular 4 step Y1'!D464 -> 321 | D39: ='Formular 4 step Y1'!D465 -> 323 | E39: ='Formular 4 step Y1'!D466 -> 325
A40: เซิฟบอร์ด ขนาด 60*120 ซม. | B40: ='Formular 4 step Y1'!D488 -> 771 | C40: ='Formular 4 step Y1'!D489 -> 773 | D40: ='Formular 4 step Y1'!D490 -> 778 | E40: ='Formular 4 step Y1'!D491 -> 783
A41: เซิฟบอร์ด ขนาด 30 ซม. ทนชื้น | B41: ='Formular 4 step Y1'!D513 -> 257 | C41: ='Formular 4 step Y1'!D514 -> 259 | D41: ='Formular 4 step Y1'!D515 -> 262 | E41: ='Formular 4 step Y1'!D516 -> 264
A42: เซิฟบอร์ด ขนาด 45 ซม. ทนชื้น | B42: ='Formular 4 step Y1'!D538 -> 321 | C42: ='Formular 4 step Y1'!D539 -> 323 | D42: ='Formular 4 step Y1'!D540 -> 326 | E42: ='Formular 4 step Y1'!D541 -> 328
A43: เซิฟบอร์ด ขนาด 60 ซม. ทนชื้น | B43: ='Formular 4 step Y1'!D563 -> 385 | C43: ='Formular 4 step Y1'!D564 -> 387 | D43: ='Formular 4 step Y1'!D565 -> 389 | E43: ='Formular 4 step Y1'!D566 -> 391
A44: เซิฟบอร์ด ขนาด 60*120 ซม. ทนชื้น | B44: ='Formular 4 step Y1'!D588 -> 967 | C44: ='Formular 4 step Y1'!D589 -> 977 | D44: ='Formular 4 step Y1'!D590 -> 982 | E44: ='Formular 4 step Y1'!D591 -> 987
A45: อะคูสติก กาแลคซี่ | B45: ='Formular 4 step Y1'!D613 -> 147.32653 | C45: ='Formular 4 step Y1'!D614 -> 148 | D45: ='Formular 4 step Y1'!D615 -> 149 | E45: ='Formular 4 step Y1'!D616 -> 151
A46: อะคูสติก-อิมเพรสชันME903 | B46: ='Formular 4 step Y1'!D638 -> 96 | C46: ='Formular 4 step Y1'!D639 -> 98 | D46: ='Formular 4 step Y1'!D640 -> 99 | E46: ='Formular 4 step Y1'!D641 -> 100
A47: อะคูสติก-อิมเพรสชันME904 | B47: ='Formular 4 step Y1'!D663 -> 182 | C47: ='Formular 4 step Y1'!D664 -> 183 | D47: ='Formular 4 step Y1'!D665 -> 185 | E47: ='Formular 4 step Y1'!D666 -> 187
A48: อะคูสติก-อิมเพรสชันME905 | B48: ='Formular 4 step Y1'!D688 -> 138 | C48: ='Formular 4 step Y1'!D689 -> 140 | D48: ='Formular 4 step Y1'!D690 -> 142 | E48: ='Formular 4 step Y1'!D691 -> 145
A49: อะคูสติก-อิมเพรสชันME908 | B49: ='Formular 4 step Y1'!D713 -> 264 | C49: ='Formular 4 step Y1'!D714 -> 265 | D49: ='Formular 4 step Y1'!D715 -> 266 | E49: ='Formular 4 step Y1'!D716 -> 267
A54: BKK Price | D54: BKK
A55: Y1 : Smart Board | C55: WIP | D55: WIPR | E55: WIPRSO
B56: W1 | C56: W2 | D56: R1 | E56: R2
A57: SB 120x240 4 mm ตราช้าง | B57: ='สูตร 4 step SB'!D13 -> 156 | C57: ='สูตร 4 step SB'!D14 -> 159 | D57: ='สูตร 4 step SB'!D15 -> 161 | E57: ='สูตร 4 step SB'!D16 -> 163
A58: SB 120x120 4 mm ตราช้าง | B58: ='สูตร 4 step SB'!D41 -> 79 | C58: ='สูตร 4 step SB'!D42 -> 81 | D58: ='สูตร 4 step SB'!D43 -> 82 | E58: ='สูตร 4 step SB'!D44 -> 83
A59: SB 60x240 4 mm ตราช้าง | B59: ='สูตร 4 step SB'!D68 -> 78 | C59: ='สูตร 4 step SB'!D69 -> 80 | D59: ='สูตร 4 step SB'!D70 -> 81 | E59: ='สูตร 4 step SB'!D71 -> 83
A60: SB 60x120 4 mm ตราช้าง | B60: ='สูตร 4 step SB'!D344 -> 43 | C60: ='สูตร 4 step SB'!D345 -> 44 | D60: ='สูตร 4 step SB'!D346 -> 45 | E60: ='สูตร 4 step SB'!D347 -> 46
A61: SB 120x240 6 mm ตราช้าง | B61: ='สูตร 4 step SB'!D96 -> 237 | C61: ='สูตร 4 step SB'!D97 -> 241 | D61: ='สูตร 4 step SB'!D98 -> 243 | E61: ='สูตร 4 step SB'!D99 -> 245
A62: SB 120x240 8 mm ตราช้าง | B62: ='สูตร 4 step SB'!D124 -> 331 | C62: ='สูตร 4 step SB'!D125 -> 336 | D62: ='สูตร 4 step SB'!D126 -> 341 | E62: ='สูตร 4 step SB'!D127 -> 345
A63: SB 120x240 10 mm ตราช้าง | B63: ='สูตร 4 step SB'!D152 -> 474 | C63: ='สูตร 4 step SB'!D153 -> 479 | D63: ='สูตร 4 step SB'!D154 -> 484 | E63: ='สูตร 4 step SB'!D155 -> 489
A64: SB 120x240 12 mm ตราช้าง | B64: ='สูตร 4 step SB'!D179 -> 575 | C64: ='สูตร 4 step SB'!D180 -> 580 | D64: ='สูตร 4 step SB'!D181 -> 585 | E64: ='สูตร 4 step SB'!D182 -> 590
A65: SB 120x240 15 mm ตราช้าง | B65: ='สูตร 4 step SB'!D645 -> 660 | C65: ='สูตร 4 step SB'!D646 -> 670 | D65: ='สูตร 4 step SB'!D647 -> 680 | E65: ='สูตร 4 step SB'!D648 -> 685
A66: SB 120x240 16 mm ตราช้าง | B66: ='สูตร 4 step SB'!D672 -> 698 | C66: ='สูตร 4 step SB'!D673 -> 708 | D66: ='สูตร 4 step SB'!D674 -> 718 | E66: ='สูตร 4 step SB'!D675 -> 728
A67: SB 120x240 18 mm ตราช้าง | B67: ='สูตร 4 step SB'!D699 -> 787 | C67: ='สูตร 4 step SB'!D700 -> 797 | D67: ='สูตร 4 step SB'!D701 -> 817 | E67: ='สูตร 4 step SB'!D702 -> 827
A68: SB 120x240 20 mm ตราช้าง | B68: ='สูตร 4 step SB'!D726 -> 882 | C68: ='สูตร 4 step SB'!D727 -> 892 | D68: ='สูตร 4 step SB'!D728 -> 907 | E68: ='สูตร 4 step SB'!D729 -> 922
A69: SB 120x280 8 mm ตราช้าง | B69: ='สูตร 4 step SB'!D206 -> 425 | C69: ='สูตร 4 step SB'!D207 -> 430 | D69: ='สูตร 4 step SB'!D208 -> 435 | E69: ='สูตร 4 step SB'!D209 -> 440
A70: ลายไม้/เซาะร่อง ตราช้าง | B70: ='สูตร 4 step SB'!D234 -> 53 | C70: ='สูตร 4 step SB'!D235 -> 54 | D70: ='สูตร 4 step SB'!D236 -> 55 | E70: ='สูตร 4 step SB'!D237 -> 56
A71: ระบายอากาศ ตราช้าง | B71: ='สูตร 4 step SB'!D262 -> 49 | C71: ='สูตร 4 step SB'!D263 -> 50 | D71: ='สูตร 4 step SB'!D264 -> 51 | E71: ='สูตร 4 step SB'!D265 -> 52
A72: ระบายอากาศโพรเทคชั่น ตราช้าง | B72: ='สูตร 4 step SB'!D618 -> 68 | C72: ='สูตร 4 step SB'!D619 -> 69 | D72: ='สูตร 4 step SB'!D620 -> 70 | E72: ='สูตร 4 step SB'!D621 -> 71
A73: ลายไม้ ระบายอากาศ /เซาะร่อง ระบายอากาศ ตราช้าง | B73: ='สูตร 4 step SB'!D290 -> 56 | C73: ='สูตร 4 step SB'!D291 -> 57 | D73: ='สูตร 4 step SB'!D292 -> 58 | E73: ='สูตร 4 step SB'!D293 -> 59
A74: ลายไม้/เซาะร่อง (ระบายอากาศ โพรเทคชั่น) ตราช้าง | B74: ='สูตร 4 step SB'!D318 -> 75 | C74: ='สูตร 4 step SB'!D319 -> 77 | D74: ='สูตร 4 step SB'!D320 -> 78 | E74: ='สูตร 4 step SB'!D321 -> 80
A76: บอร์ดซูปเปอร์ซัน 4 มม.120x240 | B76: ='สูตร 4 step SB'!D426 -> 116 | C76: ='สูตร 4 step SB'!D427 -> 118 | D76: ='สูตร 4 step SB'!D428 -> 120 | E76: ='สูตร 4 step SB'!D429 -> 122
A77: บอร์ดซูปเปอร์ซัน 4 มม.120x120 | B77: ='สูตร 4 step SB'!D454 -> 59 | C77: ='สูตร 4 step SB'!D455 -> 60 | D77: ='สูตร 4 step SB'!D456 -> 61 | E77: ='สูตร 4 step SB'!D457 -> 62
A78: บอร์ดซูปเปอร์ซัน 4 มม.60x240 | B78: ='สูตร 4 step SB'!D481 -> 59 | C78: ='สูตร 4 step SB'!D482 -> 60 | D78: ='สูตร 4 step SB'!D483 -> 61 | E78: ='สูตร 4 step SB'!D484 -> 62
A79: บอร์ดซูปเปอร์ซัน 6 มม.120x240 | B79: ='สูตร 4 step SB'!D509 -> 176 | C79: ='สูตร 4 step SB'!D510 -> 179 | D79: ='สูตร 4 step SB'!D511 -> 181 | E79: ='สูตร 4 step SB'!D512 -> 183
A80: บอร์ดซูปเปอร์ซัน 8 มม.120x240 | B80: ='สูตร 4 step SB'!D591 -> 271 | C80: ='สูตร 4 step SB'!D592 -> 275 | D80: ='สูตร 4 step SB'!D593 -> 277 | E80: ='สูตร 4 step SB'!D594 -> 279
A81: บอร์ดซูปเปอร์ซัน 15 มม.120x241 | B81: ='สูตร 4 step SB'!D1198 -> 533 | C81: ='สูตร 4 step SB'!D1199 -> 543 | D81: ='สูตร 4 step SB'!D1200 -> 553 | E81: ='สูตร 4 step SB'!D1201 -> 563
A82: บอร์ดซูปเปอร์ซัน 20 มม.120x242
A84: ไม้มอบ ตราช้าง | B84: ='สูตร 4 step SB'!D370 -> 45 | C84: ='สูตร 4 step SB'!D371 -> 46 | D84: ='สูตร 4 step SB'!D372 -> 47 | E84: ='สูตร 4 step SB'!D373 -> 48
A85: ไม้ระแนงลบมุม ซิเมนต็ 7.5 ตราช้าง | B85: ='สูตร 4 step SB'!D398 -> 38 | C85: ='สูตร 4 step SB'!D399 -> 39 | D85: ='สูตร 4 step SB'!D400 -> 40 | E85: ='สูตร 4 step SB'!D401 -> 41
A86: ไม้ระแนงลบมุม ซิเมนต์ 10 ตราช้าง | B86: ='สูตร 4 step SB'!D1143 -> 48 | C86: ='สูตร 4 step SB'!D1144 -> 49 | D86: ='สูตร 4 step SB'!D1145 -> 50 | E86: ='สูตร 4 step SB'!D1146 -> 52
A87: ไม้มอบ ซุปเปอร์ซัน | B87: ='สูตร 4 step SB'!D536 -> 29 | C87: ='สูตร 4 step SB'!D537 -> 30 | D87: ='สูตร 4 step SB'!D538 -> 31 | E87: ='สูตร 4 step SB'!D539 -> 32
A88: ไม้ระแนงลบมุม 7.5 ซุปเปอร์ซัน | B88: ='สูตร 4 step SB'!D564 -> 31 | C88: ='สูตร 4 step SB'!D565 -> 32 | D88: ='สูตร 4 step SB'!D566 -> 33 | E88: ='สูตร 4 step SB'!D567 -> 34
A90: ไม้ฝา ซูเปอร์ซัน 15*300*0.8 สีซิเมนต์ | B90: ='สูตร 4 step SB'!D753 -> 43 | C90: ='สูตร 4 step SB'!D754 -> 44 | D90: ='สูตร 4 step SB'!D755 -> 45 | E90: ='สูตร 4 step SB'!D756 -> 46
A91: ไม้ฝา ซูเปอร์ซัน 15*400*0.8 สีซิเมนต์ | B91: ='สูตร 4 step SB'!D975 -> 58 | C91: ='สูตร 4 step SB'!D976 -> 59 | D91: ='สูตร 4 step SB'!D977 -> 60 | E91: ='สูตร 4 step SB'!D978 -> 61
A92: ไม้ฝา ซูเปอร์ซัน 20*300*0.8 สีซิเมนต์ | B92: ='สูตร 4 step SB'!D1003 -> 58 | C92: ='สูตร 4 step SB'!D1001 -> 54.207727 | D92: ='สูตร 4 step SB'!D1003 -> 58 | E92: ='สูตร 4 step SB'!D1004 -> 59
A93: ไม้ฝา ซูเปอร์ซัน 20*400*0.8 สีซิเมนต์ | B93: ='สูตร 4 step SB'!D1031 -> 76 | C93: ='สูตร 4 step SB'!D1032 -> 77 | D93: ='สูตร 4 step SB'!D1033 -> 78 | E93: ='สูตร 4 step SB'!D1034 -> 79
A94: ไม้พื้น ซูเปอร์ซัน ลายไม้ 10*300*2.5 รองพื้น | B94: ='สูตร 4 step SB'!D1059 -> 185 | C94: ='สูตร 4 step SB'!D1060 -> 188 | D94: ='สูตร 4 step SB'!D1061 -> 190 | E94: ='สูตร 4 step SB'!D1062 -> 192
A95: ไม้พื้น ซูเปอร์ซัน ลายไม้ 15*300*2.5 รองพื้น | B95: ='สูตร 4 step SB'!D1087 -> 278 | C95: ='สูตร 4 step SB'!D1088 -> 282 | D95: ='สูตร 4 step SB'!D1089 -> 285 | E95: ='สูตร 4 step SB'!D1090 -> 288
A96: ไม้พื้น ซูเปอร์ซัน ลายไม้ 20*300*2.5 รองพื้น | B96: ='สูตร 4 step SB'!D1115 -> 368 | C96: ='สูตร 4 step SB'!D1116 -> 373 | D96: ='สูตร 4 step SB'!D1117 -> 378 | E96: ='สูตร 4 step SB'!D1118 -> 383
A98: ซีเมนต์บอร์ด 120*240*8 มม.(60) | B98: ='สูตร 4 step SB'!D807 -> 339 | C98: ='สูตร 4 step SB'!D808 -> 344 | D98: ='สูตร 4 step SB'!D809 -> 349 | E98: ='สูตร 4 step SB'!D810 -> 354
A99: ซีเมนต์บอร์ด 120*240*10 มม.(48) | B99: ='สูตร 4 step SB'!D835 -> 411 | C99: ='สูตร 4 step SB'!D836 -> 416 | D99: ='สูตร 4 step SB'!D837 -> 421 | E99: ='สูตร 4 step SB'!D838 -> 426
A100: ซีเมนต์บอร์ด 120*240*12 มม.(40) | B100: ='สูตร 4 step SB'!D863 -> 473 | C100: ='สูตร 4 step SB'!D864 -> 478 | D100: ='สูตร 4 step SB'!D865 -> 483 | E100: ='สูตร 4 step SB'!D866 -> 488
A101: ซีเมนต์บอร์ด 120*240*16 มม.(30) | B101: ='สูตร 4 step SB'!D891 -> 567 | C101: ='สูตร 4 step SB'!D892 -> 572 | D101: ='สูตร 4 step SB'!D893 -> 577 | E101: ='สูตร 4 step SB'!D894 -> 582
A102: ซีเมนต์บอร์ด 120*240*20 มม.(24) | B102: ='สูตร 4 step SB'!D919 -> 683 | C102: ='สูตร 4 step SB'!D920 -> 688 | D102: ='สูตร 4 step SB'!D921 -> 693 | E102: ='สูตร 4 step SB'!D922 -> 698
A103: ซีเมนต์บอร์ด 120*240*24 มม.(20) | B103: ='สูตร 4 step SB'!D947 -> 802 | C103: ='สูตร 4 step SB'!D948 -> 807 | D103: ='สูตร 4 step SB'!D949 -> 812 | E103: ='สูตร 4 step SB'!D950 -> 817
A115: New Product
A116: BKK Price | D116: BKK
A117: Y1 : Rockwool | C117: WIP | D117: WIPR | E117: WIPRSO | H117: กรณีหุ้มฟลอยด์
B118: W1 | C118: W2 | D118: R1 | E118: R2 | H118: 1 ด้าน +90 บาท
A119: Rock Chill หนา 3 นิ้ว | B119: =Rockwool!D14 -> 308.9625 | C119: =Rockwool!D15 -> 323.675 | D119: =Rockwool!D16 -> 338.3875 | E119: =Rockwool!D17 -> 353.1 | H119: 2 ด้าน +112 บาท
A120: Safe 'n' Silent Pro 330 หนา 50 มม. 60*120 (6 แผ่น/ แพ็ค) | B120: =Rockwool!D42 -> 84.9366 | C120: =Rockwool!D43 -> 86.55444 | D120: =Rockwool!D44 -> 88.9812 | E120: =Rockwool!D45 -> 93.0258
...

Sheet N DCM
A1: Internal Memo | G1: No.
A2: To : | E2: ผู้จัดการภาค / ผู้จัดการเขต | G2: Date :
A3: RE :
A4: หมายเหตุ : | D4: 1 | E4: ราคาขายข้างต้นรวม VAT
D5: 2 | E5: หากราคาข้างต้นสูง ไม่สามารถขายได้ โปรดสอบถาม ผจก.PM
D6: 3 | E6: ราคาขายข้างต้นให้ถือเป็นราคาขายต่ำสุด สามารถขายที่ราคาสูงกว่านี้ได้ ขึ้นอยู่กับแต่ละพื้นที่
D7: 4 | E7: ปริมาณการขายส่งแผ่น 120x240 ขั้นต่ำ 400 แผ่น : เดือน
D8: 5 | E8: ราคา RE (EX VAT) และไม่รวมค่าขนส่ง ยังไม่หักรีเบทประจำเดือน
A10: N Price | D10: CM | H10: CR | L10: PL | P10: NS
A11: Y 1: Gypsum | C11: WIP | D11: WIPR | E11: WIPRSO | G11: WIP | H11: WIPR | I11: WIPRSO | K11: WIP | L11: WIPR | M11: WIPRSO | O11: WIP | P11: WIPR | Q11: WIPRSO
B12: W1 | C12: W2 | D12: R1 | E12: R2 | F12: W1 | G12: W2 | H12: R1 | I12: R2 | J12: W1 | K12: W2 | L12: R1 | M12: R2 | N12: W1 | O12: W2 | P12: R1 | Q12: R2
A13: ยิปซัม ธรรมดา 9 มม. ขอบเรียบ/ลาด | B13: ='Formular 4 step Y1'!E14 -> 136 | C13: ='Formular 4 step Y1'!E15 -> 137 | D13: ='Formular 4 step Y1'!E16 -> 138 | E13: ='Formular 4 step Y1'!E17 -> 139 | F13: ='Formular 4 step Y1'!F14 -> 139 | G13: ='Formular 4 step Y1'!F15 -> 140 | H13: ='Formular 4 step Y1'!F16 -> 141 | I13: ='Formular 4 step Y1'!F17 -> 142 | J13: ='Formular 4 step Y1'!G14 -> 134 | K13: ='Formular 4 step Y1'!G15 -> 135 | L13: ='Formular 4 step Y1'!G16 -> 136 | M13: ='Formular 4 step Y1'!G17 -> 137 | N13: ='Formular 4 step Y1'!H14 -> 129 | O13: ='Formular 4 step Y1'!H15 -> 130 | P13: ='Formular 4 step Y1'!H16 -> 131 | Q13: ='Formular 4 step Y1'!H17 -> 132
A14: ยิปซัม ธรรมดา 9 มม. ขอบลาด 4 ด้าน | B14: ='Formular 4 step Y1'!E39 -> 139 | C14: ='Formular 4 step Y1'!E40 -> 140 | D14: ='Formular 4 step Y1'!E41 -> 141 | E14: ='Formular 4 step Y1'!E42 -> 142 | F14: ='Formular 4 step Y1'!F39 -> 141 | G14: ='Formular 4 step Y1'!F40 -> 142 | H14: ='Formular 4 step Y1'!F41 -> 143 | I14: ='Formular 4 step Y1'!F42 -> 144 | J14: ='Formular 4 step Y1'!G39 -> 136 | K14: ='Formular 4 step Y1'!G40 -> 137 | L14: ='Formular 4 step Y1'!G41 -> 138 | M14: ='Formular 4 step Y1'!G42 -> 139 | N14: ='Formular 4 step Y1'!H39 -> 132 | O14: ='Formular 4 step Y1'!H40 -> 133 | P14: ='Formular 4 step Y1'!H41 -> 134 | Q14: ='Formular 4 step Y1'!H42 -> 135
A15: ยิปซัม ทนชื้น/ฟลอยด์ 9 มม. ขอบเรียบ/ลาด | B15: ='Formular 4 step Y1'!E64 -> 202 | C15: ='Formular 4 step Y1'!E65 -> 203 | D15: ='Formular 4 step Y1'!E66 -> 204 | E15: ='Formular 4 step Y1'!E67 -> 205 | F15: ='Formular 4 step Y1'!F64 -> 204 | G15: ='Formular 4 step Y1'!F65 -> 205 | H15: ='Formular 4 step Y1'!F66 -> 206 | I15: ='Formular 4 step Y1'!F67 -> 207 | J15: ='Formular 4 step Y1'!G64 -> 199 | K15: ='Formular 4 step Y1'!G65 -> 200 | L15: ='Formular 4 step Y1'!G66 -> 201 | M15: ='Formular 4 step Y1'!G67 -> 202 | N15: ='Formular 4 step Y1'!H64 -> 195 | O15: ='Formular 4 step Y1'!H65 -> 196 | P15: ='Formular 4 step Y1'!H66 -> 197 | Q15: ='Formular 4 step Y1'!H67 -> 198
A16: ยิปซัม ทนชื้น/ฟลอยด์ 9 มม. ขอบลาด 4 ด้าน | B16: ='Formular 4 step Y1'!E89 -> 201 | C16: ='Formular 4 step Y1'!E90 -> 202 | D16: ='Formular 4 step Y1'!E91 -> 203 | E16: ='Formular 4 step Y1'!E92 -> 204 | F16: ='Formular 4 step Y1'!F89 -> 203 | G16: ='Formular 4 step Y1'!F90 -> 204 | H16: ='Formular 4 step Y1'!F91 -> 205 | I16: ='Formular 4 step Y1'!F92 -> 206 | J16: ='Formular 4 step Y1'!G89 -> 198 | K16: ='Formular 4 step Y1'!G90 -> 199 | L16: ='Formular 4 step Y1'!G91 -> 200 | M16: ='Formular 4 step Y1'!G92 -> 201 | N16: ='Formular 4 step Y1'!H89 -> 194 | O16: ='Formular 4 step Y1'!H90 -> 195 | P16: ='Formular 4 step Y1'!H91 -> 196 | Q16: ='Formular 4 step Y1'!H92 -> 197
A17: ยิปซัม ธรรมดา 12 มม. ขอบเรียบ/ลาด | B17: ='Formular 4 step Y1'!E114 -> 165 | C17: ='Formular 4 step Y1'!E115 -> 166 | D17: ='Formular 4 step Y1'!E116 -> 167 | E17: ='Formular 4 step Y1'!E117 -> 168 | F17: ='Formular 4 step Y1'!F114 -> 169 | G17: ='Formular 4 step Y1'!F115 -> 170 | H17: ='Formular 4 step Y1'!F116 -> 171 | I17: ='Formular 4 step Y1'!F117 -> 172 | J17: ='Formular 4 step Y1'!G114 -> 162 | K17: ='Formular 4 step Y1'!G115 -> 163 | L17: ='Formular 4 step Y1'!G116 -> 164 | M17: ='Formular 4 step Y1'!G117 -> 165 | N17: ='Formular 4 step Y1'!H114 -> 155 | O17: ='Formular 4 step Y1'!H115 -> 156 | P17: ='Formular 4 step Y1'!H116 -> 157 | Q17: ='Formular 4 step Y1'!H117 -> 158
A18: ยิปซัม ทนชื้น/ฟลอยด์ 12 มม. ขอบเรียบ/ลาด | B18: ='Formular 4 step Y1'!E139 -> 228 | C18: ='Formular 4 step Y1'!E140 -> 229 | D18: ='Formular 4 step Y1'!E141 -> 230 | E18: ='Formular 4 step Y1'!E141 -> 230 | F18: ='Formular 4 step Y1'!F139 -> 231 | G18: ='Formular 4 step Y1'!F140 -> 232 | H18: ='Formular 4 step Y1'!F141 -> 233 | I18: ='Formular 4 step Y1'!F141 -> 233 | J18: ='Formular 4 step Y1'!G139 -> 224 | K18: ='Formular 4 step Y1'!G140 -> 225 | L18: ='Formular 4 step Y1'!G141 -> 226 | M18: ='Formular 4 step Y1'!G141 -> 226 | N18: ='Formular 4 step Y1'!H139 -> 218 | O18: ='Formular 4 step Y1'!H140 -> 219 | P18: ='Formular 4 step Y1'!H141 -> 220 | Q18: ='Formular 4 step Y1'!H141 -> 220
A19: ยิปซัม ธรรมดา 15 มม. ขอบลาด | B19: ='Formular 4 step Y1'!E838 -> 239 | C19: ='Formular 4 step Y1'!E839 -> 240 | D19: ='Formular 4 step Y1'!E840 -> 241 | E19: ='Formular 4 step Y1'!E841 -> 242 | F19: ='Formular 4 step Y1'!F838 -> 245 | G19: ='Formular 4 step Y1'!F839 -> 246 | H19: ='Formular 4 step Y1'!F840 -> 247 | I19: ='Formular 4 step Y1'!F841 -> 248 | J19: ='Formular 4 step Y1'!G838 -> 234 | K19: ='Formular 4 step Y1'!G839 -> 235 | L19: ='Formular 4 step Y1'!G840 -> 236 | M19: ='Formular 4 step Y1'!G841 -> 237 | N19: ='Formular 4 step Y1'!H838 -> 224 | O19: ='Formular 4 step Y1'!H839 -> 225 | P19: ='Formular 4 step Y1'!H840 -> 226 | Q19: ='Formular 4 step Y1'!H841 -> 227
A20: ทนไฟ 12 มม. | B20: ='Formular 4 step Y1'!E164 -> 269 | C20: ='Formular 4 step Y1'!E165 -> 272 | D20: ='Formular 4 step Y1'!E166 -> 277 | E20: ='Formular 4 step Y1'!E167 -> 282 | F20: ='Formular 4 step Y1'!F164 -> 272 | G20: ='Formular 4 step Y1'!F165 -> 275 | H20: ='Formular 4 step Y1'!F166 -> 280 | I20: ='Formular 4 step Y1'!F167 -> 285 | J20: ='Formular 4 step Y1'!G164 -> 265 | K20: ='Formular 4 step Y1'!G165 -> 268 | L20: ='Formular 4 step Y1'!G166 -> 273 | M20: ='Formular 4 step Y1'!G167 -> 278 | N20: ='Formular 4 step Y1'!H164 -> 259 | O20: ='Formular 4 step Y1'!H165 -> 262 | P20: ='Formular 4 step Y1'!H166 -> 267 | Q20: ='Formular 4 step Y1'!H167 -> 272
A21: ทนไฟ 15 มม. | B21: ='Formular 4 step Y1'!E189 -> 312 | C21: ='Formular 4 step Y1'!E190 -> 315 | D21: ='Formular 4 step Y1'!E191 -> 320 | E21: ='Formular 4 step Y1'!E192 -> 325 | F21: ='Formular 4 step Y1'!F189 -> 318 | G21: ='Formular 4 step Y1'!F190 -> 321 | H21: ='Formular 4 step Y1'!F191 -> 326 | I21: ='Formular 4 step Y1'!F192 -> 331 | J21: ='Formular 4 step Y1'!G189 -> 305 | K21: ='Formular 4 step Y1'!G190 -> 308 | L21: ='Formular 4 step Y1'!G191 -> 313 | M21: ='Formular 4 step Y1'!G192 -> 318 | N21: ='Formular 4 step Y1'!H189 -> 293 | O21: ='Formular 4 step Y1'!H190 -> 296 | P21: ='Formular 4 step Y1'!H191 -> 301 | Q21: ='Formular 4 step Y1'!H192 -> 306
A22: ยิปซัมเฟล็กบอร์ด(ดัดโค้ง) 6 มม. 120*240 มม. | B22: ='Formular 4 step Y1'!E863 -> 190.57762 | C22: ='Formular 4 step Y1'!E864 -> 192.34223 | D22: ='Formular 4 step Y1'!E865 -> 197.63605 | E22: ='Formular 4 step Y1'!E866 -> 202.92987 | F22: ='Formular 4 step Y1'!F863 -> 193.27762 | G22: ='Formular 4 step Y1'!F864 -> 195.06723 | H22: ='Formular 4 step Y1'!F865 -> 200.43605 | I22: ='Formular 4 step Y1'!F866 -> 205.80487 | J22: ='Formular 4 step Y1'!G863 -> 187.87762 | K22: ='Formular 4 step Y1'!G864 -> 189.61723 | L22: ='Formular 4 step Y1'!G865 -> 194.83605 | M22: ='Formular 4 step Y1'!G866 -> 200.05487 | N22: ='Formular 4 step Y1'!H863 -> 183.01762 | O22: ='Formular 4 step Y1'!H864 -> 184.71223 | P22: ='Formular 4 step Y1'!H865 -> 189.79605 | Q22: ='Formular 4 step Y1'!H866 -> 194.87987
A23: อี่ซี่บอร์ท / คนอฟ | B23: ='Formular 4 step Y1'!E738 -> 105 | C23: ='Formular 4 step Y1'!E739 -> 106 | D23: ='Formular 4 step Y1'!E740 -> 107 | E23: ='Formular 4 step Y1'!E741 -> 108 | F23: ='Formular 4 step Y1'!F738 -> 105 | G23: ='Formular 4 step Y1'!F739 -> 106 | H23: ='Formular 4 step Y1'!F740 -> 107 | I23: ='Formular 4 step Y1'!F741 -> 108 | J23: ='Formular 4 step Y1'!G738 -> 105 | K23: ='Formular 4 step Y1'!G739 -> 106 | L23: ='Formular 4 step Y1'!G740 -> 107 | M23: ='Formular 4 step Y1'!G741 -> 108 | N23: ='Formular 4 step Y1'!H738 -> 105 | O23: ='Formular 4 step Y1'!H739 -> 106 | P23: ='Formular 4 step Y1'!H740 -> 107 | Q23: ='Formular 4 step Y1'!H741 -> 108
A24: อี่ซี่บอร์ท/คนอฟ ทนชื้น / ฟอล์ย | B24: ='Formular 4 step Y1'!E763 -> 162 | C24: ='Formular 4 step Y1'!E764 -> 163 | D24: ='Formular 4 step Y1'!E765 -> 164 | E24: ='Formular 4 step Y1'!E766 -> 165 | F24: ='Formular 4 step Y1'!F763 -> 162 | G24: ='Formular 4 step Y1'!F764 -> 163 | H24: ='Formular 4 step Y1'!F765 -> 164 | I24: ='Formular 4 step Y1'!F766 -> 165 | J24: ='Formular 4 step Y1'!G763 -> 162 | K24: ='Formular 4 step Y1'!G764 -> 163 | L24: ='Formular 4 step Y1'!G765 -> 164 | M24: ='Formular 4 step Y1'!G766 -> 165 | N24: ='Formular 4 step Y1'!H763 -> 162 | O24: ='Formular 4 step Y1'!H764 -> 163 | P24: ='Formular 4 step Y1'!H765 -> 164 | Q24: ='Formular 4 step Y1'!H766 -> 165
A25: เวเทอร์บล็อค W0 | B25: ='Formular 4 step Y1'!E788 -> 278 | C25: ='Formular 4 step Y1'!E789 -> 279 | D25: ='Formular 4 step Y1'!E790 -> 280 | E25: ='Formular 4 step Y1'!E791 -> 281 | F25: ='Formular 4 step Y1'!F788 -> 280 | G25: ='Formular 4 step Y1'!F789 -> 281 | H25: ='Formular 4 step Y1'!F790 -> 282 | I25: ='Formular 4 step Y1'!F791 -> 283 | J25: ='Formular 4 step Y1'!G788 -> 276 | K25: ='Formular 4 step Y1'!G789 -> 277 | L25: ='Formular 4 step Y1'!G790 -> 278 | M25: ='Formular 4 step Y1'!G791 -> 279 | N25: ='Formular 4 step Y1'!H788 -> 272 | O25: ='Formular 4 step Y1'!H789 -> 273 | P25: ='Formular 4 step Y1'!H790 -> 274 | Q25: ='Formular 4 step Y1'!H791 -> 275
A26: เวเทอร์บล็อค W1 | B26: ='Formular 4 step Y1'!E813 -> 435 | C26: ='Formular 4 step Y1'!E814 -> 436 | D26: ='Formular 4 step Y1'!E815 -> 437 | E26: ='Formular 4 step Y1'!E816 -> 438 | F26: ='Formular 4 step Y1'!F813 -> 437 | G26: ='Formular 4 step Y1'!F814 -> 438 | H26: ='Formular 4 step Y1'!F815 -> 439 | I26: ='Formular 4 step Y1'!F816 -> 440 | J26: ='Formular 4 step Y1'!G813 -> 433 | K26: ='Formular 4 step Y1'!G814 -> 434 | L26: ='Formular 4 step Y1'!G815 -> 435 | M26: ='Formular 4 step Y1'!G816 -> 436 | N26: ='Formular 4 step Y1'!H813 -> 429 | O26: ='Formular 4 step Y1'!H814 -> 430 | P26: ='Formular 4 step Y1'!H815 -> 431 | Q26: ='Formular 4 step Y1'!H816 -> 432
A27: ยิปซัมลดเสียงสะท้อน เอคโค่บล็อค (R1,R2,R8,S8) | B27: ='Formular 4 step Y1'!E214 -> 920 | C27: ='Formular 4 step Y1'!E215 -> 923 | D27: ='Formular 4 step Y1'!E216 -> 933 | E27: ='Formular 4 step Y1'!E217 -> 943 | F27: ='Formular 4 step Y1'!F214 -> 924 | G27: ='Formular 4 step Y1'!F215 -> 927 | H27: ='Formular 4 step Y1'!F216 -> 937 | I27: ='Formular 4 step Y1'!F217 -> 947 | J27: ='Formular 4 step Y1'!G214 -> 917 | K27: ='Formular 4 step Y1'!G215 -> 920 | L27: ='Formular 4 step Y1'!G216 -> 930 | M27: ='Formular 4 step Y1'!G217 -> 940 | N27: ='Formular 4 step Y1'!H214 -> 910 | O27: ='Formular 4 step Y1'!H215 -> 913 | P27: ='Formular 4 step Y1'!H216 -> 923 | Q27: ='Formular 4 step Y1'!H217 -> 933
A28: Paper touch ลวดลาย 60*60*8 mm. | B28: ='Formular 4 step Y1'!E239 -> 22.267906 | C28: ='Formular 4 step Y1'!E240 -> 23 | D28: ='Formular 4 step Y1'!E241 -> 24 | E28: ='Formular 4 step Y1'!E242 -> 25 | F28: ='Formular 4 step Y1'!F239 -> 22.267906 | G28: ='Formular 4 step Y1'!F240 -> 23 | H28: ='Formular 4 step Y1'!F241 -> 24 | I28: ='Formular 4 step Y1'!F242 -> 25 | J28: ='Formular 4 step Y1'!G239 -> 22.267906 | K28: ='Formular 4 step Y1'!G240 -> 23 | L28: ='Formular 4 step Y1'!G241 -> 24 | M28: ='Formular 4 step Y1'!G242 -> 25 | N28: ='Formular 4 step Y1'!H239 -> 22.267906 | O28: ='Formular 4 step Y1'!H240 -> 23 | P28: ='Formular 4 step Y1'!H241 -> 24 | Q28: ='Formular 4 step Y1'!H242 -> 25
A29: Paper touch หยาดเพชร 60*60*8 mm. | B29: ='Formular 4 step Y1'!E264 -> 19.866612 | C29: ='Formular 4 step Y1'!E265 -> 21 | D29: ='Formular 4 step Y1'!E266 -> 22 | E29: ='Formular 4 step Y1'!E267 -> 23 | F29: ='Formular 4 step Y1'!F264 -> 19.866612 | G29: ='Formular 4 step Y1'!F265 -> 21 | H29: ='Formular 4 step Y1'!F266 -> 22 | I29: ='Formular 4 step Y1'!F267 -> 23 | J29: ='Formular 4 step Y1'!G264 -> 19.866612 | K29: ='Formular 4 step Y1'!G265 -> 21 | L29: ='Formular 4 step Y1'!G266 -> 22 | M29: ='Formular 4 step Y1'!G267 -> 23 | N29: ='Formular 4 step Y1'!H264 -> 19.866612 | O29: ='Formular 4 step Y1'!H265 -> 21 | P29: ='Formular 4 step Y1'!H266 -> 22 | Q29: ='Formular 4 step Y1'!H267 -> 23
A30: Paper touch หยาดเพชร 60*60*8 mm. กันร้อน | B30: ='Formular 4 step Y1'!E289 -> 25.329818 | C30: ='Formular 4 step Y1'!E290 -> 26 | D30: ='Formular 4 step Y1'!E291 -> 27 | E30: ='Formular 4 step Y1'!E292 -> 28 | F30: ='Formular 4 step Y1'!F289 -> 25.329818 | G30: ='Formular 4 step Y1'!F290 -> 26 | H30: ='Formular 4 step Y1'!F291 -> 27 | I30: ='Formular 4 step Y1'!F292 -> 28 | J30: ='Formular 4 step Y1'!G289 -> 25.329818 | K30: ='Formular 4 step Y1'!G290 -> 26 | L30: ='Formular 4 step Y1'!G291 -> 27 | M30: ='Formular 4 step Y1'!G292 -> 28 | N30: ='Formular 4 step Y1'!H289 -> 25.329818 | O30: ='Formular 4 step Y1'!H290 -> 26 | P30: ='Formular 4 step Y1'!H291 -> 27 | Q30: ='Formular 4 step Y1'!H292 -> 28
A31: Color touch สีมุก/สีเพชร 60x60*9 mm. | B31: ='Formular 4 step Y1'!E313 -> 23 | C31: ='Formular 4 step Y1'!E314 -> 24 | D31: ='Formular 4 step Y1'!E315 -> 25 | E31: ='Formular 4 step Y1'!E316 -> 26 | F31: ='Formular 4 step Y1'!F313 -> 23 | G31: ='Formular 4 step Y1'!F314 -> 24 | H31: ='Formular 4 step Y1'!F315 -> 25 | I31: ='Formular 4 step Y1'!F316 -> 26 | J31: ='Formular 4 step Y1'!G313 -> 23 | K31: ='Formular 4 step Y1'!G314 -> 24 | L31: ='Formular 4 step Y1'!G315 -> 25 | M31: ='Formular 4 step Y1'!G316 -> 26 | N31: ='Formular 4 step Y1'!H313 -> 23 | O31: ='Formular 4 step Y1'!H314 -> 24 | P31: ='Formular 4 step Y1'!H315 -> 25 | Q31: ='Formular 4 step Y1'!H316 -> 26
A32: Color touch สีมุก/สีเพชร 60x120*9 mm. | B32: ='Formular 4 step Y1'!E338 -> 46 | C32: ='Formular 4 step Y1'!E339 -> 47 | D32: ='Formular 4 step Y1'!E340 -> 48 | E32: ='Formular 4 step Y1'!E341 -> 50 | F32: ='Formular 4 step Y1'!F338 -> 46 | G32: ='Formular 4 step Y1'!F339 -> 47 | H32: ='Formular 4 step Y1'!F340 -> 48 | I32: ='Formular 4 step Y1'!F341 -> 50 | J32: ='Formular 4 step Y1'!G338 -> 46 | K32: ='Formular 4 step Y1'!G339 -> 47 | L32: ='Formular 4 step Y1'!G340 -> 48 | M32: ='Formular 4 step Y1'!G341 -> 50 | N32: ='Formular 4 step Y1'!H338 -> 46 | O32: ='Formular 4 step Y1'!H339 -> 47 | P32: ='Formular 4 step Y1'!H340 -> 48 | Q32: ='Formular 4 step Y1'!H341 -> 50
A33: Color touch สีมุก/สีเพชร 60x120*12 mm. | B33: ='Formular 4 step Y1'!E888 -> 46.802609 | C33: ='Formular 4 step Y1'!E889 -> 47.5 | D33: ='Formular 4 step Y1'!E890 -> 48.090754 | E33: ='Formular 4 step Y1'!E891 -> 49.378899 | F33: ='Formular 4 step Y1'!F888 -> 46.802609 | G33: ='Formular 4 step Y1'!F889 -> 47.5 | H33: ='Formular 4 step Y1'!F890 -> 48.090754 | I33: ='Formular 4 step Y1'!F891 -> 49.378899 | J33: ='Formular 4 step Y1'!G888 -> 46.802609 | K33: ='Formular 4 step Y1'!G889 -> 47.5 | L33: ='Formular 4 step Y1'!G890 -> 48.090754 | M33: ='Formular 4 step Y1'!G891 -> 49.378899 | N33: ='Formular 4 step Y1'!H888 -> 46.802609 | O33: ='Formular 4 step Y1'!H889 -> 47.5 | P33: ='Formular 4 step Y1'!H890 -> 48.090754 | Q33: ='Formular 4 step Y1'!H891 -> 49.378899
A34: Color touch สีมุก/สีเพชร 60x60*9 mm. ทนชื้น | B34: ='Formular 4 step Y1'!E363 -> 28 | C34: ='Formular 4 step Y1'!E364 -> 29 | D34: ='Formular 4 step Y1'!E365 -> 31 | E34: ='Formular 4 step Y1'!E366 -> 32 | F34: ='Formular 4 step Y1'!F363 -> 28 | G34: ='Formular 4 step Y1'!F364 -> 29 | H34: ='Formular 4 step Y1'!F365 -> 31 | I34: ='Formular 4 step Y1'!F366 -> 32 | J34: ='Formular 4 step Y1'!G363 -> 28 | K34: ='Formular 4 step Y1'!G364 -> 29 | L34: ='Formular 4 step Y1'!G365 -> 31 | M34: ='Formular 4 step Y1'!G366 -> 32 | N34: ='Formular 4 step Y1'!H363 -> 28 | O34: ='Formular 4 step Y1'!H364 -> 29 | P34: ='Formular 4 step Y1'!H365 -> 31 | Q34: ='Formular 4 step Y1'!H366 -> 32
A35: Color touch สีมุก/สีเพชร 60x120*9 mm. ทนชื้น | B35: ='Formular 4 step Y1'!E388 -> 57 | C35: ='Formular 4 step Y1'!E389 -> 58 | D35: ='Formular 4 step Y1'!E390 -> 59 | E35: ='Formular 4 step Y1'!E391 -> 61 | F35: ='Formular 4 step Y1'!F388 -> 57 | G35: ='Formular 4 step Y1'!F389 -> 58 | H35: ='Formular 4 step Y1'!F390 -> 59 | I35: ='Formular 4 step Y1'!F391 -> 61 | J35: ='Formular 4 step Y1'!G388 -> 57 | K35: ='Formular 4 step Y1'!G389 -> 58 | L35: ='Formular 4 step Y1'!G390 -> 59 | M35: ='Formular 4 step Y1'!Q391 -> 62 | N35: ='Formular 4 step Y1'!H388 -> 57 | O35: ='Formular 4 step Y1'!H389 -> 58 | P35: ='Formular 4 step Y1'!H390 -> 59 | Q35: ='Formular 4 step Y1'!H391 -> 61
A36: Color touch สีมุก/สีเพชร 60x120*12 mm. ทนชื้น | B36: ='Formular 4 step Y1'!D913 -> 63.551024 | C36: ='Formular 4 step Y1'!D914 -> 64.5 | D36: ='Formular 4 step Y1'!D915 -> 65.300135 | E36: ='Formular 4 step Y1'!D916 -> 67.049246 | F36: ='Formular 4 step Y1'!F913 -> 63.442024 | G36: ='Formular 4 step Y1'!F914 -> 64.5 | H36: ='Formular 4 step Y1'!F915 -> 65.188135 | I36: ='Formular 4 step Y1'!F916 -> 66.934246 | J36: ='Formular 4 step Y1'!G913 -> 63.442024 | K36: ='Formular 4 step Y1'!G914 -> 64.5 | L36: ='Formular 4 step Y1'!G915 -> 65.188135 | M36: ='Formular 4 step Y1'!G916 -> 66.934246 | N36: ='Formular 4 step Y1'!H913 -> 63.442024 | O36: ='Formular 4 step Y1'!H914 -> 64.5 | P36: ='Formular 4 step Y1'!H915 -> 65.188135 | Q36: ='Formular 4 step Y1'!H916 -> 66.934246
A37: เซิฟบอร์ด ขนาด 30 ซม. | B37: ='Formular 4 step Y1'!E413 -> 189 | C37: ='Formular 4 step Y1'!E414 -> 190 | D37: ='Formular 4 step Y1'!E415 -> 195 | E37: ='Formular 4 step Y1'!E416 -> 200 | F37: ='Formular 4 step Y1'!F413 -> 189 | G37: ='Formular 4 step Y1'!F414 -> 190 | H37: ='Formular 4 step Y1'!F415 -> 195 | I37: ='Formular 4 step Y1'!F416 -> 200 | J37: ='Formular 4 step Y1'!G413 -> 189 | K37: ='Formular 4 step Y1'!G414 -> 190 | L37: ='Formular 4 step Y1'!G415 -> 195 | M37: ='Formular 4 step Y1'!G416 -> 200 | N37: ='Formular 4 step Y1'!H413 -> 189 | O37: ='Formular 4 step Y1'!H414 -> 190 | P37: ='Formular 4 step Y1'!H415 -> 195 | Q37: ='Formular 4 step Y1'!H416 -> 200
A38: เซิฟบอร์ด ขนาด 45 ซม. | B38: ='Formular 4 step Y1'!E438 -> 260 | C38: ='Formular 4 step Y1'!E439 -> 262 | D38: ='Formular 4 step Y1'!E440 -> 264 | E38: ='Formular 4 step Y1'!E441 -> 266 | F38: ='Formular 4 step Y1'!F438 -> 260 | G38: ='Formular 4 step Y1'!F439 -> 262 | H38: ='Formular 4 step Y1'!F440 -> 264 | I38: ='Formular 4 step Y1'!F441 -> 266 | J38: ='Formular 4 step Y1'!G438 -> 260 | K38: ='Formular 4 step Y1'!G439 -> 262 | L38: ='Formular 4 step Y1'!G440 -> 264 | M38: ='Formular 4 step Y1'!G441 -> 266 | N38: ='Formular 4 step Y1'!H438 -> 260 | O38: ='Formular 4 step Y1'!H439 -> 262 | P38: ='Formular 4 step Y1'!H440 -> 264 | Q38: ='Formular 4 step Y1'!H441 -> 266
A39: เซิฟบอร์ด ขนาด 60 ซม. | B39: ='Formular 4 step Y1'!E463 -> 320 | C39: ='Formular 4 step Y1'!E464 -> 322 | D39: ='Formular 4 step Y1'!E465 -> 324 | E39: ='Formular 4 step Y1'!E466 -> 326 | F39: ='Formular 4 step Y1'!F463 -> 320 | G39: ='Formular 4 step Y1'!F464 -> 322 | H39: ='Formular 4 step Y1'!F465 -> 324 | I39: ='Formular 4 step Y1'!F466 -> 326 | J39: ='Formular 4 step Y1'!G463 -> 320 | K39: ='Formular 4 step Y1'!G464 -> 322 | L39: ='Formular 4 step Y1'!G465 -> 324 | M39: ='Formular 4 step Y1'!G466 -> 326 | N39: ='Formular 4 step Y1'!H463 -> 320 | O39: ='Formular 4 step Y1'!H464 -> 322 | P39: ='Formular 4 step Y1'!H465 -> 324 | Q39: ='Formular 4 step Y1'!H466 -> 326
A40: เซิฟบอร์ด ขนาด 60*120 ซม. | B40: ='Formular 4 step Y1'!E488 -> 771 | C40: ='Formular 4 step Y1'!E489 -> 773 | D40: ='Formular 4 step Y1'!E490 -> 778 | E40: ='Formular 4 step Y1'!E491 -> 783 | F40: ='Formular 4 step Y1'!F488 -> 771 | G40: ='Formular 4 step Y1'!F489 -> 773 | H40: ='Formular 4 step Y1'!F490 -> 778 | I40: ='Formular 4 step Y1'!F491 -> 783 | J40: ='Formular 4 step Y1'!G488 -> 771 | K40: ='Formular 4 step Y1'!G489 -> 773 | L40: ='Formular 4 step Y1'!G490 -> 778 | M40: ='Formular 4 step Y1'!G491 -> 783 | N40: ='Formular 4 step Y1'!H488 -> 771 | O40: ='Formular 4 step Y1'!H489 -> 773 | P40: ='Formular 4 step Y1'!H490 -> 778 | Q40: ='Formular 4 step Y1'!H491 -> 783
A41: เซิฟบอร์ด ขนาด 30 ซม. ทนชื้น | B41: ='Formular 4 step Y1'!E513 -> 257 | C41: ='Formular 4 step Y1'!E514 -> 259 | D41: ='Formular 4 step Y1'!E515 -> 262 | E41: ='Formular 4 step Y1'!E516 -> 264 | F41: ='Formular 4 step Y1'!F513 -> 257 | G41: ='Formular 4 step Y1'!F514 -> 259 | H41: ='Formular 4 step Y1'!F515 -> 262 | I41: ='Formular 4 step Y1'!F516 -> 264 | J41: ='Formular 4 step Y1'!G513 -> 257 | K41: ='Formular 4 step Y1'!G514 -> 259 | L41: ='Formular 4 step Y1'!G515 -> 262 | M41: ='Formular 4 step Y1'!G516 -> 264 | N41: ='Formular 4 step Y1'!H513 -> 257 | O41: ='Formular 4 step Y1'!H514 -> 259 | P41: ='Formular 4 step Y1'!H515 -> 262 | Q41: ='Formular 4 step Y1'!H516 -> 264
A42: เซิฟบอร์ด ขนาด 45 ซม. ทนชื้น | B42: ='Formular 4 step Y1'!E538 -> 322 | C42: ='Formular 4 step Y1'!E539 -> 324 | D42: ='Formular 4 step Y1'!E540 -> 327 | E42: ='Formular 4 step Y1'!E541 -> 329 | F42: ='Formular 4 step Y1'!F538 -> 322 | G42: ='Formular 4 step Y1'!F539 -> 324 | H42: ='Formular 4 step Y1'!F540 -> 327 | I42: ='Formular 4 step Y1'!F541 -> 329 | J42: ='Formular 4 step Y1'!G538 -> 322 | K42: ='Formular 4 step Y1'!G539 -> 324 | L42: ='Formular 4 step Y1'!G540 -> 327 | M42: ='Formular 4 step Y1'!G541 -> 329 | N42: ='Formular 4 step Y1'!H538 -> 322 | O42: ='Formular 4 step Y1'!H539 -> 324 | P42: ='Formular 4 step Y1'!H540 -> 327 | Q42: ='Formular 4 step Y1'!H541 -> 329
A43: เซิฟบอร์ด ขนาด 60 ซม. ทนชื้น | B43: ='Formular 4 step Y1'!E563 -> 385 | C43: ='Formular 4 step Y1'!E564 -> 387 | D43: ='Formular 4 step Y1'!E565 -> 389 | E43: ='Formular 4 step Y1'!E566 -> 391 | F43: ='Formular 4 step Y1'!F563 -> 385 | G43: ='Formular 4 step Y1'!F564 -> 387 | H43: ='Formular 4 step Y1'!F565 -> 389 | I43: ='Formular 4 step Y1'!F566 -> 391 | J43: ='Formular 4 step Y1'!G563 -> 385 | K43: ='Formular 4 step Y1'!G564 -> 387 | L43: ='Formular 4 step Y1'!G565 -> 389 | M43: ='Formular 4 step Y1'!G566 -> 391 | N43: ='Formular 4 step Y1'!H563 -> 385 | O43: ='Formular 4 step Y1'!H564 -> 387 | P43: ='Formular 4 step Y1'!H565 -> 389 | Q43: ='Formular 4 step Y1'!H566 -> 391
A44: เซิฟบอร์ด ขนาด 60*120 ซม. ทนชื้น | B44: ='Formular 4 step Y1'!E588 -> 968 | C44: ='Formular 4 step Y1'!E589 -> 978 | D44: ='Formular 4 step Y1'!E590 -> 983 | E44: ='Formular 4 step Y1'!E591 -> 988 | F44: ='Formular 4 step Y1'!F588 -> 968 | G44: ='Formular 4 step Y1'!F589 -> 978 | H44: ='Formular 4 step Y1'!F590 -> 983 | I44: ='Formular 4 step Y1'!F591 -> 988 | J44: ='Formular 4 step Y1'!G588 -> 968 | K44: ='Formular 4 step Y1'!G589 -> 978 | L44: ='Formular 4 step Y1'!G590 -> 983 | M44: ='Formular 4 step Y1'!G591 -> 988 | N44: ='Formular 4 step Y1'!H588 -> 968 | O44: ='Formular 4 step Y1'!H589 -> 978 | P44: ='Formular 4 step Y1'!H590 -> 983 | Q44: ='Formular 4 step Y1'!H591 -> 988
A45: อะคูสติก กาแลคซี่ | B45: ='Formular 4 step Y1'!E613 -> 147.32653 | C45: ='Formular 4 step Y1'!E614 -> 148 | D45: ='Formular 4 step Y1'!E615 -> 149 | E45: ='Formular 4 step Y1'!E616 -> 151 | F45: ='Formular 4 step Y1'!F613 -> 147.32653 | G45: ='Formular 4 step Y1'!F614 -> 148 | H45: ='Formular 4 step Y1'!F615 -> 149 | I45: ='Formular 4 step Y1'!F616 -> 151 | J45: ='Formular 4 step Y1'!G613 -> 147.32653 | K45: ='Formular 4 step Y1'!G614 -> 148 | L45: ='Formular 4 step Y1'!G615 -> 149 | M45: ='Formular 4 step Y1'!G616 -> 151 | N45: ='Formular 4 step Y1'!H613 -> 147.32653 | O45: ='Formular 4 step Y1'!H614 -> 148 | P45: ='Formular 4 step Y1'!H615 -> 149 | Q45: ='Formular 4 step Y1'!H616 -> 151
A46: อะคูสติก-อิมเพรสชันME903 | B46: ='Formular 4 step Y1'!E638 -> 96 | C46: ='Formular 4 step Y1'!E639 -> 98 | D46: ='Formular 4 step Y1'!E640 -> 99 | E46: ='Formular 4 step Y1'!E641 -> 100 | F46: ='Formular 4 step Y1'!F638 -> 96 | G46: ='Formular 4 step Y1'!F639 -> 98 | H46: ='Formular 4 step Y1'!F640 -> 99 | I46: ='Formular 4 step Y1'!F641 -> 100 | J46: ='Formular 4 step Y1'!G638 -> 96 | K46: ='Formular 4 step Y1'!G639 -> 98 | L46: ='Formular 4 step Y1'!G640 -> 99 | M46: ='Formular 4 step Y1'!G641 -> 100 | N46: ='Formular 4 step Y1'!H638 -> 96 | O46: ='Formular 4 step Y1'!H639 -> 98 | P46: ='Formular 4 step Y1'!H640 -> 99 | Q46: ='Formular 4 step Y1'!H641 -> 100
A47: อะคูสติก-อิมเพรสชันME904 | B47: ='Formular 4 step Y1'!E663 -> 182 | C47: ='Formular 4 step Y1'!E664 -> 183 | D47: ='Formular 4 step Y1'!E665 -> 185 | E47: ='Formular 4 step Y1'!E666 -> 187 | F47: ='Formular 4 step Y1'!F663 -> 182 | G47: ='Formular 4 step Y1'!F664 -> 183 | H47: ='Formular 4 step Y1'!F665 -> 185 | I47: ='Formular 4 step Y1'!F666 -> 187 | J47: ='Formular 4 step Y1'!G663 -> 182 | K47: ='Formular 4 step Y1'!G664 -> 183 | L47: ='Formular 4 step Y1'!G665 -> 185 | M47: ='Formular 4 step Y1'!G666 -> 187 | N47: ='Formular 4 step Y1'!H663 -> 182 | O47: ='Formular 4 step Y1'!H664 -> 183 | P47: ='Formular 4 step Y1'!H665 -> 185 | Q47: ='Formular 4 step Y1'!H666 -> 187
A48: อะคูสติก-อิมเพรสชันME905 | B48: ='Formular 4 step Y1'!E688 -> 138 | C48: ='Formular 4 step Y1'!E689 -> 140 | D48: ='Formular 4 step Y1'!E690 -> 142 | E48: ='Formular 4 step Y1'!E691 -> 145 | F48: ='Formular 4 step Y1'!F688 -> 138 | G48: ='Formular 4 step Y1'!F689 -> 140 | H48: ='Formular 4 step Y1'!F690 -> 142 | I48: ='Formular 4 step Y1'!F691 -> 145 | J48: ='Formular 4 step Y1'!G688 -> 138 | K48: ='Formular 4 step Y1'!G689 -> 140 | L48: ='Formular 4 step Y1'!G690 -> 142 | M48: ='Formular 4 step Y1'!G691 -> 145 | N48: ='Formular 4 step Y1'!H688 -> 138 | O48: ='Formular 4 step Y1'!H689 -> 140 | P48: ='Formular 4 step Y1'!H690 -> 142 | Q48: ='Formular 4 step Y1'!H691 -> 145
A49: อะคูสติก-อิมเพรสชันME908 | B49: ='Formular 4 step Y1'!E713 -> 264 | C49: ='Formular 4 step Y1'!E714 -> 265 | D49: ='Formular 4 step Y1'!E715 -> 266 | E49: ='Formular 4 step Y1'!E716 -> 267 | F49: ='Formular 4 step Y1'!F713 -> 264 | G49: ='Formular 4 step Y1'!F714 -> 265 | H49: ='Formular 4 step Y1'!F715 -> 266 | I49: ='Formular 4 step Y1'!F716 -> 267 | J49: ='Formular 4 step Y1'!G713 -> 264 | K49: ='Formular 4 step Y1'!G714 -> 265 | L49: ='Formular 4 step Y1'!G715 -> 266 | M49: ='Formular 4 step Y1'!G716 -> 267 | N49: ='Formular 4 step Y1'!H713 -> 264 | O49: ='Formular 4 step Y1'!H714 -> 265 | P49: ='Formular 4 step Y1'!H715 -> 266 | Q49: ='Formular 4 step Y1'!H716 -> 267
A54: N Price | D54: CM | H54: CR | L54: PL | P54: NS
A55: Y1 : Smart Board | C55: WIP | D55: WIPR | E55: WIPRSO | G55: WIP | H55: WIPR | I55: WIPRSO | K55: WIP | L55: WIPR | M55: WIPRSO | O55: WIP | P55: WIPR | Q55: WIPRSO
B56: W1 | C56: W2 | D56: R1 | E56: R2 | F56: W1 | G56: W2 | H56: R1 | I56: R2 | J56: W1 | K56: W2 | L56: R1 | M56: R2 | N56: W1 | O56: W2 | P56: R1 | Q56: R2
A57: SB 120x240 4 mm ตราช้าง | B57: ='สูตร 4 step SB'!E13 -> 165 | C57: ='สูตร 4 step SB'!E14 -> 168 | D57: ='สูตร 4 step SB'!E15 -> 170 | E57: ='สูตร 4 step SB'!E16 -> 172 | F57: ='สูตร 4 step SB'!F13 -> 168 | G57: ='สูตร 4 step SB'!F14 -> 171 | H57: ='สูตร 4 step SB'!F15 -> 173 | I57: ='สูตร 4 step SB'!F16 -> 175 | J57: ='สูตร 4 step SB'!G13 -> 162 | K57: ='สูตร 4 step SB'!G14 -> 165 | L57: ='สูตร 4 step SB'!G15 -> 167 | M57: ='สูตร 4 step SB'!G16 -> 169 | N57: ='สูตร 4 step SB'!H13 -> 156 | O57: ='สูตร 4 step SB'!H14 -> 159 | P57: ='สูตร 4 step SB'!H15 -> 161 | Q57: ='สูตร 4 step SB'!H16 -> 163
A58: SB 120x120 4 mm ตราช้าง | B58: ='สูตร 4 step SB'!E41 -> 84 | C58: ='สูตร 4 step SB'!E42 -> 86 | D58: ='สูตร 4 step SB'!E43 -> 87 | E58: ='สูตร 4 step SB'!E44 -> 88 | F58: ='สูตร 4 step SB'!F41 -> 85 | G58: ='สูตร 4 step SB'!F42 -> 87 | H58: ='สูตร 4 step SB'!F43 -> 88 | I58: ='สูตร 4 step SB'!F44 -> 89 | J58: ='สูตร 4 step SB'!G41 -> 82 | K58: ='สูตร 4 step SB'!G42 -> 84 | L58: ='สูตร 4 step SB'!G43 -> 85 | M58: ='สูตร 4 step SB'!G44 -> 86 | N58: ='สูตร 4 step SB'!H41 -> 79 | O58: ='สูตร 4 step SB'!H42 -> 81 | P58: ='สูตร 4 step SB'!H43 -> 82 | Q58: ='สูตร 4 step SB'!H44 -> 83
A59: SB 60x240 4 mm ตราช้าง | B59: ='สูตร 4 step SB'!E68 -> 83 | C59: ='สูตร 4 step SB'!E69 -> 85 | D59: ='สูตร 4 step SB'!E70 -> 86 | E59: ='สูตร 4 step SB'!E71 -> 88 | F59: ='สูตร 4 step SB'!F68 -> 84 | G59: ='สูตร 4 step SB'!F69 -> 86 | H59: ='สูตร 4 step SB'!F70 -> 87 | I59: ='สูตร 4 step SB'!F71 -> 89 | J59: ='สูตร 4 step SB'!G68 -> 81 | K59: ='สูตร 4 step SB'!G69 -> 83 | L59: ='สูตร 4 step SB'!G70 -> 84 | M59: ='สูตร 4 step SB'!G71 -> 86 | N59: ='สูตร 4 step SB'!H68 -> 78 | O59: ='สูตร 4 step SB'!H69 -> 80 | P59: ='สูตร 4 step SB'!H70 -> 81 | Q59: ='สูตร 4 step SB'!H71 -> 83
A60: SB 60x120 4 mm ตราช้าง | B60: ='สูตร 4 step SB'!E344 -> 45 | C60: ='สูตร 4 step SB'!E345 -> 46 | D60: ='สูตร 4 step SB'!E346 -> 47 | E60: ='สูตร 4 step SB'!E347 -> 48 | F60: ='สูตร 4 step SB'!F344 -> 46 | G60: ='สูตร 4 step SB'!F345 -> 47 | H60: ='สูตร 4 step SB'!F346 -> 48 | I60: ='สูตร 4 step SB'!F347 -> 49 | J60: ='สูตร 4 step SB'!G344 -> 44 | K60: ='สูตร 4 step SB'!G345 -> 45 | L60: ='สูตร 4 step SB'!G346 -> 46 | M60: ='สูตร 4 step SB'!G347 -> 47 | N60: ='สูตร 4 step SB'!H344 -> 43 | O60: ='สูตร 4 step SB'!H345 -> 44 | P60: ='สูตร 4 step SB'!H346 -> 45 | Q60: ='สูตร 4 step SB'!H347 -> 46
A61: SB 120x240 6 mm ตราช้าง | B61: ='สูตร 4 step SB'!E96 -> 250 | C61: ='สูตร 4 step SB'!E97 -> 254 | D61: ='สูตร 4 step SB'!E98 -> 256 | E61: ='สูตร 4 step SB'!E99 -> 258 | F61: ='สูตร 4 step SB'!F96 -> 255 | G61: ='สูตร 4 step SB'!F97 -> 259 | H61: ='สูตร 4 step SB'!F98 -> 261 | I61: ='สูตร 4 step SB'!F99 -> 263 | J61: ='สูตร 4 step SB'!G96 -> 245 | K61: ='สูตร 4 step SB'!G97 -> 249 | L61: ='สูตร 4 step SB'!G98 -> 251 | M61: ='สูตร 4 step SB'!G99 -> 253 | N61: ='สูตร 4 step SB'!H96 -> 236 | O61: ='สูตร 4 step SB'!H97 -> 240 | P61: ='สูตร 4 step SB'!H98 -> 242 | Q61: ='สูตร 4 step SB'!H99 -> 244
A62: SB 120x240 8 mm ตราช้าง | B62: ='สูตร 4 step SB'!E124 -> 349 | C62: ='สูตร 4 step SB'!E125 -> 354 | D62: ='สูตร 4 step SB'!E126 -> 359 | E62: ='สูตร 4 step SB'!E127 -> 363 | F62: ='สูตร 4 step SB'!F124 -> 355 | G62: ='สูตร 4 step SB'!F125 -> 360 | H62: ='สูตร 4 step SB'!F126 -> 365 | I62: ='สูตร 4 step SB'!F127 -> 369 | J62: ='สูตร 4 step SB'!G124 -> 342 | K62: ='สูตร 4 step SB'!G125 -> 347 | L62: ='สูตร 4 step SB'!G126 -> 352 | M62: ='สูตร 4 step SB'!G127 -> 356 | N62: ='สูตร 4 step SB'!H124 -> 331 | O62: ='สูตร 4 step SB'!H125 -> 336 | P62: ='สูตร 4 step SB'!H126 -> 341 | Q62: ='สูตร 4 step SB'!H127 -> 345
A63: SB 120x240 10 mm ตราช้าง | B63: ='สูตร 4 step SB'!E152 -> 496 | C63: ='สูตร 4 step SB'!E153 -> 501 | D63: ='สูตร 4 step SB'!E154 -> 506 | E63: ='สูตร 4 step SB'!E155 -> 511 | F63: ='สูตร 4 step SB'!F152 -> 503 | G63: ='สูตร 4 step SB'!F153 -> 508 | H63: ='สูตร 4 step SB'!F154 -> 513 | I63: ='สูตร 4 step SB'!F155 -> 518 | J63: ='สูตร 4 step SB'!G152 -> 488 | K63: ='สูตร 4 step SB'!G153 -> 493 | L63: ='สูตร 4 step SB'!G154 -> 498 | M63: ='สูตร 4 step SB'!G155 -> 503 | N63: ='สูตร 4 step SB'!H152 -> 473 | O63: ='สูตร 4 step SB'!H153 -> 478 | P63: ='สูตร 4 step SB'!H154 -> 483 | Q63: ='สูตร 4 step SB'!H155 -> 488
A64: SB 120x240 12 mm ตราช้าง | B64: ='สูตร 4 step SB'!E179 -> 601 | C64: ='สูตร 4 step SB'!E180 -> 606 | D64: ='สูตร 4 step SB'!E181 -> 611 | E64: ='สูตร 4 step SB'!E182 -> 616 | F64: ='สูตร 4 step SB'!F179 -> 610 | G64: ='สูตร 4 step SB'!F180 -> 615 | H64: ='สูตร 4 step SB'!F181 -> 620 | I64: ='สูตร 4 step SB'!F182 -> 625 | J64: ='สูตร 4 step SB'!G179 -> 592 | K64: ='สูตร 4 step SB'!G180 -> 597 | L64: ='สูตร 4 step SB'!G181 -> 602 | M64: ='สูตร 4 step SB'!G182 -> 607 | N64: ='สูตร 4 step SB'!H179 -> 574 | O64: ='สูตร 4 step SB'!H180 -> 579 | P64: ='สูตร 4 step SB'!H181 -> 584 | Q64: ='สูตร 4 step SB'!H182 -> 589
A65: SB 120x240 15 mm ตราช้าง | B65: ='สูตร 4 step SB'!E645 -> 692 | C65: ='สูตร 4 step SB'!E646 -> 702 | D65: ='สูตร 4 step SB'!E647 -> 712 | E65: ='สูตร 4 step SB'!E648 -> 717 | F65: ='สูตร 4 step SB'!F645 -> 704 | G65: ='สูตร 4 step SB'!F646 -> 714 | H65: ='สูตร 4 step SB'!F647 -> 724 | I65: ='สูตร 4 step SB'!F648 -> 729 | J65: ='สูตร 4 step SB'!G645 -> 681 | K65: ='สูตร 4 step SB'!G646 -> 691 | L65: ='สูตร 4 step SB'!G647 -> 701 | M65: ='สูตร 4 step SB'!G648 -> 706 | N65: ='สูตร 4 step SB'!H645 -> 659 | O65: ='สูตร 4 step SB'!H646 -> 669 | P65: ='สูตร 4 step SB'!H647 -> 679 | Q65: ='สูตร 4 step SB'!H648 -> 684
A66: SB 120x240 16 mm ตราช้าง | B66: ='สูตร 4 step SB'!E672 -> 733 | C66: ='สูตร 4 step SB'!E673 -> 743 | D66: ='สูตร 4 step SB'!E674 -> 753 | E66: ='สูตร 4 step SB'!E675 -> 763 | F66: ='สูตร 4 step SB'!F672 -> 746 | G66: ='สูตร 4 step SB'!F673 -> 756 | H66: ='สูตร 4 step SB'!F674 -> 766 | I66: ='สูตร 4 step SB'!F675 -> 776 | J66: ='สูตร 4 step SB'!G672 -> 720 | K66: ='สูตร 4 step SB'!G673 -> 730 | L66: ='สูตร 4 step SB'!G674 -> 740 | M66: ='สูตร 4 step SB'!G675 -> 750 | N66: ='สูตร 4 step SB'!H672 -> 697 | O66: ='สูตร 4 step SB'!H673 -> 707 | P66: ='สูตร 4 step SB'!H674 -> 717 | Q66: ='สูตร 4 step SB'!H675 -> 727
A67: SB 120x240 18 mm ตราช้าง | B67: ='สูตร 4 step SB'!E699 -> 827 | C67: ='สูตร 4 step SB'!E700 -> 837 | D67: ='สูตร 4 step SB'!E701 -> 857 | E67: ='สูตร 4 step SB'!E702 -> 867 | F67: ='สูตร 4 step SB'!F699 -> 842 | G67: ='สูตร 4 step SB'!F700 -> 852 | H67: ='สูตร 4 step SB'!F701 -> 872 | I67: ='สูตร 4 step SB'!F702 -> 882 | J67: ='สูตร 4 step SB'!G699 -> 813 | K67: ='สูตร 4 step SB'!G700 -> 823 | L67: ='สูตร 4 step SB'!G701 -> 843 | M67: ='สูตร 4 step SB'!G702 -> 853 | N67: ='สูตร 4 step SB'!H699 -> 787 | O67: ='สูตร 4 step SB'!H700 -> 797 | P67: ='สูตร 4 step SB'!H701 -> 817 | Q67: ='สูตร 4 step SB'!H702 -> 827
A68: SB 120x240 20 mm ตราช้าง | B68: ='สูตร 4 step SB'!E726 -> 926 | C68: ='สูตร 4 step SB'!E727 -> 936 | D68: ='สูตร 4 step SB'!E728 -> 951 | E68: ='สูตร 4 step SB'!E729 -> 966 | F68: ='สูตร 4 step SB'!F726 -> 942 | G68: ='สูตร 4 step SB'!F727 -> 952 | H68: ='สูตร 4 step SB'!F728 -> 967 | I68: ='สูตร 4 step SB'!F729 -> 982 | J68: ='สูตร 4 step SB'!G726 -> 911 | K68: ='สูตร 4 step SB'!G727 -> 921 | L68: ='สูตร 4 step SB'!G728 -> 936 | M68: ='สูตร 4 step SB'!G729 -> 951 | N68: ='สูตร 4 step SB'!H726 -> 881 | O68: ='สูตร 4 step SB'!H727 -> 891 | P68: ='สูตร 4 step SB'!H728 -> 906 | Q68: ='สูตร 4 step SB'!H729 -> 921
A69: SB 120x280 8 mm ตราช้าง | B69: ='สูตร 4 step SB'!E206 -> 445 | C69: ='สูตร 4 step SB'!E207 -> 450 | D69: ='สูตร 4 step SB'!E208 -> 455 | E69: ='สูตร 4 step SB'!E209 -> 460 | F69: ='สูตร 4 step SB'!F206 -> 452 | G69: ='สูตร 4 step SB'!F207 -> 457 | H69: ='สูตร 4 step SB'!F208 -> 462 | I69: ='สูตร 4 step SB'!F209 -> 467 | J69: ='สูตร 4 step SB'!G206 -> 438 | K69: ='สูตร 4 step SB'!G207 -> 443 | L69: ='สูตร 4 step SB'!G208 -> 448 | M69: ='สูตร 4 step SB'!G209 -> 453 | N69: ='สูตร 4 step SB'!H206 -> 425 | O69: ='สูตร 4 step SB'!H207 -> 430 | P69: ='สูตร 4 step SB'!H208 -> 435 | Q69: ='สูตร 4 step SB'!H209 -> 440
A70: ลายไม้/เซาะร่อง ตราช้าง | B70: ='สูตร 4 step SB'!E234 -> 55 | C70: ='สูตร 4 step SB'!E235 -> 56 | D70: ='สูตร 4 step SB'!E236 -> 57 | E70: ='สูตร 4 step SB'!E237 -> 58 | F70: ='สูตร 4 step SB'!F234 -> 56 | G70: ='สูตร 4 step SB'!F235 -> 57 | H70: ='สูตร 4 step SB'!F236 -> 58 | I70: ='สูตร 4 step SB'!F237 -> 59 | J70: ='สูตร 4 step SB'!G234 -> 54 | K70: ='สูตร 4 step SB'!G235 -> 55 | L70: ='สูตร 4 step SB'!G236 -> 56 | M70: ='สูตร 4 step SB'!G237 -> 57 | N70: ='สูตร 4 step SB'!H234 -> 53 | O70: ='สูตร 4 step SB'!H235 -> 54 | P70: ='สูตร 4 step SB'!H236 -> 55 | Q70: ='สูตร 4 step SB'!H237 -> 56
A71: ระบายอากาศ ตราช้าง | B71: ='สูตร 4 step SB'!E262 -> 51 | C71: ='สูตร 4 step SB'!E263 -> 52 | D71: ='สูตร 4 step SB'!E264 -> 53 | E71: ='สูตร 4 step SB'!E265 -> 54 | F71: ='สูตร 4 step SB'!F262 -> 52 | G71: ='สูตร 4 step SB'!F263 -> 53 | H71: ='สูตร 4 step SB'!F264 -> 54 | I71: ='สูตร 4 step SB'!F265 -> 55 | J71: ='สูตร 4 step SB'!G262 -> 50 | K71: ='สูตร 4 step SB'!G263 -> 51 | L71: ='สูตร 4 step SB'!G264 -> 52 | M71: ='สูตร 4 step SB'!G265 -> 53 | N71: ='สูตร 4 step SB'!H262 -> 49 | O71: ='สูตร 4 step SB'!H263 -> 50 | P71: ='สูตร 4 step SB'!H264 -> 51 | Q71: ='สูตร 4 step SB'!H265 -> 52
A72: ระบายอากาศโพรเทคชั่น ตราช้าง | B72: ='สูตร 4 step SB'!E618 -> 71 | C72: ='สูตร 4 step SB'!E619 -> 72 | D72: ='สูตร 4 step SB'!E620 -> 73 | E72: ='สูตร 4 step SB'!E621 -> 74 | F72: ='สูตร 4 step SB'!F618 -> 72 | G72: ='สูตร 4 step SB'!F619 -> 73 | H72: ='สูตร 4 step SB'!F620 -> 74 | I72: ='สูตร 4 step SB'!F621 -> 75 | J72: ='สูตร 4 step SB'!G618 -> 70 | K72: ='สูตร 4 step SB'!G619 -> 71 | L72: ='สูตร 4 step SB'!G620 -> 72 | M72: ='สูตร 4 step SB'!G621 -> 73 | N72: ='สูตร 4 step SB'!H618 -> 68 | O72: ='สูตร 4 step SB'!H619 -> 69 | P72: ='สูตร 4 step SB'!H620 -> 70 | Q72: ='สูตร 4 step SB'!H621 -> 71
A73: ลายไม้ ระบายอากาศ /เซาะร่อง ระบายอากาศ ตราช้าง | B73: ='สูตร 4 step SB'!E290 -> 58 | C73: ='สูตร 4 step SB'!E291 -> 59 | D73: ='สูตร 4 step SB'!E292 -> 60 | E73: ='สูตร 4 step SB'!E293 -> 61 | F73: ='สูตร 4 step SB'!F290 -> 59 | G73: ='สูตร 4 step SB'!F291 -> 60 | H73: ='สูตร 4 step SB'!F292 -> 61 | I73: ='สูตร 4 step SB'!F293 -> 62 | J73: ='สูตร 4 step SB'!G290 -> 58 | K73: ='สูตร 4 step SB'!G291 -> 59 | L73: ='สูตร 4 step SB'!G292 -> 60 | M73: ='สูตร 4 step SB'!G293 -> 61 | N73: ='สูตร 4 step SB'!H290 -> 56 | O73: ='สูตร 4 step SB'!H291 -> 57 | P73: ='สูตร 4 step SB'!H292 -> 58 | Q73: ='สูตร 4 step SB'!H293 -> 59
A74: ลายไม้/เซาะร่อง (ระบายอากาศ โพรเทคชั่น) ตราช้าง | B74: ='สูตร 4 step SB'!E318 -> 77 | C74: ='สูตร 4 step SB'!E319 -> 79 | D74: ='สูตร 4 step SB'!E320 -> 80 | E74: ='สูตร 4 step SB'!E321 -> 82 | F74: ='สูตร 4 step SB'!F318 -> 78 | G74: ='สูตร 4 step SB'!F319 -> 80 | H74: ='สูตร 4 step SB'!F320 -> 81 | I74: ='สูตร 4 step SB'!F321 -> 83 | J74: ='สูตร 4 step SB'!G318 -> 76 | K74: ='สูตร 4 step SB'!G319 -> 78 | L74: ='สูตร 4 step SB'!G320 -> 79 | M74: ='สูตร 4 step SB'!G321 -> 81 | N74: ='สูตร 4 step SB'!H318 -> 75 | O74: ='สูตร 4 step SB'!H319 -> 77 | P74: ='สูตร 4 step SB'!H320 -> 78 | Q74: ='สูตร 4 step SB'!H321 -> 80
A76: บอร์ดซูปเปอร์ซัน 4 มม.120x240 | B76: ='สูตร 4 step SB'!E426 -> 125 | C76: ='สูตร 4 step SB'!E427 -> 127 | D76: ='สูตร 4 step SB'!E428 -> 129 | E76: ='สูตร 4 step SB'!E429 -> 131 | F76: ='สูตร 4 step SB'!F426 -> 128 | G76: ='สูตร 4 step SB'!F427 -> 130 | H76: ='สูตร 4 step SB'!F428 -> 132 | I76: ='สูตร 4 step SB'!F429 -> 134 | J76: ='สูตร 4 step SB'!G426 -> 122 | K76: ='สูตร 4 step SB'!G427 -> 124 | L76: ='สูตร 4 step SB'!G428 -> 126 | M76: ='สูตร 4 step SB'!G429 -> 128 | N76: ='สูตร 4 step SB'!H426 -> 116 | O76: ='สูตร 4 step SB'!H427 -> 118 | P76: ='สูตร 4 step SB'!H428 -> 120 | Q76: ='สูตร 4 step SB'!H429 -> 122
A77: บอร์ดซูปเปอร์ซัน 4 มม.120x120 | B77: ='สูตร 4 step SB'!E454 -> 64 | C77: ='สูตร 4 step SB'!E455 -> 65 | D77: ='สูตร 4 step SB'!E456 -> 66 | E77: ='สูตร 4 step SB'!E457 -> 67 | F77: ='สูตร 4 step SB'!F454 -> 65 | G77: ='สูตร 4 step SB'!F455 -> 66 | H77: ='สูตร 4 step SB'!F456 -> 67 | I77: ='สูตร 4 step SB'!F457 -> 68 | J77: ='สูตร 4 step SB'!G454 -> 62 | K77: ='สูตร 4 step SB'!G455 -> 63 | L77: ='สูตร 4 step SB'!G456 -> 64 | M77: ='สูตร 4 step SB'!G457 -> 65 | N77: ='สูตร 4 step SB'!H454 -> 59 | O77: ='สูตร 4 step SB'!H455 -> 60 | P77: ='สูตร 4 step SB'!H456 -> 61 | Q77: ='สูตร 4 step SB'!H457 -> 62
A78: บอร์ดซูปเปอร์ซัน 4 มม.60x240 | B78: ='สูตร 4 step SB'!E481 -> 64 | C78: ='สูตร 4 step SB'!E482 -> 65 | D78: ='สูตร 4 step SB'!E483 -> 66 | E78: ='สูตร 4 step SB'!E484 -> 67 | F78: ='สูตร 4 step SB'!F481 -> 65 | G78: ='สูตร 4 step SB'!F482 -> 66 | H78: ='สูตร 4 step SB'!F483 -> 67 | I78: ='สูตร 4 step SB'!F484 -> 68 | J78: ='สูตร 4 step SB'!G481 -> 62 | K78: ='สูตร 4 step SB'!G482 -> 63 | L78: ='สูตร 4 step SB'!G483 -> 64 | M78: ='สูตร 4 step SB'!G484 -> 65 | N78: ='สูตร 4 step SB'!H481 -> 59 | O78: ='สูตร 4 step SB'!H482 -> 60 | P78: ='สูตร 4 step SB'!H483 -> 61 | Q78: ='สูตร 4 step SB'!H484 -> 62
A79: บอร์ดซูปเปอร์ซัน 6 มม.120x240 | B79: ='สูตร 4 step SB'!E509 -> 189 | C79: ='สูตร 4 step SB'!E510 -> 192 | D79: ='สูตร 4 step SB'!E511 -> 194 | E79: ='สูตร 4 step SB'!E512 -> 196 | F79: ='สูตร 4 step SB'!F509 -> 194 | G79: ='สูตร 4 step SB'!F510 -> 197 | H79: ='สูตร 4 step SB'!F511 -> 199 | I79: ='สูตร 4 step SB'!F512 -> 201 | J79: ='สูตร 4 step SB'!G509 -> 184 | K79: ='สูตร 4 step SB'!G510 -> 187 | L79: ='สูตร 4 step SB'!G511 -> 189 | M79: ='สูตร 4 step SB'!G512 -> 191 | N79: ='สูตร 4 step SB'!H509 -> 176 | O79: ='สูตร 4 step SB'!H510 -> 179 | P79: ='สูตร 4 step SB'!H511 -> 181 | Q79: ='สูตร 4 step SB'!H512 -> 183
A80: บอร์ดซูปเปอร์ซัน 8 มม.120x240 | B80: ='สูตร 4 step SB'!E591 -> 288 | C80: ='สูตร 4 step SB'!E592 -> 292 | D80: ='สูตร 4 step SB'!E593 -> 294 | E80: ='สูตร 4 step SB'!E594 -> 296 | F80: ='สูตร 4 step SB'!F591 -> 294 | G80: ='สูตร 4 step SB'!F592 -> 298 | H80: ='สูตร 4 step SB'!F593 -> 300 | I80: ='สูตร 4 step SB'!F594 -> 302 | J80: ='สูตร 4 step SB'!G591 -> 282 | K80: ='สูตร 4 step SB'!G592 -> 286 | L80: ='สูตร 4 step SB'!G593 -> 288 | M80: ='สูตร 4 step SB'!G594 -> 290 | N80: ='สูตร 4 step SB'!H591 -> 270 | O80: ='สูตร 4 step SB'!H592 -> 274 | P80: ='สูตร 4 step SB'!H593 -> 276 | Q80: ='สูตร 4 step SB'!H594 -> 278
A81: บอร์ดซูปเปอร์ซัน 15 มม.120x240 | B81: ='สูตร 4 step SB'!E1198 -> 565 | C81: ='สูตร 4 step SB'!E1199 -> 575 | D81: ='สูตร 4 step SB'!E1200 -> 585 | E81: ='สูตร 4 step SB'!E1201 -> 595 | F81: ='สูตร 4 step SB'!F1198 -> 577 | G81: ='สูตร 4 step SB'!F1199 -> 587 | H81: ='สูตร 4 step SB'!F1200 -> 597 | I81: ='สูตร 4 step SB'!F1201 -> 607 | J81: ='สูตร 4 step SB'!G1198 -> 553 | K81: ='สูตร 4 step SB'!G1199 -> 563 | L81: ='สูตร 4 step SB'!G1200 -> 573 | M81: ='สูตร 4 step SB'!G1201 -> 583 | N81: ='สูตร 4 step SB'!H1198 -> 532 | O81: ='สูตร 4 step SB'!H1199 -> 542 | P81: ='สูตร 4 step SB'!H1200 -> 552 | Q81: ='สูตร 4 step SB'!H1201 -> 562
A82: บอร์ดซูปเปอร์ซัน 20 มม.120x240
A84: ไม้มอบ ตราช้าง | B84: ='สูตร 4 step SB'!E370 -> 46 | C84: ='สูตร 4 step SB'!E371 -> 47 | D84: ='สูตร 4 step SB'!E372 -> 48 | E84: ='สูตร 4 step SB'!E373 -> 49 | F84: ='สูตร 4 step SB'!F370 -> 47 | G84: ='สูตร 4 step SB'!F371 -> 48 | H84: ='สูตร 4 step SB'!F372 -> 49 | I84: ='สูตร 4 step SB'!F373 -> 50 | J84: ='สูตร 4 step SB'!G370 -> 46 | K84: ='สูตร 4 step SB'!G371 -> 47 | L84: ='สูตร 4 step SB'!G372 -> 48 | M84: ='สูตร 4 step SB'!G373 -> 49 | N84: ='สูตร 4 step SB'!H370 -> 45 | O84: ='สูตร 4 step SB'!H371 -> 46 | P84: ='สูตร 4 step SB'!H372 -> 47 | Q84: ='สูตร 4 step SB'!H373 -> 48
A85: ไม้ระแนงลบมุม ซิเมนต็ 7.5 ตราช้าง | B85: ='สูตร 4 step SB'!E398 -> 39 | C85: ='สูตร 4 step SB'!E399 -> 40 | D85: ='สูตร 4 step SB'!E400 -> 41 | E85: ='สูตร 4 step SB'!E401 -> 42 | F85: ='สูตร 4 step SB'!F398 -> 40 | G85: ='สูตร 4 step SB'!F399 -> 41 | H85: ='สูตร 4 step SB'!F400 -> 42 | I85: ='สูตร 4 step SB'!F401 -> 43 | J85: ='สูตร 4 step SB'!G398 -> 39 | K85: ='สูตร 4 step SB'!G399 -> 40 | L85: ='สูตร 4 step SB'!G400 -> 41 | M85: ='สูตร 4 step SB'!G401 -> 42 | N85: ='สูตร 4 step SB'!H398 -> 38 | O85: ='สูตร 4 step SB'!H399 -> 39 | P85: ='สูตร 4 step SB'!H400 -> 40 | Q85: ='สูตร 4 step SB'!H401 -> 41
A86: ไม้ระแนงลบมุม ซิเมนต์ 10 ตราช้าง | B86: ='สูตร 4 step SB'!E1143 -> 49 | C86: ='สูตร 4 step SB'!E1144 -> 50 | D86: ='สูตร 4 step SB'!E1145 -> 51 | E86: ='สูตร 4 step SB'!E1146 -> 53 | F86: ='สูตร 4 step SB'!F1143 -> 50 | G86: ='สูตร 4 step SB'!F1144 -> 51 | H86: ='สูตร 4 step SB'!F1145 -> 52 | I86: ='สูตร 4 step SB'!F1146 -> 54 | J86: ='สูตร 4 step SB'!G1143 -> 49 | K86: ='สูตร 4 step SB'!G1144 -> 50 | L86: ='สูตร 4 step SB'!G1145 -> 51 | M86: ='สูตร 4 step SB'!G1146 -> 53 | N86: ='สูตร 4 step SB'!H1143 -> 48 | O86: ='สูตร 4 step SB'!H1144 -> 49 | P86: ='สูตร 4 step SB'!H1145 -> 50 | Q86: ='สูตร 4 step SB'!H1146 -> 52
A87: ไม้มอบ ซุปเปอร์ซัน | B87: ='สูตร 4 step SB'!E536 -> 30 | C87: ='สูตร 4 step SB'!E537 -> 31 | D87: ='สูตร 4 step SB'!E538 -> 32 | E87: ='สูตร 4 step SB'!E539 -> 33 | F87: ='สูตร 4 step SB'!F536 -> 31 | G87: ='สูตร 4 step SB'!F537 -> 32 | H87: ='สูตร 4 step SB'!F538 -> 33 | I87: ='สูตร 4 step SB'!F539 -> 34 | J87: ='สูตร 4 step SB'!G536 -> 30 | K87: ='สูตร 4 step SB'!G537 -> 31 | L87: ='สูตร 4 step SB'!G538 -> 32 | M87: ='สูตร 4 step SB'!G539 -> 33 | N87: ='สูตร 4 step SB'!H536 -> 29 | O87: ='สูตร 4 step SB'!H537 -> 30 | P87: ='สูตร 4 step SB'!H538 -> 31 | Q87: ='สูตร 4 step SB'!H539 -> 32
A88: ไม้ระแนงลบมุม 7.5 ซุปเปอร์ซัน | B88: ='สูตร 4 step SB'!E564 -> 33 | C88: ='สูตร 4 step SB'!E565 -> 34 | D88: ='สูตร 4 step SB'!E566 -> 35 | E88: ='สูตร 4 step SB'!E567 -> 36 | F88: ='สูตร 4 step SB'!F564 -> 33 | G88: ='สูตร 4 step SB'!F565 -> 34 | H88: ='สูตร 4 step SB'!F566 -> 35 | I88: ='สูตร 4 step SB'!F567 -> 36 | J88: ='สูตร 4 step SB'!G564 -> 32 | K88: ='สูตร 4 step SB'!G565 -> 33 | L88: ='สูตร 4 step SB'!G566 -> 34 | M88: ='สูตร 4 step SB'!G567 -> 35 | N88: ='สูตร 4 step SB'!H564 -> 31 | O88: ='สูตร 4 step SB'!H565 -> 32 | P88: ='สูตร 4 step SB'!H566 -> 33 | Q88: ='สูตร 4 step SB'!H567 -> 34
A90: ไม้ฝา ซูเปอร์ซัน 15*300*0.8 สีซิเมนต์ | B90: ='สูตร 4 step SB'!E753 -> 46 | C90: ='สูตร 4 step SB'!E754 -> 47 | D90: ='สูตร 4 step SB'!E755 -> 48 | E90: ='สูตร 4 step SB'!E756 -> 49 | F90: ='สูตร 4 step SB'!F753 -> 47 | G90: ='สูตร 4 step SB'!F754 -> 48 | H90: ='สูตร 4 step SB'!F755 -> 49 | I90: ='สูตร 4 step SB'!F756 -> 50 | J90: ='สูตร 4 step SB'!G753 -> 45 | K90: ='สูตร 4 step SB'!G754 -> 46 | L90: ='สูตร 4 step SB'!G755 -> 47 | M90: ='สูตร 4 step SB'!G756 -> 48 | N90: ='สูตร 4 step SB'!H753 -> 43 | O90: ='สูตร 4 step SB'!H754 -> 44 | P90: ='สูตร 4 step SB'!H755 -> 45 | Q90: ='สูตร 4 step SB'!H756 -> 46
A91: ไม้ฝา ซูเปอร์ซัน 15*400*0.8 สีซิเมนต์ | B91: ='สูตร 4 step SB'!E975 -> 61 | C91: ='สูตร 4 step SB'!E976 -> 62 | D91: ='สูตร 4 step SB'!E977 -> 63 | E91: ='สูตร 4 step SB'!E978 -> 64 | F91: ='สูตร 4 step SB'!F975 -> 63 | G91: ='สูตร 4 step SB'!F976 -> 64 | H91: ='สูตร 4 step SB'!F977 -> 65 | I91: ='สูตร 4 step SB'!F978 -> 66 | J91: ='สูตร 4 step SB'!G975 -> 60 | K91: ='สูตร 4 step SB'!G976 -> 61 | L91: ='สูตร 4 step SB'!G977 -> 62 | M91: ='สูตร 4 step SB'!G978 -> 63 | N91: ='สูตร 4 step SB'!H975 -> 58 | O91: ='สูตร 4 step SB'!H976 -> 59 | P91: ='สูตร 4 step SB'!H977 -> 60 | Q91: ='สูตร 4 step SB'!H978 -> 61
A92: ไม้ฝา ซูเปอร์ซัน 20*300*0.8 สีซิเมนต์ | B92: ='สูตร 4 step SB'!E1003 -> 61 | C92: ='สูตร 4 step SB'!E1001 -> 57.828636 | D92: ='สูตร 4 step SB'!E1003 -> 61 | E92: ='สูตร 4 step SB'!E1004 -> 62 | F92: ='สูตร 4 step SB'!F1003 -> 63 | G92: ='สูตร 4 step SB'!F1001 -> 59.1225 | H92: ='สูตร 4 step SB'!F1003 -> 63 | I92: ='สูตร 4 step SB'!F1004 -> 64 | J92: ='สูตร 4 step SB'!G1003 -> 60 | K92: ='สูตร 4 step SB'!G1001 -> 56.535 | L92: ='สูตร 4 step SB'!G1003 -> 60 | M92: ='สูตร 4 step SB'!G1004 -> 61 | N92: ='สูตร 4 step SB'!H1003 -> 58 | O92: ='สูตร 4 step SB'!H1001 -> 54.132273 | P92: ='สูตร 4 step SB'!H1003 -> 58 | Q92: ='สูตร 4 step SB'!H1004 -> 59
A93: ไม้ฝา ซูเปอร์ซัน 20*400*0.8 สีซิเมนต์ | B93: ='สูตร 4 step SB'!E1031 -> 81 | C93: ='สูตร 4 step SB'!E1032 -> 82 | D93: ='สูตร 4 step SB'!E1033 -> 83 | E93: ='สูตร 4 step SB'!E1034 -> 84 | F93: ='สูตร 4 step SB'!F1031 -> 82 | G93: ='สูตร 4 step SB'!F1032 -> 83 | H93: ='สูตร 4 step SB'!F1033 -> 84 | I93: ='สูตร 4 step SB'!F1034 -> 85 | J93: ='สูตร 4 step SB'!G1031 -> 79 | K93: ='สูตร 4 step SB'!G1032 -> 80 | L93: ='สูตร 4 step SB'!G1033 -> 81 | M93: ='สูตร 4 step SB'!G1034 -> 82 | N93: ='สูตร 4 step SB'!H1031 -> 76 | O93: ='สูตร 4 step SB'!H1032 -> 77 | P93: ='สูตร 4 step SB'!H1033 -> 78 | Q93: ='สูตร 4 step SB'!H1034 -> 79
A94: ไม้พื้น ซูเปอร์ซัน ลายไม้ 10*300*2.5 รองพื้น | B94: ='สูตร 4 step SB'!E1059 -> 191 | C94: ='สูตร 4 step SB'!E1060 -> 194 | D94: ='สูตร 4 step SB'!E1061 -> 196 | E94: ='สูตร 4 step SB'!E1062 -> 198 | F94: ='สูตร 4 step SB'!F1059 -> 193 | G94: ='สูตร 4 step SB'!F1060 -> 196 | H94: ='สูตร 4 step SB'!F1061 -> 198 | I94: ='สูตร 4 step SB'!F1062 -> 200 | J94: ='สูตร 4 step SB'!G1059 -> 189 | K94: ='สูตร 4 step SB'!G1060 -> 192 | L94: ='สูตร 4 step SB'!G1061 -> 194 | M94: ='สูตร 4 step SB'!G1062 -> 196 | N94: ='สูตร 4 step SB'!H1059 -> 185 | O94: ='สูตร 4 step SB'!H1060 -> 188 | P94: ='สูตร 4 step SB'!H1061 -> 190 | Q94: ='สูตร 4 step SB'!H1062 -> 192
A95: ไม้พื้น ซูเปอร์ซัน ลายไม้ 15*300*2.5 รองพื้น | B95: ='สูตร 4 step SB'!E1087 -> 287 | C95: ='สูตร 4 step SB'!E1088 -> 291 | D95: ='สูตร 4 step SB'!E1089 -> 294 | E95: ='สูตร 4 step SB'!E1090 -> 297 | F95: ='สูตร 4 step SB'!F1087 -> 290 | G95: ='สูตร 4 step SB'!F1088 -> 294 | H95: ='สูตร 4 step SB'!F1089 -> 297 | I95: ='สูตร 4 step SB'!F1090 -> 300 | J95: ='สูตร 4 step SB'!G1087 -> 284 | K95: ='สูตร 4 step SB'!G1088 -> 288 | L95: ='สูตร 4 step SB'!G1089 -> 291 | M95: ='สูตร 4 step SB'!G1090 -> 294 | N95: ='สูตร 4 step SB'!H1087 -> 278 | O95: ='สูตร 4 step SB'!H1088 -> 282 | P95: ='สูตร 4 step SB'!H1089 -> 285 | Q95: ='สูตร 4 step SB'!H1090 -> 288
A96: ไม้พื้น ซูเปอร์ซัน ลายไม้ 20*300*2.5 รองพื้น | B96: ='สูตร 4 step SB'!E1115 -> 380 | C96: ='สูตร 4 step SB'!E1116 -> 385 | D96: ='สูตร 4 step SB'!E1117 -> 390 | E96: ='สูตร 4 step SB'!E1118 -> 395 | F96: ='สูตร 4 step SB'!F1115 -> 384 | G96: ='สูตร 4 step SB'!F1116 -> 389 | H96: ='สูตร 4 step SB'!F1117 -> 394 | I96: ='สูตร 4 step SB'!F1118 -> 399 | J96: ='สูตร 4 step SB'!G1115 -> 376 | K96: ='สูตร 4 step SB'!G1116 -> 381 | L96: ='สูตร 4 step SB'!G1117 -> 386 | M96: ='สูตร 4 step SB'!G1118 -> 391 | N96: ='สูตร 4 step SB'!H1115 -> 368 | O96: ='สูตร 4 step SB'!H1116 -> 373 | P96: ='สูตร 4 step SB'!H1117 -> 378 | Q96: ='สูตร 4 step SB'!H1118 -> 383
A98: ซีเมนต์บอร์ด 120*240*8 มม.(60) | B98: ='สูตร 4 step SB'!E807 -> 349 | C98: ='สูตร 4 step SB'!E808 -> 354 | D98: ='สูตร 4 step SB'!E809 -> 359 | E98: ='สูตร 4 step SB'!E810 -> 364 | F98: ='สูตร 4 step SB'!F807 -> 354 | G98: ='สูตร 4 step SB'!F808 -> 359 | H98: ='สูตร 4 step SB'!F809 -> 364 | I98: ='สูตร 4 step SB'!F810 -> 369 | J98: ='สูตร 4 step SB'!G807 -> 344 | K98: ='สูตร 4 step SB'!G808 -> 349 | L98: ='สูตร 4 step SB'!G809 -> 354 | M98: ='สูตร 4 step SB'!G810 -> 359 | N98: ='สูตร 4 step SB'!H807 -> 341 | O98: ='สูตร 4 step SB'!H808 -> 346 | P98: ='สูตร 4 step SB'!H809 -> 351 | Q98: ='สูตร 4 step SB'!H810 -> 356
A99: ซีเมนต์บอร์ด 120*240*10 มม.(48) | B99: ='สูตร 4 step SB'!E835 -> 424 | C99: ='สูตร 4 step SB'!E836 -> 429 | D99: ='สูตร 4 step SB'!E837 -> 434 | E99: ='สูตร 4 step SB'!E838 -> 439 | F99: ='สูตร 4 step SB'!F835 -> 430 | G99: ='สูตร 4 step SB'!F836 -> 435 | H99: ='สูตร 4 step SB'!F837 -> 440 | I99: ='สูตร 4 step SB'!F838 -> 445 | J99: ='สูตร 4 step SB'!G835 -> 418 | K99: ='สูตร 4 step SB'!G836 -> 423 | L99: ='สูตร 4 step SB'!G837 -> 428 | M99: ='สูตร 4 step SB'!G838 -> 433 | N99: ='สูตร 4 step SB'!H835 -> 413 | O99: ='สูตร 4 step SB'!H836 -> 418 | P99: ='สูตร 4 step SB'!H837 -> 423 | Q99: ='สูตร 4 step SB'!H838 -> 428
A100: ซีเมนต์บอร์ด 120*240*12 มม.(40) | B100: ='สูตร 4 step SB'!E863 -> 488 | C100: ='สูตร 4 step SB'!E864 -> 493 | D100: ='สูตร 4 step SB'!E865 -> 498 | E100: ='สูตร 4 step SB'!E866 -> 503 | F100: ='สูตร 4 step SB'!F863 -> 496 | G100: ='สูตร 4 step SB'!F864 -> 501 | H100: ='สูตร 4 step SB'!F865 -> 506 | I100: ='สูตร 4 step SB'!F866 -> 511 | J100: ='สูตร 4 step SB'!G863 -> 481 | K100: ='สูตร 4 step SB'!G864 -> 486 | L100: ='สูตร 4 step SB'!G865 -> 491 | M100: ='สูตร 4 step SB'!G866 -> 496 | N100: ='สูตร 4 step SB'!H863 -> 476 | O100: ='สูตร 4 step SB'!H864 -> 481 | P100: ='สูตร 4 step SB'!H865 -> 486 | Q100: ='สูตร 4 step SB'!H866 -> 491
A101: ซีเมนต์บอร์ด 120*240*16 มม.(30) | B101: ='สูตร 4 step SB'!E891 -> 587 | C101: ='สูตร 4 step SB'!E892 -> 592 | D101: ='สูตร 4 step SB'!E893 -> 597 | E101: ='สูตร 4 step SB'!E894 -> 602 | F101: ='สูตร 4 step SB'!F891 -> 598 | G101: ='สูตร 4 step SB'!F892 -> 603 | H101: ='สูตร 4 step SB'!F893 -> 608 | I101: ='สูตร 4 step SB'!F894 -> 613 | J101: ='สูตร 4 step SB'!G891 -> 577 | K101: ='สูตร 4 step SB'!G892 -> 582 | L101: ='สูตร 4 step SB'!G893 -> 587 | M101: ='สูตร 4 step SB'!G894 -> 592 | N101: ='สูตร 4 step SB'!H891 -> 570 | O101: ='สูตร 4 step SB'!H892 -> 575 | P101: ='สูตร 4 step SB'!H893 -> 580 | Q101: ='สูตร 4 step SB'!H894 -> 585
A102: ซีเมนต์บอร์ด 120*240*20 มม.(24) | B102: ='สูตร 4 step SB'!E919 -> 708 | C102: ='สูตร 4 step SB'!E920 -> 713 | D102: ='สูตร 4 step SB'!E921 -> 718 | E102: ='สูตร 4 step SB'!E922 -> 723 | F102: ='สูตร 4 step SB'!F919 -> 722 | G102: ='สูตร 4 step SB'!F920 -> 727 | H102: ='สูตร 4 step SB'!F921 -> 732 | I102: ='สูตร 4 step SB'!F922 -> 737 | J102: ='สูตร 4 step SB'!G919 -> 697 | K102: ='สูตร 4 step SB'!G920 -> 702 | L102: ='สูตร 4 step SB'!G921 -> 707 | M102: ='สูตร 4 step SB'!G922 -> 712 | N102: ='สูตร 4 step SB'!H919 -> 688 | O102: ='สูตร 4 step SB'!H920 -> 693 | P102: ='สูตร 4 step SB'!H921 -> 698 | Q102: ='สูตร 4 step SB'!H922 -> 703
A103: ซีเมนต์บอร์ด 120*240*24 มม.(20) | B103: ='สูตร 4 step SB'!E947 -> 832 | C103: ='สูตร 4 step SB'!E948 -> 837 | D103: ='สูตร 4 step SB'!E949 -> 842 | E103: ='สูตร 4 step SB'!E950 -> 847 | F103: ='สูตร 4 step SB'!F947 -> 848 | G103: ='สูตร 4 step SB'!F948 -> 853 | H103: ='สูตร 4 step SB'!F949 -> 858 | I103: ='สูตร 4 step SB'!F950 -> 863 | J103: ='สูตร 4 step SB'!G947 -> 818 | K103: ='สูตร 4 step SB'!G948 -> 823 | L103: ='สูตร 4 step SB'!G949 -> 828 | M103: ='สูตร 4 step SB'!G950 -> 833 | N103: ='สูตร 4 step SB'!H947 -> 807 | O103: ='สูตร 4 step SB'!H948 -> 812 | P103: ='สูตร 4 step SB'!H949 -> 817 | Q103: ='สูตร 4 step SB'!H950 -> 822
A115: New Product
A116: N Price | D116: CM | H116: CR | L116: PL | P116: NS
A117: Y1 : Rockwool | C117: WIP | D117: WIPR | E117: WIPRSO | G117: WIP | H117: WIPR | I117: WIPRSO | K117: WIP | L117: WIPR | M117: WIPRSO | O117: WIP | P117: WIPR | Q117: WIPRSO
B118: W1 | C118: W2 | D118: R1 | E118: R2 | F118: W1 | G118: W2 | H118: R1 | I118: R2 | J118: W1 | K118: W2 | L118: R1 | M118: R2 | N118: W1 | O118: W2 | P118: R1 | Q118: R2
A119: Rock Chill หนา 3 นิ้ว | B119: =Rockwool!E14 -> 338.3625 | C119: =Rockwool!E15 -> 354.475 | D119: =Rockwool!E16 -> 370.5875 | E119: =Rockwool!E17 -> 386.7 | J119: =Rockwool!G14 -> 335.3595 | K119: =Rockwool!G15 -> 351.329 | L119: =Rockwool!G16 -> 367.2985 | M119: =Rockwool!G17 -> 383.268 | N119: =Rockwool!H14 -> 324.6705 | O119: =Rockwool!H15 -> 340.131 | P119: =Rockwool!H16 -> 349.4073 | Q119: =Rockwool!H17 -> 355.5915
A120: Safe 'n' Silent Pro 330 หนา 50 มม. 60*120 (6 แผ่น/ แพ็ค) | B120: =Rockwool!E42 -> 81.16794 | C120: =Rockwool!E43 -> 82.713996 | D120: =Rockwool!E44 -> 85.03308 | E120: =Rockwool!E45 -> 88.89822 | J120: =Rockwool!G42 -> 88.69644 | K120: =Rockwool!G43 -> 90.385896 | L120: =Rockwool!G44 -> 92.92008 | M120: =Rockwool!G45 -> 97.14372 | N120: =Rockwool!H42 -> 83.72994 | O120: =Rockwool!H43 -> 85.324796 | P120: =Rockwool!H44 -> 87.71708 | Q120: =Rockwool!H45 -> 91.70422
...

Sheet NE DCM
A1: Internal Memo | H1: No.
A2: To : | C2: ผู้จัดการภาค / ผู้จัดการเขต | H2: Date :
A3: RE :
A4: หมายเหตุ : | D4: 1 | E4: ราคาขายข้างต้นรวม VAT
D5: 2 | E5: หากราคาข้างต้นสูง ไม่สามารถขายได้ โปรดสอบถาม ผจก.PM
D6: 3 | E6: ราคาขายข้างต้นให้ถือเป็นราคาขายต่ำสุด สามารถขายที่ราคาสูงกว่านี้ได้ ขึ้นอยู่กับแต่ละพื้นที่
D7: 4 | E7: ปริมาณการขายส่งแผ่น 120x240 ขั้นต่ำ 400 แผ่น : เดือน
D8: 5 | E8: ราคา RE (EX VAT) และไม่รวมค่าขนส่ง ยังไม่หักรีเบทประจำเดือน
A10: NE | D10: KK | H10: SK | L10: UD | P10: UB | T10: NR
A11: Y 1: Gypsum | C11: WIP | D11: WIPR | E11: WIPRSO | G11: WIP | H11: WIPR | I11: WIPRSO | K11: WIP | L11: WIPR | M11: WIPRSO | O11: WIP | P11: WIPR | Q11: WIPRSO | S11: WIP | T11: WIPR | U11: WIPRSO
B12: W1 | C12: W2 | D12: R1 | E12: R2 | F12: W1 | G12: W2 | H12: R1 | I12: R2 | J12: W1 | K12: W2 | L12: R1 | M12: R2 | N12: W1 | O12: W2 | P12: R1 | Q12: R2 | R12: W1 | S12: W2 | T12: R1 | U12: R2
A13: ยิปซัม ธรรมดา 9 มม. ขอบเรียบ/ลาด | B13: ='Formular 4 step Y1'!I14 -> 134 | C13: ='Formular 4 step Y1'!I15 -> 135 | D13: ='Formular 4 step Y1'!I16 -> 136 | E13: ='Formular 4 step Y1'!I17 -> 137 | F13: ='Formular 4 step Y1'!J14 -> 138 | G13: ='Formular 4 step Y1'!J15 -> 139 | H13: ='Formular 4 step Y1'!J16 -> 140 | I13: ='Formular 4 step Y1'!J17 -> 141 | J13: ='Formular 4 step Y1'!K14 -> 136 | K13: ='Formular 4 step Y1'!K15 -> 137 | L13: ='Formular 4 step Y1'!K16 -> 138 | M13: ='Formular 4 step Y1'!K17 -> 139 | N13: ='Formular 4 step Y1'!L14 -> 137 | O13: ='Formular 4 step Y1'!L15 -> 138 | P13: ='Formular 4 step Y1'!L16 -> 139 | Q13: ='Formular 4 step Y1'!L17 -> 140 | R13: ='Formular 4 step Y1'!M14 -> 132 | S13: ='Formular 4 step Y1'!M15 -> 133 | T13: ='Formular 4 step Y1'!M16 -> 134 | U13: ='Formular 4 step Y1'!M17 -> 135
A14: ยิปซัม ธรรมดา 9 มม. ขอบลาด 4 ด้าน | B14: ='Formular 4 step Y1'!I39 -> 133 | C14: ='Formular 4 step Y1'!I40 -> 134 | D14: ='Formular 4 step Y1'!I41 -> 135 | E14: ='Formular 4 step Y1'!I42 -> 136 | F14: ='Formular 4 step Y1'!J39 -> 137 | G14: ='Formular 4 step Y1'!J40 -> 138 | H14: ='Formular 4 step Y1'!J41 -> 139 | I14: ='Formular 4 step Y1'!J42 -> 140 | J14: ='Formular 4 step Y1'!K39 -> 135 | K14: ='Formular 4 step Y1'!K40 -> 136 | L14: ='Formular 4 step Y1'!K41 -> 137 | M14: ='Formular 4 step Y1'!K42 -> 138 | N14: ='Formular 4 step Y1'!L39 -> 137 | O14: ='Formular 4 step Y1'!L40 -> 138 | P14: ='Formular 4 step Y1'!L41 -> 139 | Q14: ='Formular 4 step Y1'!L42 -> 140 | R14: ='Formular 4 step Y1'!M39 -> 131 | S14: ='Formular 4 step Y1'!M40 -> 132 | T14: ='Formular 4 step Y1'!M41 -> 133 | U14: ='Formular 4 step Y1'!M42 -> 134
A15: ยิปซัม ทนชื้น/ฟลอยด์ 9 มม. ขอบเรียบ/ลาด | B15: ='Formular 4 step Y1'!I64 -> 197 | C15: ='Formular 4 step Y1'!I65 -> 198 | D15: ='Formular 4 step Y1'!I66 -> 199 | E15: ='Formular 4 step Y1'!I67 -> 200 | F15: ='Formular 4 step Y1'!J64 -> 201 | G15: ='Formular 4 step Y1'!J65 -> 202 | H15: ='Formular 4 step Y1'!J66 -> 203 | I15: ='Formular 4 step Y1'!J67 -> 204 | J15: ='Formular 4 step Y1'!K64 -> 199 | K15: ='Formular 4 step Y1'!K65 -> 200 | L15: ='Formular 4 step Y1'!K66 -> 201 | M15: ='Formular 4 step Y1'!K67 -> 202 | N15: ='Formular 4 step Y1'!L64 -> 200 | O15: ='Formular 4 step Y1'!L65 -> 201 | P15: ='Formular 4 step Y1'!L66 -> 202 | Q15: ='Formular 4 step Y1'!L67 -> 203 | R15: ='Formular 4 step Y1'!M64 -> 195 | S15: ='Formular 4 step Y1'!M65 -> 196 | T15: ='Formular 4 step Y1'!M66 -> 197 | U15: ='Formular 4 step Y1'!M67 -> 198
A16: ยิปซัม ทนชื้น/ฟลอยด์ 9 มม. ขอบลาด 4 ด้าน | B16: ='Formular 4 step Y1'!I89 -> 195 | C16: ='Formular 4 step Y1'!I90 -> 196 | D16: ='Formular 4 step Y1'!I91 -> 197 | E16: ='Formular 4 step Y1'!I92 -> 198 | F16: ='Formular 4 step Y1'!J89 -> 199 | G16: ='Formular 4 step Y1'!J90 -> 200 | H16: ='Formular 4 step Y1'!J91 -> 201 | I16: ='Formular 4 step Y1'!J92 -> 202 | J16: ='Formular 4 step Y1'!K89 -> 197 | K16: ='Formular 4 step Y1'!K90 -> 198 | L16: ='Formular 4 step Y1'!K91 -> 199 | M16: ='Formular 4 step Y1'!K92 -> 200 | N16: ='Formular 4 step Y1'!L89 -> 199 | O16: ='Formular 4 step Y1'!L90 -> 200 | P16: ='Formular 4 step Y1'!L91 -> 201 | Q16: ='Formular 4 step Y1'!L92 -> 202 | R16: ='Formular 4 step Y1'!M89 -> 193 | S16: ='Formular 4 step Y1'!M90 -> 194 | T16: ='Formular 4 step Y1'!M91 -> 195 | U16: ='Formular 4 step Y1'!M92 -> 196
A17: ยิปซัม ธรรมดา 12 มม. ขอบเรียบ/ลาด | B17: ='Formular 4 step Y1'!I114 -> 160 | C17: ='Formular 4 step Y1'!I115 -> 161 | D17: ='Formular 4 step Y1'!I116 -> 162 | E17: ='Formular 4 step Y1'!I117 -> 163 | F17: ='Formular 4 step Y1'!J114 -> 166 | G17: ='Formular 4 step Y1'!J115 -> 167 | H17: ='Formular 4 step Y1'!J116 -> 168 | I17: ='Formular 4 step Y1'!J117 -> 169 | J17: ='Formular 4 step Y1'!K114 -> 163 | K17: ='Formular 4 step Y1'!K115 -> 164 | L17: ='Formular 4 step Y1'!K116 -> 165 | M17: ='Formular 4 step Y1'!K117 -> 166 | N17: ='Formular 4 step Y1'!L114 -> 165 | O17: ='Formular 4 step Y1'!L115 -> 166 | P17: ='Formular 4 step Y1'!L116 -> 167 | Q17: ='Formular 4 step Y1'!L117 -> 168 | R17: ='Formular 4 step Y1'!M114 -> 158 | S17: ='Formular 4 step Y1'!M115 -> 159 | T17: ='Formular 4 step Y1'!M116 -> 160 | U17: ='Formular 4 step Y1'!M117 -> 161
A18: ยิปซัม ทนชื้น/ฟลอยด์ 12 มม. ขอบเรียบ/ลาด | B18: ='Formular 4 step Y1'!I139 -> 220 | C18: ='Formular 4 step Y1'!I140 -> 221 | D18: ='Formular 4 step Y1'!I141 -> 222 | E18: ='Formular 4 step Y1'!I141 -> 222 | F18: ='Formular 4 step Y1'!J139 -> 226 | G18: ='Formular 4 step Y1'!J140 -> 227 | H18: ='Formular 4 step Y1'!J141 -> 228 | I18: ='Formular 4 step Y1'!J142 -> 229 | J18: ='Formular 4 step Y1'!K139 -> 223 | K18: ='Formular 4 step Y1'!K140 -> 224 | L18: ='Formular 4 step Y1'!K141 -> 225 | M18: ='Formular 4 step Y1'!K142 -> 226 | N18: ='Formular 4 step Y1'!L139 -> 225 | O18: ='Formular 4 step Y1'!L140 -> 226 | P18: ='Formular 4 step Y1'!L141 -> 227 | Q18: ='Formular 4 step Y1'!L142 -> 228 | R18: ='Formular 4 step Y1'!M139 -> 218 | S18: ='Formular 4 step Y1'!M140 -> 219 | T18: ='Formular 4 step Y1'!M141 -> 220 | U18: ='Formular 4 step Y1'!M142 -> 221
A19: ยิปซัม ธรรมดา 15 มม. ขอบลาด | B19: ='Formular 4 step Y1'!I838 -> 234 | C19: ='Formular 4 step Y1'!I839 -> 235 | D19: ='Formular 4 step Y1'!I840 -> 236 | E19: ='Formular 4 step Y1'!I841 -> 237 | F19: ='Formular 4 step Y1'!J838 -> 244 | G19: ='Formular 4 step Y1'!J839 -> 245 | H19: ='Formular 4 step Y1'!J840 -> 246 | I19: ='Formular 4 step Y1'!J841 -> 247 | J19: ='Formular 4 step Y1'!K838 -> 238 | K19: ='Formular 4 step Y1'!K839 -> 239 | L19: ='Formular 4 step Y1'!K840 -> 240 | M19: ='Formular 4 step Y1'!K841 -> 241 | N19: ='Formular 4 step Y1'!L838 -> 241 | O19: ='Formular 4 step Y1'!L839 -> 242 | P19: ='Formular 4 step Y1'!L840 -> 243 | Q19: ='Formular 4 step Y1'!L841 -> 244 | R19: ='Formular 4 step Y1'!M838 -> 228 | S19: ='Formular 4 step Y1'!M839 -> 229 | T19: ='Formular 4 step Y1'!M840 -> 230 | U19: ='Formular 4 step Y1'!M841 -> 231
A20: ทนไฟ 12 มม. | B20: ='Formular 4 step Y1'!I164 -> 264 | C20: ='Formular 4 step Y1'!I165 -> 267 | D20: ='Formular 4 step Y1'!I166 -> 272 | E20: ='Formular 4 step Y1'!I167 -> 277 | F20: ='Formular 4 step Y1'!J164 -> 269 | G20: ='Formular 4 step Y1'!J165 -> 272 | H20: ='Formular 4 step Y1'!J166 -> 277 | I20: ='Formular 4 step Y1'!J167 -> 282 | J20: ='Formular 4 step Y1'!K164 -> 266 | K20: ='Formular 4 step Y1'!K165 -> 269 | L20: ='Formular 4 step Y1'!K166 -> 274 | M20: ='Formular 4 step Y1'!K167 -> 279 | N20: ='Formular 4 step Y1'!L164 -> 269 | O20: ='Formular 4 step Y1'!L165 -> 272 | P20: ='Formular 4 step Y1'!L166 -> 277 | Q20: ='Formular 4 step Y1'!L167 -> 282 | R20: ='Formular 4 step Y1'!M164 -> 261 | S20: ='Formular 4 step Y1'!M165 -> 264 | T20: ='Formular 4 step Y1'!M166 -> 269 | U20: ='Formular 4 step Y1'!M167 -> 274
A21: ทนไฟ 15 มม. | B21: ='Formular 4 step Y1'!I189 -> 301 | C21: ='Formular 4 step Y1'!I190 -> 304 | D21: ='Formular 4 step Y1'!I191 -> 309 | E21: ='Formular 4 step Y1'!I192 -> 314 | F21: ='Formular 4 step Y1'!J189 -> 311 | G21: ='Formular 4 step Y1'!J190 -> 314 | H21: ='Formular 4 step Y1'!J191 -> 319 | I21: ='Formular 4 step Y1'!J192 -> 324 | J21: ='Formular 4 step Y1'!K189 -> 306 | K21: ='Formular 4 step Y1'!K190 -> 309 | L21: ='Formular 4 step Y1'!K191 -> 314 | M21: ='Formular 4 step Y1'!K192 -> 319 | N21: ='Formular 4 step Y1'!L189 -> 310 | O21: ='Formular 4 step Y1'!L190 -> 313 | P21: ='Formular 4 step Y1'!L191 -> 318 | Q21: ='Formular 4 step Y1'!L192 -> 323 | R21: ='Formular 4 step Y1'!M189 -> 296 | S21: ='Formular 4 step Y1'!M190 -> 299 | T21: ='Formular 4 step Y1'!M191 -> 304 | U21: ='Formular 4 step Y1'!M192 -> 309
A22: ยิปซัมเฟล็กบอร์ด(ดัดโค้ง) 6 มม. 120*240 มม. | B22: ='Formular 4 step Y1'!I863 -> 180.32104 | C22: ='Formular 4 step Y1'!I864 -> 181.99068 | D22: ='Formular 4 step Y1'!I865 -> 186.9996 | E22: ='Formular 4 step Y1'!I866 -> 192.00852 | F22: ='Formular 4 step Y1'!J863 -> 184.64104 | G22: ='Formular 4 step Y1'!J864 -> 186.35068 | H22: ='Formular 4 step Y1'!J865 -> 191.4796 | I22: ='Formular 4 step Y1'!J866 -> 196.60852 | J22: ='Formular 4 step Y1'!K863 -> 182.48104 | K22: ='Formular 4 step Y1'!K864 -> 184.17068 | L22: ='Formular 4 step Y1'!K865 -> 189.2396 | M22: ='Formular 4 step Y1'!K866 -> 194.30852 | N22: ='Formular 4 step Y1'!L863 -> 184.10104 | O22: ='Formular 4 step Y1'!L864 -> 185.80568 | P22: ='Formular 4 step Y1'!L865 -> 190.9196 | Q22: ='Formular 4 step Y1'!L866 -> 196.03352 | R22: ='Formular 4 step Y1'!M863 -> 178.16104 | S22: ='Formular 4 step Y1'!M864 -> 179.81068 | T22: ='Formular 4 step Y1'!M865 -> 184.7596 | U22: ='Formular 4 step Y1'!M866 -> 189.70852
A23: อี่ซี่บอร์ท / คนอฟ | B23: ='Formular 4 step Y1'!I738 -> 105 | C23: ='Formular 4 step Y1'!I739 -> 106 | D23: ='Formular 4 step Y1'!I740 -> 107 | E23: ='Formular 4 step Y1'!I741 -> 108 | F23: ='Formular 4 step Y1'!J738 -> 105 | G23: ='Formular 4 step Y1'!J739 -> 106 | H23: ='Formular 4 step Y1'!J740 -> 107 | I23: ='Formular 4 step Y1'!J741 -> 108 | J23: ='Formular 4 step Y1'!K738 -> 105 | K23: ='Formular 4 step Y1'!K739 -> 106 | L23: ='Formular 4 step Y1'!K740 -> 107 | M23: ='Formular 4 step Y1'!K741 -> 108 | N23: ='Formular 4 step Y1'!L738 -> 105 | O23: ='Formular 4 step Y1'!L739 -> 106 | P23: ='Formular 4 step Y1'!L740 -> 107 | Q23: ='Formular 4 step Y1'!L741 -> 108 | R23: ='Formular 4 step Y1'!M738 -> 105 | S23: ='Formular 4 step Y1'!M739 -> 106 | T23: ='Formular 4 step Y1'!M740 -> 107 | U23: ='Formular 4 step Y1'!M741 -> 108
A24: อี่ซี่บอร์ท/คนอฟ ทนชื้น / ฟอล์ย | B24: ='Formular 4 step Y1'!I763 -> 162 | C24: ='Formular 4 step Y1'!I764 -> 163 | D24: ='Formular 4 step Y1'!I765 -> 164 | E24: ='Formular 4 step Y1'!I766 -> 165 | F24: ='Formular 4 step Y1'!J763 -> 162 | G24: ='Formular 4 step Y1'!J764 -> 163 | H24: ='Formular 4 step Y1'!J765 -> 164 | I24: ='Formular 4 step Y1'!J766 -> 165 | J24: ='Formular 4 step Y1'!K763 -> 162 | K24: ='Formular 4 step Y1'!K764 -> 163 | L24: ='Formular 4 step Y1'!K765 -> 164 | M24: ='Formular 4 step Y1'!K766 -> 165 | N24: ='Formular 4 step Y1'!L763 -> 162 | O24: ='Formular 4 step Y1'!L764 -> 163 | P24: ='Formular 4 step Y1'!L765 -> 164 | Q24: ='Formular 4 step Y1'!L766 -> 165 | R24: ='Formular 4 step Y1'!M763 -> 162 | S24: ='Formular 4 step Y1'!M764 -> 163 | T24: ='Formular 4 step Y1'!M765 -> 164 | U24: ='Formular 4 step Y1'!M766 -> 165
A25: เวเทอร์บล็อค W0 | B25: ='Formular 4 step Y1'!I788 -> 275 | C25: ='Formular 4 step Y1'!I789 -> 276 | D25: ='Formular 4 step Y1'!I790 -> 277 | E25: ='Formular 4 step Y1'!I791 -> 278 | F25: ='Formular 4 step Y1'!J788 -> 278 | G25: ='Formular 4 step Y1'!J789 -> 279 | H25: ='Formular 4 step Y1'!J790 -> 280 | I25: ='Formular 4 step Y1'!J791 -> 281 | J25: ='Formular 4 step Y1'!K788 -> 276 | K25: ='Formular 4 step Y1'!K789 -> 277 | L25: ='Formular 4 step Y1'!K790 -> 278 | M25: ='Formular 4 step Y1'!K791 -> 279 | N25: ='Formular 4 step Y1'!L788 -> 277 | O25: ='Formular 4 step Y1'!L789 -> 278 | P25: ='Formular 4 step Y1'!L790 -> 279 | Q25: ='Formular 4 step Y1'!L791 -> 280 | R25: ='Formular 4 step Y1'!M788 -> 272 | S25: ='Formular 4 step Y1'!M789 -> 273 | T25: ='Formular 4 step Y1'!M790 -> 274 | U25: ='Formular 4 step Y1'!M791 -> 275
A26: เวเทอร์บล็อค W1 | B26: ='Formular 4 step Y1'!I813 -> 431 | C26: ='Formular 4 step Y1'!I814 -> 432 | D26: ='Formular 4 step Y1'!I815 -> 433 | E26: ='Formular 4 step Y1'!I816 -> 434 | F26: ='Formular 4 step Y1'!J813 -> 435 | G26: ='Formular 4 step Y1'!J814 -> 436 | H26: ='Formular 4 step Y1'!J815 -> 437 | I26: ='Formular 4 step Y1'!J816 -> 438 | J26: ='Formular 4 step Y1'!K813 -> 433 | K26: ='Formular 4 step Y1'!K814 -> 434 | L26: ='Formular 4 step Y1'!K815 -> 435 | M26: ='Formular 4 step Y1'!K816 -> 436 | N26: ='Formular 4 step Y1'!L813 -> 434 | O26: ='Formular 4 step Y1'!L814 -> 435 | P26: ='Formular 4 step Y1'!L815 -> 436 | Q26: ='Formular 4 step Y1'!L816 -> 437 | R26: ='Formular 4 step Y1'!M813 -> 429 | S26: ='Formular 4 step Y1'!M814 -> 430 | T26: ='Formular 4 step Y1'!M815 -> 431 | U26: ='Formular 4 step Y1'!M816 -> 432
A27: ยิปซัมลดเสียงสะท้อน เอคโค่บล็อค (R1,R2,R8,S8) | B27: ='Formular 4 step Y1'!I214 -> 913 | C27: ='Formular 4 step Y1'!I215 -> 916 | D27: ='Formular 4 step Y1'!I216 -> 926 | E27: ='Formular 4 step Y1'!I217 -> 936 | F27: ='Formular 4 step Y1'!J214 -> 918 | G27: ='Formular 4 step Y1'!J215 -> 921 | H27: ='Formular 4 step Y1'!J216 -> 931 | I27: ='Formular 4 step Y1'!J217 -> 941 | J27: ='Formular 4 step Y1'!K214 -> 915 | K27: ='Formular 4 step Y1'!K215 -> 918 | L27: ='Formular 4 step Y1'!K216 -> 928 | M27: ='Formular 4 step Y1'!K217 -> 938 | N27: ='Formular 4 step Y1'!L214 -> 918 | O27: ='Formular 4 step Y1'!L215 -> 921 | P27: ='Formular 4 step Y1'!L216 -> 931 | Q27: ='Formular 4 step Y1'!L217 -> 941 | R27: ='Formular 4 step Y1'!M214 -> 910 | S27: ='Formular 4 step Y1'!M215 -> 913 | T27: ='Formular 4 step Y1'!M216 -> 923 | U27: ='Formular 4 step Y1'!M217 -> 933
A28: Paper touch ลวดลาย 60*60*8 mm. | B28: ='Formular 4 step Y1'!I239 -> 21.751662 | C28: ='Formular 4 step Y1'!I240 -> 23 | D28: ='Formular 4 step Y1'!I241 -> 24 | E28: ='Formular 4 step Y1'!I242 -> 25 | F28: ='Formular 4 step Y1'!J239 -> 21.751662 | G28: ='Formular 4 step Y1'!J240 -> 23 | H28: ='Formular 4 step Y1'!J241 -> 24 | I28: ='Formular 4 step Y1'!J242 -> 25 | J28: ='Formular 4 step Y1'!K239 -> 21.751662 | K28: ='Formular 4 step Y1'!K240 -> 23 | L28: ='Formular 4 step Y1'!K241 -> 24 | M28: ='Formular 4 step Y1'!K242 -> 25 | N28: ='Formular 4 step Y1'!L239 -> 21.751662 | O28: ='Formular 4 step Y1'!L240 -> 23 | P28: ='Formular 4 step Y1'!L241 -> 24 | Q28: ='Formular 4 step Y1'!L242 -> 25 | R28: ='Formular 4 step Y1'!M239 -> 21.751662 | S28: ='Formular 4 step Y1'!M240 -> 23 | T28: ='Formular 4 step Y1'!M241 -> 24 | U28: ='Formular 4 step Y1'!M242 -> 25
A29: Paper touch หยาดเพชร 60*60*8 mm. | B29: ='Formular 4 step Y1'!I264 -> 19.916612 | C29: ='Formular 4 step Y1'!I265 -> 21 | D29: ='Formular 4 step Y1'!I266 -> 22 | E29: ='Formular 4 step Y1'!J267 -> 23 | F29: ='Formular 4 step Y1'!J264 -> 19.916612 | G29: ='Formular 4 step Y1'!J265 -> 21 | H29: ='Formular 4 step Y1'!J266 -> 22 | I29: ='Formular 4 step Y1'!K267 -> 23 | J29: ='Formular 4 step Y1'!K264 -> 19.916612 | K29: ='Formular 4 step Y1'!K265 -> 21 | L29: ='Formular 4 step Y1'!K266 -> 22 | M29: ='Formular 4 step Y1'!L267 -> 23 | N29: ='Formular 4 step Y1'!L264 -> 19.916612 | O29: ='Formular 4 step Y1'!L265 -> 21 | P29: ='Formular 4 step Y1'!L266 -> 22 | Q29: ='Formular 4 step Y1'!M267 -> 23 | R29: ='Formular 4 step Y1'!M264 -> 19.916612 | S29: ='Formular 4 step Y1'!M265 -> 21 | T29: ='Formular 4 step Y1'!M266 -> 22 | U29: ='Formular 4 step Y1'!M267 -> 23
A30: Paper touch หยาดเพชร 60*60*8 mm. กันร้อน | B30: ='Formular 4 step Y1'!I264 -> 19.916612 | C30: ='Formular 4 step Y1'!I265 -> 21 | D30: ='Formular 4 step Y1'!J266 -> 22 | E30: ='Formular 4 step Y1'!K267 -> 23 | F30: ='Formular 4 step Y1'!I264 -> 19.916612 | G30: ='Formular 4 step Y1'!J265 -> 21 | H30: ='Formular 4 step Y1'!K266 -> 22 | I30: ='Formular 4 step Y1'!L267 -> 23 | J30: ='Formular 4 step Y1'!K264 -> 19.916612 | K30: ='Formular 4 step Y1'!K265 -> 21 | L30: ='Formular 4 step Y1'!K266 -> 22 | M30: ='Formular 4 step Y1'!K267 -> 23 | N30: ='Formular 4 step Y1'!L264 -> 19.916612 | O30: ='Formular 4 step Y1'!L265 -> 21 | P30: ='Formular 4 step Y1'!L266 -> 22 | Q30: ='Formular 4 step Y1'!L267 -> 23 | R30: ='Formular 4 step Y1'!M289 -> 24.729686 | S30: ='Formular 4 step Y1'!M290 -> 26 | T30: ='Formular 4 step Y1'!M291 -> 27 | U30: ='Formular 4 step Y1'!M292 -> 28
A31: Color touch สีมุก/สีเพชร 60x60*9 mm. | B31: ='Formular 4 step Y1'!I289 -> 24.729686 | C31: ='Formular 4 step Y1'!I290 -> 26 | D31: ='Formular 4 step Y1'!I291 -> 27 | E31: ='Formular 4 step Y1'!I292 -> 28 | F31: ='Formular 4 step Y1'!J289 -> 24.729686 | G31: ='Formular 4 step Y1'!J290 -> 26 | H31: ='Formular 4 step Y1'!J291 -> 27 | I31: ='Formular 4 step Y1'!J292 -> 28 | J31: ='Formular 4 step Y1'!K289 -> 24.729686 | K31: ='Formular 4 step Y1'!K290 -> 26 | L31: ='Formular 4 step Y1'!K291 -> 27 | M31: ='Formular 4 step Y1'!K292 -> 28 | N31: ='Formular 4 step Y1'!L289 -> 24.729686 | O31: ='Formular 4 step Y1'!L290 -> 26 | P31: ='Formular 4 step Y1'!L291 -> 27 | Q31: ='Formular 4 step Y1'!L292 -> 28 | R31: ='Formular 4 step Y1'!M313 -> 23 | S31: ='Formular 4 step Y1'!M314 -> 24 | T31: ='Formular 4 step Y1'!M315 -> 25 | U31: ='Formular 4 step Y1'!M316 -> 26
A32: Color touch สีมุก/สีเพชร 60x120*9 mm. | B32: ='Formular 4 step Y1'!I338 -> 46 | C32: ='Formular 4 step Y1'!I339 -> 47 | D32: ='Formular 4 step Y1'!I340 -> 48 | E32: ='Formular 4 step Y1'!I341 -> 50 | F32: ='Formular 4 step Y1'!J338 -> 46 | G32: ='Formular 4 step Y1'!J339 -> 47 | H32: ='Formular 4 step Y1'!J340 -> 48 | I32: ='Formular 4 step Y1'!J341 -> 50 | J32: ='Formular 4 step Y1'!K338 -> 46 | K32: ='Formular 4 step Y1'!K339 -> 47 | L32: ='Formular 4 step Y1'!K340 -> 48 | M32: ='Formular 4 step Y1'!K341 -> 50 | N32: ='Formular 4 step Y1'!L338 -> 46 | O32: ='Formular 4 step Y1'!L339 -> 47 | P32: ='Formular 4 step Y1'!L340 -> 48 | Q32: ='Formular 4 step Y1'!L341 -> 50 | R32: ='Formular 4 step Y1'!M338 -> 46 | S32: ='Formular 4 step Y1'!M339 -> 47 | T32: ='Formular 4 step Y1'!M340 -> 48 | U32: ='Formular 4 step Y1'!M341 -> 50
A33: Color touch สีมุก/สีเพชร 60x120*12 mm. | B33: ='Formular 4 step Y1'!I888 -> 46.911609 | C33: ='Formular 4 step Y1'!I889 -> 47.5 | D33: ='Formular 4 step Y1'!I890 -> 48.202754 | E33: ='Formular 4 step Y1'!I891 -> 49.493899 | F33: ='Formular 4 step Y1'!J888 -> 46.911609 | G33: ='Formular 4 step Y1'!J889 -> 47.5 | H33: ='Formular 4 step Y1'!J890 -> 48.202754 | I33: ='Formular 4 step Y1'!J891 -> 49.493899 | J33: ='Formular 4 step Y1'!K888 -> 46.911609 | K33: ='Formular 4 step Y1'!K889 -> 47.5 | L33: ='Formular 4 step Y1'!K890 -> 48.202754 | M33: ='Formular 4 step Y1'!K891 -> 49.493899 | N33: ='Formular 4 step Y1'!L888 -> 46.911609 | O33: ='Formular 4 step Y1'!L889 -> 47.5 | P33: ='Formular 4 step Y1'!L890 -> 48.202754 | Q33: ='Formular 4 step Y1'!L891 -> 49.493899 | R33: ='Formular 4 step Y1'!M888 -> 46.911609 | S33: ='Formular 4 step Y1'!M889 -> 47.5 | T33: ='Formular 4 step Y1'!M890 -> 48.202754 | U33: ='Formular 4 step Y1'!M891 -> 49.493899
A34: Color touch สีมุก/สีเพชร 60x60*9 mm. ทนชื้น | B34: ='Formular 4 step Y1'!I363 -> 28 | C34: ='Formular 4 step Y1'!I364 -> 29 | D34: ='Formular 4 step Y1'!I365 -> 31 | E34: ='Formular 4 step Y1'!I366 -> 32 | F34: ='Formular 4 step Y1'!J363 -> 28 | G34: ='Formular 4 step Y1'!J364 -> 29 | H34: ='Formular 4 step Y1'!J365 -> 31 | I34: ='Formular 4 step Y1'!J366 -> 32 | J34: ='Formular 4 step Y1'!K363 -> 28 | K34: ='Formular 4 step Y1'!K364 -> 29 | L34: ='Formular 4 step Y1'!K365 -> 31 | M34: ='Formular 4 step Y1'!K366 -> 32 | N34: ='Formular 4 step Y1'!L363 -> 28 | O34: ='Formular 4 step Y1'!L364 -> 29 | P34: ='Formular 4 step Y1'!L365 -> 31 | Q34: ='Formular 4 step Y1'!L366 -> 32 | R34: ='Formular 4 step Y1'!M363 -> 28 | S34: ='Formular 4 step Y1'!M364 -> 29 | T34: ='Formular 4 step Y1'!M365 -> 31 | U34: ='Formular 4 step Y1'!M366 -> 32
A35: Color touch สีมุก/สีเพชร 60x120*9 mm. ทนชื้น | B35: ='Formular 4 step Y1'!I388 -> 57 | C35: ='Formular 4 step Y1'!I389 -> 58 | D35: ='Formular 4 step Y1'!I390 -> 59 | E35: ='Formular 4 step Y1'!I391 -> 61 | F35: ='Formular 4 step Y1'!J388 -> 57 | G35: ='Formular 4 step Y1'!J389 -> 58 | H35: ='Formular 4 step Y1'!J390 -> 59 | I35: ='Formular 4 step Y1'!J391 -> 61 | J35: ='Formular 4 step Y1'!K388 -> 57 | K35: ='Formular 4 step Y1'!K389 -> 58 | L35: ='Formular 4 step Y1'!K390 -> 59 | M35: ='Formular 4 step Y1'!K391 -> 61 | N35: ='Formular 4 step Y1'!L388 -> 57 | O35: ='Formular 4 step Y1'!L389 -> 58 | P35: ='Formular 4 step Y1'!L390 -> 59 | Q35: ='Formular 4 step Y1'!L391 -> 61 | R35: ='Formular 4 step Y1'!M388 -> 57 | S35: ='Formular 4 step Y1'!M389 -> 58 | T35: ='Formular 4 step Y1'!M390 -> 59 | U35: ='Formular 4 step Y1'!M391 -> 61
A36: Color touch สีมุก/สีเพชร 60x120*12 mm. ทนชื้น | B36: ='Formular 4 step Y1'!I913 -> 63.551024 | C36: ='Formular 4 step Y1'!I914 -> 64.5 | D36: ='Formular 4 step Y1'!I915 -> 65.300135 | E36: ='Formular 4 step Y1'!I916 -> 67.049246 | F36: ='Formular 4 step Y1'!J913 -> 63.551024 | G36: ='Formular 4 step Y1'!J914 -> 64.5 | H36: ='Formular 4 step Y1'!J915 -> 65.300135 | I36: ='Formular 4 step Y1'!J916 -> 67.049246 | J36: ='Formular 4 step Y1'!K913 -> 63.551024 | K36: ='Formular 4 step Y1'!K914 -> 64.5 | L36: ='Formular 4 step Y1'!K915 -> 65.300135 | M36: ='Formular 4 step Y1'!K916 -> 67.049246 | N36: ='Formular 4 step Y1'!L913 -> 63.551024 | O36: ='Formular 4 step Y1'!L914 -> 64.5 | P36: ='Formular 4 step Y1'!L915 -> 65.300135 | Q36: ='Formular 4 step Y1'!L916 -> 67.049246 | R36: ='Formular 4 step Y1'!M913 -> 63.551024 | S36: ='Formular 4 step Y1'!M914 -> 64.5 | T36: ='Formular 4 step Y1'!M915 -> 65.300135 | U36: ='Formular 4 step Y1'!M916 -> 67.049246
A37: เซิฟบอร์ด ขนาด 30 ซม. | B37: ='Formular 4 step Y1'!I413 -> 173 | C37: ='Formular 4 step Y1'!I414 -> 174 | D37: ='Formular 4 step Y1'!I415 -> 179 | E37: ='Formular 4 step Y1'!I416 -> 184 | F37: ='Formular 4 step Y1'!J413 -> 173 | G37: ='Formular 4 step Y1'!J414 -> 174 | H37: ='Formular 4 step Y1'!J415 -> 179 | I37: ='Formular 4 step Y1'!J416 -> 184 | J37: ='Formular 4 step Y1'!K413 -> 173 | K37: ='Formular 4 step Y1'!K414 -> 174 | L37: ='Formular 4 step Y1'!K415 -> 179 | M37: ='Formular 4 step Y1'!K416 -> 184 | N37: ='Formular 4 step Y1'!L413 -> 173 | O37: ='Formular 4 step Y1'!L414 -> 174 | P37: ='Formular 4 step Y1'!L415 -> 179 | Q37: ='Formular 4 step Y1'!L416 -> 184 | R37: ='Formular 4 step Y1'!M413 -> 173 | S37: ='Formular 4 step Y1'!M414 -> 174 | T37: ='Formular 4 step Y1'!M415 -> 179 | U37: ='Formular 4 step Y1'!M416 -> 184
A38: เซิฟบอร์ด ขนาด 45 ซม. | B38: ='Formular 4 step Y1'!I438 -> 238 | C38: ='Formular 4 step Y1'!I439 -> 240 | D38: ='Formular 4 step Y1'!I440 -> 242 | E38: ='Formular 4 step Y1'!I441 -> 244 | F38: ='Formular 4 step Y1'!J438 -> 238 | G38: ='Formular 4 step Y1'!J439 -> 240 | H38: ='Formular 4 step Y1'!J440 -> 242 | I38: ='Formular 4 step Y1'!J441 -> 244 | J38: ='Formular 4 step Y1'!K438 -> 238 | K38: ='Formular 4 step Y1'!K439 -> 240 | L38: ='Formular 4 step Y1'!K440 -> 242 | M38: ='Formular 4 step Y1'!K441 -> 244 | N38: ='Formular 4 step Y1'!L438 -> 238 | O38: ='Formular 4 step Y1'!L439 -> 240 | P38: ='Formular 4 step Y1'!L440 -> 242 | Q38: ='Formular 4 step Y1'!L441 -> 244 | R38: ='Formular 4 step Y1'!M438 -> 238 | S38: ='Formular 4 step Y1'!M439 -> 240 | T38: ='Formular 4 step Y1'!M440 -> 242 | U38: ='Formular 4 step Y1'!M441 -> 244
A39: เซิฟบอร์ด ขนาด 60 ซม. | B39: ='Formular 4 step Y1'!I463 -> 293 | C39: ='Formular 4 step Y1'!I464 -> 295 | D39: ='Formular 4 step Y1'!I465 -> 297 | E39: ='Formular 4 step Y1'!I466 -> 299 | F39: ='Formular 4 step Y1'!J463 -> 293 | G39: ='Formular 4 step Y1'!J464 -> 295 | H39: ='Formular 4 step Y1'!J465 -> 297 | I39: ='Formular 4 step Y1'!J466 -> 299 | J39: ='Formular 4 step Y1'!K463 -> 293 | K39: ='Formular 4 step Y1'!K464 -> 295 | L39: ='Formular 4 step Y1'!K465 -> 297 | M39: ='Formular 4 step Y1'!K466 -> 299 | N39: ='Formular 4 step Y1'!L463 -> 293 | O39: ='Formular 4 step Y1'!L464 -> 295 | P39: ='Formular 4 step Y1'!L465 -> 297 | Q39: ='Formular 4 step Y1'!L466 -> 299 | R39: ='Formular 4 step Y1'!M463 -> 293 | S39: ='Formular 4 step Y1'!M464 -> 295 | T39: ='Formular 4 step Y1'!M465 -> 297 | U39: ='Formular 4 step Y1'!M466 -> 299
A40: เซิฟบอร์ด ขนาด 60*120 ซม. | B40: ='Formular 4 step Y1'!I488 -> 706 | C40: ='Formular 4 step Y1'!I489 -> 708 | D40: ='Formular 4 step Y1'!I490 -> 713 | E40: ='Formular 4 step Y1'!I491 -> 718 | F40: ='Formular 4 step Y1'!J488 -> 706 | G40: ='Formular 4 step Y1'!J489 -> 708 | H40: ='Formular 4 step Y1'!J490 -> 713 | I40: ='Formular 4 step Y1'!J491 -> 718 | J40: ='Formular 4 step Y1'!K488 -> 706 | K40: ='Formular 4 step Y1'!K489 -> 708 | L40: ='Formular 4 step Y1'!K490 -> 713 | M40: ='Formular 4 step Y1'!K491 -> 718 | N40: ='Formular 4 step Y1'!L488 -> 706 | O40: ='Formular 4 step Y1'!L489 -> 708 | P40: ='Formular 4 step Y1'!L490 -> 713 | Q40: ='Formular 4 step Y1'!L491 -> 718 | R40: ='Formular 4 step Y1'!M488 -> 706 | S40: ='Formular 4 step Y1'!M489 -> 708 | T40: ='Formular 4 step Y1'!M490 -> 713 | U40: ='Formular 4 step Y1'!M491 -> 718
A41: เซิฟบอร์ด ขนาด 30 ซม. ทนชื้น | B41: ='Formular 4 step Y1'!I513 -> 236 | C41: ='Formular 4 step Y1'!I514 -> 238 | D41: ='Formular 4 step Y1'!I515 -> 241 | E41: ='Formular 4 step Y1'!I516 -> 243 | F41: ='Formular 4 step Y1'!J513 -> 236 | G41: ='Formular 4 step Y1'!J514 -> 238 | H41: ='Formular 4 step Y1'!J515 -> 241 | I41: ='Formular 4 step Y1'!J516 -> 243 | J41: ='Formular 4 step Y1'!K513 -> 236 | K41: ='Formular 4 step Y1'!K514 -> 238 | L41: ='Formular 4 step Y1'!K515 -> 241 | M41: ='Formular 4 step Y1'!K516 -> 243 | N41: ='Formular 4 step Y1'!L513 -> 236 | O41: ='Formular 4 step Y1'!L514 -> 238 | P41: ='Formular 4 step Y1'!L515 -> 241 | Q41: ='Formular 4 step Y1'!L516 -> 243 | R41: ='Formular 4 step Y1'!M513 -> 236 | S41: ='Formular 4 step Y1'!M514 -> 238 | T41: ='Formular 4 step Y1'!M515 -> 241 | U41: ='Formular 4 step Y1'!M516 -> 243
A42: เซิฟบอร์ด ขนาด 45 ซม. ทนชื้น | B42: ='Formular 4 step Y1'!I538 -> 295 | C42: ='Formular 4 step Y1'!I539 -> 297 | D42: ='Formular 4 step Y1'!I540 -> 300 | E42: ='Formular 4 step Y1'!I541 -> 302 | F42: ='Formular 4 step Y1'!J538 -> 295 | G42: ='Formular 4 step Y1'!J539 -> 297 | H42: ='Formular 4 step Y1'!J540 -> 300 | I42: ='Formular 4 step Y1'!J541 -> 302 | J42: ='Formular 4 step Y1'!K538 -> 295 | K42: ='Formular 4 step Y1'!K539 -> 297 | L42: ='Formular 4 step Y1'!K540 -> 300 | M42: ='Formular 4 step Y1'!K541 -> 302 | N42: ='Formular 4 step Y1'!L538 -> 295 | O42: ='Formular 4 step Y1'!L539 -> 297 | P42: ='Formular 4 step Y1'!L540 -> 300 | Q42: ='Formular 4 step Y1'!L541 -> 302 | R42: ='Formular 4 step Y1'!M538 -> 295 | S42: ='Formular 4 step Y1'!M539 -> 297 | T42: ='Formular 4 step Y1'!M540 -> 300 | U42: ='Formular 4 step Y1'!M541 -> 302
A43: เซิฟบอร์ด ขนาด 60 ซม. ทนชื้น | B43: ='Formular 4 step Y1'!I563 -> 353 | C43: ='Formular 4 step Y1'!I564 -> 355 | D43: ='Formular 4 step Y1'!I565 -> 357 | E43: ='Formular 4 step Y1'!I566 -> 359 | F43: ='Formular 4 step Y1'!J563 -> 353 | G43: ='Formular 4 step Y1'!J564 -> 355 | H43: ='Formular 4 step Y1'!J565 -> 357 | I43: ='Formular 4 step Y1'!J566 -> 359 | J43: ='Formular 4 step Y1'!K563 -> 353 | K43: ='Formular 4 step Y1'!K564 -> 355 | L43: ='Formular 4 step Y1'!K565 -> 357 | M43: ='Formular 4 step Y1'!K566 -> 359 | N43: ='Formular 4 step Y1'!L563 -> 353 | O43: ='Formular 4 step Y1'!L564 -> 355 | P43: ='Formular 4 step Y1'!L565 -> 357 | Q43: ='Formular 4 step Y1'!L566 -> 359 | R43: ='Formular 4 step Y1'!M563 -> 353 | S43: ='Formular 4 step Y1'!M564 -> 355 | T43: ='Formular 4 step Y1'!M565 -> 357 | U43: ='Formular 4 step Y1'!M566 -> 359
A44: เซิฟบอร์ด ขนาด 60*120 ซม. ทนชื้น | B44: ='Formular 4 step Y1'!I588 -> 889 | C44: ='Formular 4 step Y1'!I589 -> 899 | D44: ='Formular 4 step Y1'!I590 -> 904 | E44: ='Formular 4 step Y1'!I591 -> 909 | F44: ='Formular 4 step Y1'!J588 -> 889 | G44: ='Formular 4 step Y1'!J589 -> 899 | H44: ='Formular 4 step Y1'!J590 -> 904 | I44: ='Formular 4 step Y1'!J591 -> 909 | J44: ='Formular 4 step Y1'!K588 -> 889 | K44: ='Formular 4 step Y1'!K589 -> 899 | L44: ='Formular 4 step Y1'!K590 -> 904 | M44: ='Formular 4 step Y1'!K591 -> 909 | N44: ='Formular 4 step Y1'!L588 -> 889 | O44: ='Formular 4 step Y1'!L589 -> 899 | P44: ='Formular 4 step Y1'!L590 -> 904 | Q44: ='Formular 4 step Y1'!L591 -> 909 | R44: ='Formular 4 step Y1'!M588 -> 889 | S44: ='Formular 4 step Y1'!M589 -> 899 | T44: ='Formular 4 step Y1'!M590 -> 904 | U44: ='Formular 4 step Y1'!M591 -> 909
A45: อะคูสติก กาแลคซี่ | B45: ='Formular 4 step Y1'!I613 -> 147.32653 | C45: ='Formular 4 step Y1'!I614 -> 148 | D45: ='Formular 4 step Y1'!I615 -> 149 | E45: ='Formular 4 step Y1'!I616 -> 151 | F45: ='Formular 4 step Y1'!J613 -> 147.32653 | G45: ='Formular 4 step Y1'!J614 -> 148 | H45: ='Formular 4 step Y1'!J615 -> 149 | I45: ='Formular 4 step Y1'!J616 -> 151 | J45: ='Formular 4 step Y1'!K613 -> 147.32653 | K45: ='Formular 4 step Y1'!K614 -> 148 | L45: ='Formular 4 step Y1'!K615 -> 149 | M45: ='Formular 4 step Y1'!K616 -> 151 | N45: ='Formular 4 step Y1'!L613 -> 147.32653 | O45: ='Formular 4 step Y1'!L614 -> 148 | P45: ='Formular 4 step Y1'!L615 -> 149 | Q45: ='Formular 4 step Y1'!L616 -> 151 | R45: ='Formular 4 step Y1'!M613 -> 147.32653 | S45: ='Formular 4 step Y1'!M614 -> 148 | T45: ='Formular 4 step Y1'!M615 -> 149 | U45: ='Formular 4 step Y1'!M616 -> 151
A46: อะคูสติก-อิมเพรสชันME903 | B46: ='Formular 4 step Y1'!I638 -> 96 | C46: ='Formular 4 step Y1'!I639 -> 98 | D46: ='Formular 4 step Y1'!I640 -> 99 | E46: ='Formular 4 step Y1'!I641 -> 100 | F46: ='Formular 4 step Y1'!J638 -> 96 | G46: ='Formular 4 step Y1'!J639 -> 98 | H46: ='Formular 4 step Y1'!J640 -> 99 | I46: ='Formular 4 step Y1'!J641 -> 100 | J46: ='Formular 4 step Y1'!K638 -> 96 | K46: ='Formular 4 step Y1'!K639 -> 98 | L46: ='Formular 4 step Y1'!K640 -> 99 | M46: ='Formular 4 step Y1'!K641 -> 100 | N46: ='Formular 4 step Y1'!L638 -> 96 | O46: ='Formular 4 step Y1'!L639 -> 98 | P46: ='Formular 4 step Y1'!L640 -> 99 | Q46: ='Formular 4 step Y1'!L641 -> 100 | R46: ='Formular 4 step Y1'!M638 -> 96 | S46: ='Formular 4 step Y1'!M639 -> 98 | T46: ='Formular 4 step Y1'!M640 -> 99 | U46: ='Formular 4 step Y1'!M641 -> 100
A47: อะคูสติก-อิมเพรสชันME904 | B47: ='Formular 4 step Y1'!I663 -> 182 | C47: ='Formular 4 step Y1'!I664 -> 183 | D47: ='Formular 4 step Y1'!I665 -> 185 | E47: ='Formular 4 step Y1'!I666 -> 187 | F47: ='Formular 4 step Y1'!J663 -> 182 | G47: ='Formular 4 step Y1'!J664 -> 183 | H47: ='Formular 4 step Y1'!J665 -> 185 | I47: ='Formular 4 step Y1'!J666 -> 187 | J47: ='Formular 4 step Y1'!K663 -> 182 | K47: ='Formular 4 step Y1'!K664 -> 183 | L47: ='Formular 4 step Y1'!K665 -> 185 | M47: ='Formular 4 step Y1'!K666 -> 187 | N47: ='Formular 4 step Y1'!L663 -> 182 | O47: ='Formular 4 step Y1'!L664 -> 183 | P47: ='Formular 4 step Y1'!L665 -> 185 | Q47: ='Formular 4 step Y1'!L666 -> 187 | R47: ='Formular 4 step Y1'!M663 -> 182 | S47: ='Formular 4 step Y1'!M664 -> 183 | T47: ='Formular 4 step Y1'!M665 -> 185 | U47: ='Formular 4 step Y1'!M666 -> 187
A48: อะคูสติก-อิมเพรสชันME905 | B48: ='Formular 4 step Y1'!I688 -> 138 | C48: ='Formular 4 step Y1'!I689 -> 140 | D48: ='Formular 4 step Y1'!I690 -> 142 | E48: ='Formular 4 step Y1'!I691 -> 145 | F48: ='Formular 4 step Y1'!J688 -> 138 | G48: ='Formular 4 step Y1'!J689 -> 140 | H48: ='Formular 4 step Y1'!J690 -> 142 | I48: ='Formular 4 step Y1'!J691 -> 145 | J48: ='Formular 4 step Y1'!K688 -> 138 | K48: ='Formular 4 step Y1'!K689 -> 140 | L48: ='Formular 4 step Y1'!K690 -> 142 | M48: ='Formular 4 step Y1'!K691 -> 145 | N48: ='Formular 4 step Y1'!L688 -> 138 | O48: ='Formular 4 step Y1'!L689 -> 140 | P48: ='Formular 4 step Y1'!L690 -> 142 | Q48: ='Formular 4 step Y1'!L691 -> 145 | R48: ='Formular 4 step Y1'!M687 -> 160.5 | S48: ='Formular 4 step Y1'!M688 -> 138 | T48: ='Formular 4 step Y1'!M689 -> 140 | U48: ='Formular 4 step Y1'!M690 -> 142
A49: อะคูสติก-อิมเพรสชันME908 | B49: ='Formular 4 step Y1'!I714 -> 265 | C49: ='Formular 4 step Y1'!I715 -> 266 | D49: ='Formular 4 step Y1'!I716 -> 267 | E49: ='Formular 4 step Y1'!#REF! -> #REF! | F49: ='Formular 4 step Y1'!J713 -> 264 | G49: ='Formular 4 step Y1'!J714 -> 265 | H49: ='Formular 4 step Y1'!J715 -> 266 | I49: ='Formular 4 step Y1'!J716 -> 267 | J49: ='Formular 4 step Y1'!K713 -> 264 | K49: ='Formular 4 step Y1'!K714 -> 265 | L49: ='Formular 4 step Y1'!K715 -> 266 | M49: ='Formular 4 step Y1'!K716 -> 267 | N49: ='Formular 4 step Y1'!L713 -> 264 | O49: ='Formular 4 step Y1'!L714 -> 265 | P49: ='Formular 4 step Y1'!L715 -> 266 | Q49: ='Formular 4 step Y1'!L716 -> 267 | R49: ='Formular 4 step Y1'!M713 -> 264 | S49: ='Formular 4 step Y1'!M714 -> 265 | T49: ='Formular 4 step Y1'!M715 -> 266 | U49: ='Formular 4 step Y1'!M716 -> 267
A54: NE | D54: KK | H54: SK | L54: UD | P54: UB | T54: NR
A55: Y1 : Smart Board | C55: WIP | D55: WIPR | E55: WIPRSO | G55: WIP | H55: WIPR | I55: WIPRSO | K55: WIP | L55: WIPR | M55: WIPRSO | O55: WIP | P55: WIPR | Q55: WIPRSO | S55: WIP | T55: WIPR | U55: WIPRSO
B56: W1 | C56: W2 | D56: R1 | E56: R2 | F56: W1 | G56: W2 | H56: R1 | I56: R2 | J56: W1 | K56: W2 | L56: R1 | M56: R2 | N56: W1 | O56: W2 | P56: R1 | Q56: R2 | R56: W1 | S56: W2 | T56: R1 | U56: R2
A57: SB 120x240 4 mm ตราช้าง | B57: ='สูตร 4 step SB'!I13 -> 158 | C57: ='สูตร 4 step SB'!I14 -> 161 | D57: ='สูตร 4 step SB'!I15 -> 163 | E57: ='สูตร 4 step SB'!I16 -> 165 | F57: ='สูตร 4 step SB'!J13 -> 163 | G57: ='สูตร 4 step SB'!J14 -> 166 | H57: ='สูตร 4 step SB'!J15 -> 168 | I57: ='สูตร 4 step SB'!J16 -> 170 | J57: ='สูตร 4 step SB'!K13 -> 161 | K57: ='สูตร 4 step SB'!K14 -> 164 | L57: ='สูตร 4 step SB'!K15 -> 166 | M57: ='สูตร 4 step SB'!K16 -> 168 | N57: ='สูตร 4 step SB'!L13 -> 163 | O57: ='สูตร 4 step SB'!L14 -> 166 | P57: ='สูตร 4 step SB'!L15 -> 168 | Q57: ='สูตร 4 step SB'!L16 -> 170 | R57: ='สูตร 4 step SB'!M13 -> 156 | S57: ='สูตร 4 step SB'!M14 -> 159 | T57: ='สูตร 4 step SB'!M15 -> 161 | U57: ='สูตร 4 step SB'!M16 -> 163
A58: SB 120x120 4 mm ตราช้าง | B58: ='สูตร 4 step SB'!I41 -> 80 | C58: ='สูตร 4 step SB'!I42 -> 82 | D58: ='สูตร 4 step SB'!I43 -> 83 | E58: ='สูตร 4 step SB'!I44 -> 84 | F58: ='สูตร 4 step SB'!J41 -> 83 | G58: ='สูตร 4 step SB'!J42 -> 85 | H58: ='สูตร 4 step SB'!J43 -> 86 | I58: ='สูตร 4 step SB'!J44 -> 87 | J58: ='สูตร 4 step SB'!K41 -> 82 | K58: ='สูตร 4 step SB'!K42 -> 84 | L58: ='สูตร 4 step SB'!K43 -> 85 | M58: ='สูตร 4 step SB'!K44 -> 86 | N58: ='สูตร 4 step SB'!L41 -> 83 | O58: ='สูตร 4 step SB'!L42 -> 85 | P58: ='สูตร 4 step SB'!L43 -> 86 | Q58: ='สูตร 4 step SB'!L44 -> 87 | R58: ='สูตร 4 step SB'!M41 -> 79 | S58: ='สูตร 4 step SB'!M42 -> 81 | T58: ='สูตร 4 step SB'!M43 -> 82 | U58: ='สูตร 4 step SB'!M44 -> 83
A59: SB 60x240 4 mm ตราช้าง | B59: ='สูตร 4 step SB'!I68 -> 79 | C59: ='สูตร 4 step SB'!I69 -> 81 | D59: ='สูตร 4 step SB'!I70 -> 82 | E59: ='สูตร 4 step SB'!I71 -> 84 | F59: ='สูตร 4 step SB'!J68 -> 82 | G59: ='สูตร 4 step SB'!J69 -> 84 | H59: ='สูตร 4 step SB'!J70 -> 85 | I59: ='สูตร 4 step SB'!J71 -> 87 | J59: ='สูตร 4 step SB'!K68 -> 81 | K59: ='สูตร 4 step SB'!K69 -> 83 | L59: ='สูตร 4 step SB'!K70 -> 84 | M59: ='สูตร 4 step SB'!K71 -> 86 | N59: ='สูตร 4 step SB'!L68 -> 82 | O59: ='สูตร 4 step SB'!L69 -> 84 | P59: ='สูตร 4 step SB'!L70 -> 85 | Q59: ='สูตร 4 step SB'!L71 -> 87 | R59: ='สูตร 4 step SB'!M68 -> 78 | S59: ='สูตร 4 step SB'!M69 -> 80 | T59: ='สูตร 4 step SB'!M70 -> 81 | U59: ='สูตร 4 step SB'!M71 -> 83
A60: SB 60x120 4 mm ตราช้าง | B60: ='สูตร 4 step SB'!I344 -> 44 | C60: ='สูตร 4 step SB'!I345 -> 45 | D60: ='สูตร 4 step SB'!I346 -> 46 | E60: ='สูตร 4 step SB'!I347 -> 47 | F60: ='สูตร 4 step SB'!J344 -> 45 | G60: ='สูตร 4 step SB'!J345 -> 46 | H60: ='สูตร 4 step SB'!J346 -> 47 | I60: ='สูตร 4 step SB'!J347 -> 48 | J60: ='สูตร 4 step SB'!K344 -> 44 | K60: ='สูตร 4 step SB'!K345 -> 45 | L60: ='สูตร 4 step SB'!K346 -> 46 | M60: ='สูตร 4 step SB'!K347 -> 47 | N60: ='สูตร 4 step SB'!L344 -> 45 | O60: ='สูตร 4 step SB'!L345 -> 46 | P60: ='สูตร 4 step SB'!L346 -> 47 | Q60: ='สูตร 4 step SB'!L347 -> 48 | R60: ='สูตร 4 step SB'!M344 -> 43 | S60: ='สูตร 4 step SB'!M345 -> 44 | T60: ='สูตร 4 step SB'!M346 -> 45 | U60: ='สูตร 4 step SB'!M347 -> 46
A61: SB 120x240 6 mm ตราช้าง | B61: ='สูตร 4 step SB'!I96 -> 240 | C61: ='สูตร 4 step SB'!I97 -> 244 | D61: ='สูตร 4 step SB'!I98 -> 246 | E61: ='สูตร 4 step SB'!I99 -> 248 | F61: ='สูตร 4 step SB'!J96 -> 247 | G61: ='สูตร 4 step SB'!J97 -> 251 | H61: ='สูตร 4 step SB'!J98 -> 253 | I61: ='สูตร 4 step SB'!J99 -> 255 | J61: ='สูตร 4 step SB'!K96 -> 244 | K61: ='สูตร 4 step SB'!K97 -> 248 | L61: ='สูตร 4 step SB'!K98 -> 250 | M61: ='สูตร 4 step SB'!K99 -> 252 | N61: ='สูตร 4 step SB'!L96 -> 247 | O61: ='สูตร 4 step SB'!L97 -> 251 | P61: ='สูตร 4 step SB'!L98 -> 253 | Q61: ='สูตร 4 step SB'!L99 -> 255 | R61: ='สูตร 4 step SB'!M96 -> 236 | S61: ='สูตร 4 step SB'!M97 -> 240 | T61: ='สูตร 4 step SB'!M98 -> 242 | U61: ='สูตร 4 step SB'!M99 -> 244
A62: SB 120x240 8 mm ตราช้าง | B62: ='สูตร 4 step SB'!I124 -> 335 | C62: ='สูตร 4 step SB'!I125 -> 340 | D62: ='สูตร 4 step SB'!I126 -> 345 | E62: ='สูตร 4 step SB'!I127 -> 349 | F62: ='สูตร 4 step SB'!J124 -> 345 | G62: ='สูตร 4 step SB'!J125 -> 350 | H62: ='สูตร 4 step SB'!J126 -> 355 | I62: ='สูตร 4 step SB'!J127 -> 359 | J62: ='สูตร 4 step SB'!K124 -> 340 | K62: ='สูตร 4 step SB'!K125 -> 345 | L62: ='สูตร 4 step SB'!K126 -> 350 | M62: ='สูตร 4 step SB'!K127 -> 354 | N62: ='สูตร 4 step SB'!L124 -> 344 | O62: ='สูตร 4 step SB'!L125 -> 349 | P62: ='สูตร 4 step SB'!L126 -> 354 | Q62: ='สูตร 4 step SB'!L127 -> 358 | R62: ='สูตร 4 step SB'!M124 -> 330 | S62: ='สูตร 4 step SB'!M125 -> 335 | T62: ='สูตร 4 step SB'!M126 -> 340 | U62: ='สูตร 4 step SB'!M127 -> 344
A63: SB 120x240 10 mm ตราช้าง | B63: ='สูตร 4 step SB'!I152 -> 479 | C63: ='สูตร 4 step SB'!I153 -> 484 | D63: ='สูตร 4 step SB'!I154 -> 489 | E63: ='สูตร 4 step SB'!I155 -> 494 | F63: ='สูตร 4 step SB'!J152 -> 491 | G63: ='สูตร 4 step SB'!J153 -> 496 | H63: ='สูตร 4 step SB'!J154 -> 501 | I63: ='สูตร 4 step SB'!J155 -> 506 | J63: ='สูตร 4 step SB'!K152 -> 485 | K63: ='สูตร 4 step SB'!K153 -> 490 | L63: ='สูตร 4 step SB'!K154 -> 495 | M63: ='สูตร 4 step SB'!K155 -> 500 | N63: ='สูตร 4 step SB'!L152 -> 490 | O63: ='สูตร 4 step SB'!L153 -> 495 | P63: ='สูตร 4 step SB'!L154 -> 500 | Q63: ='สูตร 4 step SB'!L155 -> 505 | R63: ='สูตร 4 step SB'!M152 -> 473 | S63: ='สูตร 4 step SB'!M153 -> 478 | T63: ='สูตร 4 step SB'!M154 -> 483 | U63: ='สูตร 4 step SB'!M155 -> 488
A64: SB 120x240 12 mm ตราช้าง | B64: ='สูตร 4 step SB'!I179 -> 581 | C64: ='สูตร 4 step SB'!I180 -> 586 | D64: ='สูตร 4 step SB'!I181 -> 591 | E64: ='สูตร 4 step SB'!I182 -> 596 | F64: ='สูตร 4 step SB'!J179 -> 596 | G64: ='สูตร 4 step SB'!J180 -> 601 | H64: ='สูตร 4 step SB'!J181 -> 606 | I64: ='สูตร 4 step SB'!J182 -> 611 | J64: ='สูตร 4 step SB'!K179 -> 588 | K64: ='สูตร 4 step SB'!K180 -> 593 | L64: ='สูตร 4 step SB'!K181 -> 598 | M64: ='สูตร 4 step SB'!K182 -> 603 | N64: ='สูตร 4 step SB'!L179 -> 594 | O64: ='สูตร 4 step SB'!L180 -> 599 | P64: ='สูตร 4 step SB'!L181 -> 604 | Q64: ='สูตร 4 step SB'!L182 -> 609 | R64: ='สูตร 4 step SB'!M179 -> 574 | S64: ='สูตร 4 step SB'!M180 -> 579 | T64: ='สูตร 4 step SB'!M181 -> 584 | U64: ='สูตร 4 step SB'!M182 -> 589
A65: SB 120x240 15 mm ตราช้าง | B65: ='สูตร 4 step SB'!I645 -> 667 | C65: ='สูตร 4 step SB'!I646 -> 677 | D65: ='สูตร 4 step SB'!I647 -> 687 | E65: ='สูตร 4 step SB'!I648 -> 692 | F65: ='สูตร 4 step SB'!J645 -> 686 | G65: ='สูตร 4 step SB'!J646 -> 696 | H65: ='สูตร 4 step SB'!J647 -> 706 | I65: ='สูตร 4 step SB'!J648 -> 711 | J65: ='สูตร 4 step SB'!K645 -> 676 | K65: ='สูตร 4 step SB'!K646 -> 686 | L65: ='สูตร 4 step SB'!K647 -> 696 | M65: ='สูตร 4 step SB'!K648 -> 701 | N65: ='สูตร 4 step SB'!L645 -> 684 | O65: ='สูตร 4 step SB'!L646 -> 694 | P65: ='สูตร 4 step SB'!L647 -> 704 | Q65: ='สูตร 4 step SB'!L648 -> 709 | R65: ='สูตร 4 step SB'!M645 -> 658 | S65: ='สูตร 4 step SB'!M646 -> 668 | T65: ='สูตร 4 step SB'!M647 -> 678 | U65: ='สูตร 4 step SB'!M648 -> 683
A66: SB 120x240 16 mm ตราช้าง | B66: ='สูตร 4 step SB'!I672 -> 706 | C66: ='สูตร 4 step SB'!I673 -> 716 | D66: ='สูตร 4 step SB'!I674 -> 726 | E66: ='สูตร 4 step SB'!I675 -> 736 | F66: ='สูตร 4 step SB'!J672 -> 726 | G66: ='สูตร 4 step SB'!J673 -> 736 | H66: ='สูตร 4 step SB'!J674 -> 746 | I66: ='สูตร 4 step SB'!J675 -> 756 | J66: ='สูตร 4 step SB'!K672 -> 716 | K66: ='สูตร 4 step SB'!K673 -> 726 | L66: ='สูตร 4 step SB'!K674 -> 736 | M66: ='สูตร 4 step SB'!K675 -> 746 | N66: ='สูตร 4 step SB'!L672 -> 724 | O66: ='สูตร 4 step SB'!L673 -> 734 | P66: ='สูตร 4 step SB'!L674 -> 744 | Q66: ='สูตร 4 step SB'!L675 -> 754 | R66: ='สูตร 4 step SB'!M672 -> 696 | S66: ='สูตร 4 step SB'!M673 -> 706 | T66: ='สูตร 4 step SB'!M674 -> 716 | U66: ='สูตร 4 step SB'!M675 -> 726
A67: SB 120x240 18 mm ตราช้าง | B67: ='สูตร 4 step SB'!I699 -> 797 | C67: ='สูตร 4 step SB'!I700 -> 807 | D67: ='สูตร 4 step SB'!I701 -> 827 | E67: ='สูตร 4 step SB'!I702 -> 837 | F67: ='สูตร 4 step SB'!J699 -> 819 | G67: ='สูตร 4 step SB'!J700 -> 829 | H67: ='สูตร 4 step SB'!J701 -> 849 | I67: ='สูตร 4 step SB'!J702 -> 859 | J67: ='สูตร 4 step SB'!K699 -> 808 | K67: ='สูตร 4 step SB'!K700 -> 818 | L67: ='สูตร 4 step SB'!K701 -> 838 | M67: ='สูตร 4 step SB'!K702 -> 848 | N67: ='สูตร 4 step SB'!L699 -> 817 | O67: ='สูตร 4 step SB'!L700 -> 827 | P67: ='สูตร 4 step SB'!L701 -> 847 | Q67: ='สูตร 4 step SB'!L702 -> 857 | R67: ='สูตร 4 step SB'!M699 -> 785 | S67: ='สูตร 4 step SB'!M700 -> 795 | T67: ='สูตร 4 step SB'!M701 -> 815 | U67: ='สูตร 4 step SB'!M702 -> 825
A68: SB 120x240 20 mm ตราช้าง | B68: ='สูตร 4 step SB'!I726 -> 893 | C68: ='สูตร 4 step SB'!I727 -> 903 | D68: ='สูตร 4 step SB'!I728 -> 918 | E68: ='สูตร 4 step SB'!I729 -> 933 | F68: ='สูตร 4 step SB'!J726 -> 917 | G68: ='สูตร 4 step SB'!J727 -> 927 | H68: ='สูตร 4 step SB'!J728 -> 942 | I68: ='สูตร 4 step SB'!J729 -> 957 | J68: ='สูตร 4 step SB'!K726 -> 905 | K68: ='สูตร 4 step SB'!K727 -> 915 | L68: ='สูตร 4 step SB'!K728 -> 930 | M68: ='สูตร 4 step SB'!K729 -> 945 | N68: ='สูตร 4 step SB'!L726 -> 915 | O68: ='สูตร 4 step SB'!L727 -> 925 | P68: ='สูตร 4 step SB'!L728 -> 940 | Q68: ='สูตร 4 step SB'!L729 -> 955 | R68: ='สูตร 4 step SB'!M726 -> 880 | S68: ='สูตร 4 step SB'!M727 -> 890 | T68: ='สูตร 4 step SB'!M728 -> 905 | U68: ='สูตร 4 step SB'!M729 -> 920
A69: SB 120x280 8 mm ตราช้าง | B69: ='สูตร 4 step SB'!I206 -> 430 | C69: ='สูตร 4 step SB'!I207 -> 435 | D69: ='สูตร 4 step SB'!I208 -> 440 | E69: ='สูตร 4 step SB'!I209 -> 445 | F69: ='สูตร 4 step SB'!J206 -> 441 | G69: ='สูตร 4 step SB'!J207 -> 446 | H69: ='สูตร 4 step SB'!J208 -> 451 | I69: ='สูตร 4 step SB'!J209 -> 456 | J69: ='สูตร 4 step SB'!K206 -> 435 | K69: ='สูตร 4 step SB'!K207 -> 440 | L69: ='สูตร 4 step SB'!K208 -> 445 | M69: ='สูตร 4 step SB'!K209 -> 450 | N69: ='สูตร 4 step SB'!L206 -> 440 | O69: ='สูตร 4 step SB'!L207 -> 445 | P69: ='สูตร 4 step SB'!L208 -> 450 | Q69: ='สูตร 4 step SB'!L209 -> 455 | R69: ='สูตร 4 step SB'!M206 -> 424 | S69: ='สูตร 4 step SB'!M207 -> 429 | T69: ='สูตร 4 step SB'!M208 -> 434 | U69: ='สูตร 4 step SB'!M209 -> 439
A70: ลายไม้/เซาะร่อง ตราช้าง | B70: ='สูตร 4 step SB'!I234 -> 53 | C70: ='สูตร 4 step SB'!I235 -> 54 | D70: ='สูตร 4 step SB'!I236 -> 55 | E70: ='สูตร 4 step SB'!I237 -> 56 | F70: ='สูตร 4 step SB'!J234 -> 55 | G70: ='สูตร 4 step SB'!J235 -> 56 | H70: ='สูตร 4 step SB'!J236 -> 57 | I70: ='สูตร 4 step SB'!J237 -> 58 | J70: ='สูตร 4 step SB'!K234 -> 54 | K70: ='สูตร 4 step SB'!K235 -> 55 | L70: ='สูตร 4 step SB'!K236 -> 56 | M70: ='สูตร 4 step SB'!K237 -> 57 | N70: ='สูตร 4 step SB'!L234 -> 55 | O70: ='สูตร 4 step SB'!L235 -> 56 | P70: ='สูตร 4 step SB'!L236 -> 57 | Q70: ='สูตร 4 step SB'!L237 -> 58 | R70: ='สูตร 4 step SB'!M234 -> 53 | S70: ='สูตร 4 step SB'!M235 -> 54 | T70: ='สูตร 4 step SB'!M236 -> 55 | U70: ='สูตร 4 step SB'!M237 -> 56
A71: ระบายอากาศ ตราช้าง | B71: ='สูตร 4 step SB'!I262 -> 49 | C71: ='สูตร 4 step SB'!I263 -> 50 | D71: ='สูตร 4 step SB'!I264 -> 51 | E71: ='สูตร 4 step SB'!I265 -> 52 | F71: ='สูตร 4 step SB'!J262 -> 51 | G71: ='สูตร 4 step SB'!J263 -> 52 | H71: ='สูตร 4 step SB'!J264 -> 53 | I71: ='สูตร 4 step SB'!J265 -> 54 | J71: ='สูตร 4 step SB'!K262 -> 50 | K71: ='สูตร 4 step SB'!K263 -> 51 | L71: ='สูตร 4 step SB'!K264 -> 52 | M71: ='สูตร 4 step SB'!K265 -> 53 | N71: ='สูตร 4 step SB'!L262 -> 50 | O71: ='สูตร 4 step SB'!L263 -> 51 | P71: ='สูตร 4 step SB'!L264 -> 52 | Q71: ='สูตร 4 step SB'!L265 -> 53 | R71: ='สูตร 4 step SB'!M262 -> 49 | S71: ='สูตร 4 step SB'!M263 -> 50 | T71: ='สูตร 4 step SB'!M264 -> 51 | U71: ='สูตร 4 step SB'!M265 -> 52
A72: ระบายอากาศโพรเทคชั่น ตราช้าง | B72: ='สูตร 4 step SB'!I618 -> 69 | C72: ='สูตร 4 step SB'!I619 -> 70 | D72: ='สูตร 4 step SB'!I620 -> 71 | E72: ='สูตร 4 step SB'!I621 -> 72 | F72: ='สูตร 4 step SB'!J618 -> 70 | G72: ='สูตร 4 step SB'!J619 -> 71 | H72: ='สูตร 4 step SB'!J620 -> 72 | I72: ='สูตร 4 step SB'!J621 -> 73 | J72: ='สูตร 4 step SB'!K618 -> 70 | K72: ='สูตร 4 step SB'!K619 -> 71 | L72: ='สูตร 4 step SB'!K620 -> 72 | M72: ='สูตร 4 step SB'!K621 -> 73 | N72: ='สูตร 4 step SB'!L618 -> 70 | O72: ='สูตร 4 step SB'!L619 -> 71 | P72: ='สูตร 4 step SB'!L620 -> 72 | Q72: ='สูตร 4 step SB'!L621 -> 73 | R72: ='สูตร 4 step SB'!M618 -> 68 | S72: ='สูตร 4 step SB'!M619 -> 69 | T72: ='สูตร 4 step SB'!M620 -> 70 | U72: ='สูตร 4 step SB'!M621 -> 71
A73: ลายไม้ ระบายอากาศ /เซาะร่อง ระบายอากาศ ตราช้าง | B73: ='สูตร 4 step SB'!I290 -> 57 | C73: ='สูตร 4 step SB'!I291 -> 58 | D73: ='สูตร 4 step SB'!I292 -> 59 | E73: ='สูตร 4 step SB'!I293 -> 60 | F73: ='สูตร 4 step SB'!J290 -> 58 | G73: ='สูตร 4 step SB'!J291 -> 59 | H73: ='สูตร 4 step SB'!J292 -> 60 | I73: ='สูตร 4 step SB'!J293 -> 61 | J73: ='สูตร 4 step SB'!K290 -> 57 | K73: ='สูตร 4 step SB'!K291 -> 58 | L73: ='สูตร 4 step SB'!K292 -> 59 | M73: ='สูตร 4 step SB'!K293 -> 60 | N73: ='สูตร 4 step SB'!L290 -> 58 | O73: ='สูตร 4 step SB'!L291 -> 59 | P73: ='สูตร 4 step SB'!L292 -> 60 | Q73: ='สูตร 4 step SB'!L293 -> 61 | R73: ='สูตร 4 step SB'!M290 -> 56 | S73: ='สูตร 4 step SB'!M291 -> 57 | T73: ='สูตร 4 step SB'!M292 -> 58 | U73: ='สูตร 4 step SB'!M293 -> 59
